Workbook
Name allowance: 'Charge-offs and Recoveries'!$C$27
Name CASHDIVCOM: 'Changes in Equity'!$B$12
Name CASHDIVPREF: 'Changes in Equity'!$B$11
Name RISKTOTASS: SUM('Calculation of Risk Weighted As'!$C$47:$F$47)
Name TOTASS: 'Bank Assets Analysis'!$H$39
Name TOTEQT: 'Changes in Equity'!$B$14
Name TOTLIAB: 'Bank Liabilities Analysis'!$H$35

Sheet Balance
A1: #FN1{101,100,223}
A2: БАЛАНСОВЫЙ ОТЧЕТ КОММЕРЧЕСКОГО БАНКА | C2: Таблица-1(Форма-0110BS)
A3: #FN1{10}
A4: #FNP{date_end}
A5: АКТИВЫ | B5: в тыс.сум
A7: 1. Кассовая наличность и другие платежные документы | C7: #FN1{101}
A8: 2. К получению из ЦБРУ | C8: -#FN1A{103,16103}
A9: 3. К получению из других банков | C9: #FN1{105}
A10: 4. Счета купли и продажи
A11: а. Ценные бумаги | B11: #FN1{10701-10795,10801-10895}
A12: б. Драгоценные металлы, монеты, камни | B12: #FN1{10901-10909}
A13: в. Минус: Резерв возможных убытков по счетам купли-продажи | B13: #FN1{10799,10899,10999}
A14: г. Счета купли-продажи, чистые | C14: =B11+B12-B13 -> #VALUE!
A15: 5 а. Инвестиции | B15: #FN1{15801-15821,15901-15993}
A16: б. Минус: Резерв возможных убытков по инвестициям | B16: #FN1{15899,15999}
A17: в. Инвестиции, чистые | C17: =B15-B16 -> #VALUE!
A18: 6. Ценные бумаги купленные по соглашению c обратным выкупом | C18: #FN1{118}
A19: 7. Ссуды и Лизинговые операции
A20: а. Брутто ссуды | B20: #FN1{1110,11195,1190,1210,1230,1240,1250,1260,1270,1290}+#FN1{1300,1310,1320,1330,1430,14501,14505,14701,14705,14801,14809,14901,14905}+#FN1{15001,15005,15101,15105,15201,15205,15301,15305,15401,15405}+#FN1{15501,15505,15701,15703}
A21: б. Лизинговые операции, Брутто | B21: #FN1{15601-15619,15705}
A22: в. Минус: Резерв возможных убытков по ссудам и лизингу | B22: #FN1{11199,12199,12399,12499,12599,12699,12799,12999}+#FN1{13099,13199,13299,13399,14399,14599,14799,14899,14999}+#FN1{15099,15199,15299,15399,15499,15599,15699,15799}
A23: г. Cсуды и лизинговые операции, чистые | C23: =B20+B21-B22 -> #VALUE!
A24: 8 а. Купленные векселя | B24: #FN1{11301-11395}
A25: б. Минус: Резерв возможных убытков по купленным векселям | B25: #FN1{11399}
A26: в. Купленные векселя, чистые | C26: =B24-B25 -> #VALUE!
A27: 9. Обязательства клиентов по финансовым инструментам | C27: #FN1{115,117}
A28: 10. Основные средства, чистые | C28: #FN1{165,166}
A29: 11. Начисленные проценты к получению | C29: #FN1{163}
A30: 12. Другое собственное имущество банка
A31: а. Инвестиции в недвижимость | B31: #FN1{16709}
A32: б. Другие активы, приобретенные при кредитных расчетах | B32: #FN1{16701,16703,16705,16713}
A33: в. Минус:Резервы на возможные убытки по другому собственному имуществу банка | B33: #FN1{16799}
A34: г. Чистые активы, приобретенные при ссудных расчетах | C34: =B31+B32-B33 -> #VALUE!
A35: 13. Другие активы | C35: =C36-C7-C8-C9-C14-C17-C18-C23-C26-C27-C28-C29-C34 -> #VALUE!
A36: 14. Итого активов | C36: =C78-C80 -> #VALUE!
A37: в том числе 16100 | C37: -#FN1A{161}
A38: ОБЯЗАТЕЛЬСТВА И АКЦИОНЕРНЫЙ КАПИТАЛ
A40: ОБЯЗАТЕЛЬСТВА
A41: 15. Депозиты до востребования | C41: #FN1{202,226}
A42: 16.Сберегательные депозиты | C42: #FN1{204,23604}
A43: 17. Срочные депозиты | C43: #FN1{206,23606}
A44: 18. К оплате в ЦБРУ | C44: #FN1{208}
A45: 19. К оплате в другие банки | C45: #FN1{210,212}
A46: 20. Ценные бумаги проданные по соглашению с последующим выкупом | C46: #FN1{223}
A47: 21. Ссуды к оплате | C47: #FN1{216,220,221,23602,23608,23610}
A48: 22. Субординированные долговые обязательства
A49: 23. Начисленные проценты к оплате | C49: #FN1{224}
A50: 24. Другие обязательства | C50: =C51-C41-C42-C43-C44-C45-C46-C47-C49 -> #VALUE!
A51: 25. Итого обязательств | C51: =C79-C80 -> #VALUE!
A52: в том числе 22200 | C52: #FN1{222}
A53: СОБСТВЕННЫЙ КАПИТАЛ
A54: 26.Уставный капитал | C54: =C55+C56 -> #VALUE!
A55: а. Акции - Обыкновенные | C55: #FN1{30312,30318}-#FN1{30306,30324}
A56: б. Акции - Привилегированные | C56: #FN1{30309,30315}-#FN1{30303,30321}
A57: 27.Добавленный капитал | C57: #FN1{30603}
A58: 28.Резервный капитал | C58: =C59+C61+C62 -> #VALUE!
A59: а. Резервный фонд общего назначения | C59: #FN1{30903}
A60: а.1. Из них, резервы созданные по стандартным активам | C60: ='Loan Classification'!G16 -> 0
A61: б. Резерв на девальвацию | C61: #FN1{30906}
A62: в. Другие резервы и фонды | C62: #FN1{30908,30904,30905,30907,30909,30910}
A63: 29.Нераспределенная прибыль | C63: #FN1{4,5,31203,31206}
A64: 30. Итого собственного капитала | C64: =C54+C57+C58+C63 -> #VALUE!
A65: 31. Итого обязательств и собственного капитала | C65: =C51+C64 -> #VALUE!
A66: Подпись Руководителя:
A67: Подпись Главного Бухгалтера:
B70: Доходы | C70: #FN1{4}
B71: Расходы | C71: #FN1{5}
B72: Капитал | C72: #FN1{3}
B73: 11 | C73: #FN1{1}
B74: Пассивы | C74: #FN1{2}
B75: 16100 | C75: -#FN1A{16101,16102,16104,16105,16107,16109}
B76: 22200 | C76: #FN1{222}
B77: мин 161, 222 | C77: =MIN(C75,C76) -> 0
B78: Активы минус мин{161,222} | C78: =C73-C77 -> #VALUE!
B79: Пассивы минус мин{161,222} | C79: =C74-C77 -> #VALUE!
B80: 175 | C80: #FN1{175}

Sheet Income
B1: Приложение №1 к Рекомендациям по заполнению отчетности коммерческих банков по банковскому надзору представляемых Центральному банку Республики Узбекистан
A2: ОТЧЕТ О ПРИБЫЛЯХ И УБЫТКАХ | B2: Таблица-2 (Форма-0204IS)
A3: #FNP{date_end}
A4: Категории | B4: в тыс. сум
A5: 1. ПРОЦЕНТНЫЕ ДОХОДЫ
A6: a. Процентные доходы по счетам в ЦБРУ | B6: #FN1{402}
A7: б. Процентные доходы по счетам в других банках | B7: #FN1{404}
A8: в. Процентные доходы по купленным векселям | B8: #FN1{408}
A9: г. Процентные доходы по инвестициям | B9: #FN1{448}
A10: д. Процентные доходы по счетам купли-продажи ценных бумаг | B10: #FN1{406,407}
A11: е. Процентные доходы по обязательствам клиентов | B11: #FN1{410}
A12: ж. Процентные доходы по обяз-вам клиентов по непогашенным акцептам этого банка | B12: #FN1{412}
A13: з. Процент, Дисконт {Скидки} и взносы по ссудам и лизинговым операциям | B13: #FN1{414,416,418,419,420,421,422,423,424,425,426}+#FN1{436,437,439,440,441,442,443,444,445,446,447}+#FN1{451}
A14: и. Процентные доходы по соглашениям о покупке ценных бумаг с обратным выкупом | B14: #FN1{450}
A15: к. Другие процентные доходы | B15: #FN1{449}
A16: л. Итого процентных доходов | B16: =SUM(B6:B15) -> 0
A18: 2. ПРОЦЕНТНЫЕ РАСХОДЫ
A19: а. Процентные расходы по депозитам до востребования | B19: #FN1{501}
A20: б. Процентные расходы по сберегательным депозитам | B20: #FN1{506,54204}
A21: в. Процентные расходы по срочным депозитам | B21: #FN1{511,54206}
A22: г. Процентные расходы по счетам к оплате в ЦБРУ | B22: #FN1{516}
A23: д. Процентные расходы по счетам к оплате в другие банки | B23: #FN1{521}
A24: е. Итого процентных расходов по депозитам | B24: =SUM(B19:B23) -> 0
A25: ж. Процентные расходы по ссудам к оплате | B25: #FN1{531,541,54202,54208,54210}
A26: з. Процентные расходы по соглашениям о продаже ц/б с последующим выкупом | B26: #FN1{543}
A27: и. Другие процентные расходы | B27: #FN1{549,526}
A28: к. Итого процентных расходов по займам | B28: =SUM(B25:B27) -> 0
A29: л. Итого процентных расходов | B29: =B28+B24 -> 0
A31: 3. ЧИСТЫЕ ПРОЦЕНТНЫЕ ДОХОДЫ ДО ОЦЕНКИ ВОЗМОЖНЫХ УБЫТКОВ ПО ССУДАМ И ЛИЗИНГУ | B31: =B16-B29 -> 0
A32: а. Минус: Оценка возможных убытков по ссудам и лизингу | B32: #FN1{56802,56803,56814,56838,56842,56895}
A33: б. Чистые процентные доходы после оценки возможных убытков по ссудам и лизингу | B33: =B31-B32 -> #VALUE!
A35: 4. БЕСПРОЦЕНТНЫЕ ДОХОДЫ
A36: а. Доходы от комиссий и платы за услуги | B36: #FN1{452}
A37: б. Прибыль в иностранной валюте | B37: #FN1{454}
A38: в. Прибыль от коммерческих операций | B38: #FN1{456}
A39: г. Прибыль и дивиденды от инвестиций | B39: #FN1{457,458}
A40: д. Другие беспроцентные доходы | B40: #FN1{459}
A41: е. Итого беспроцентных доходов | B41: =SUM(B36:B40) -> 0
A43: 5. БЕСПРОЦЕНТНЫЕ РАСХОДЫ
A44: а. Комиссионные расходы и расходы за услуги | B44: #FN1{551}
A45: б. Убытки в иностранной валюте | B45: #FN1{553}
A46: в. Убытки по счетам купли-продажи | B46: #FN1{556}
A47: г. Убытки от инвестиций | B47: #FN1{557,558}
A48: д. Другие беспроцентные расходы | B48: #FN1{559}
A49: е. Итого беспроцентных расходов | B49: =SUM(B44:B48) -> 0
A51: 6. ЧИСТЫЙ ДОХОД ДО ОПЕРАЦИОННЫХ РАСХОДОВ | B51: =B33+B41-B49 -> #VALUE!
A53: 7. ОПЕРАЦИОННЫЕ РАСХОДЫ
A54: а. Заработная плата и другие расходы на сотрудников | B54: #FN1{561}
A55: б. Аренда и содержание | B55: #FN1{562}
A56: в. Командировочные и транспортные расходы | B56: #FN1{563}
A57: г. Административные расходы | B57: #FN1{564}
A58: д. Репрезентация и благотворительность | B58: #FN1{565}
A59: е. Расходы на износ | B59: #FN1{566}
A60: ж. Страхование, налоги и другие расходы | B60: #FN1{567}
A61: з. Итого операционных расходов | B61: =SUM(B54:B60) -> 0
A63: 8. ОЦЕНКА НЕКРЕДИТНЫХ УБЫТКОВ | B63: #FN1{568}-#FN1{56802,56803,56814,56838,56842,56895}
A65: 9. ЧИСТАЯ ПРИБЫЛЬ ДО УПЛАТЫ НАЛОГОВ И ДРУГИХ ПОПРАВОК | B65: =B51-B61-B63 -> #VALUE!
A66: а. Оценка подоходного налога | B66: #FN1{569}
A68: 10. ДОХОД ДО ВВЕДЕНИЯ ПОПРАВОК | B68: =B65-B66 -> #VALUE!
A69: а. Непредвиденные доходы или убытки, чистые
A70: б. Другие поправки к прибыли, чистые
A72: 11. ЧИСТАЯ ПРИБЫЛЬ (УБЫТКИ) | B72: =B68+B69+B70 -> #VALUE!
A74: Подпись Руководителя:
A75: Подпись Главного Бухгалтера:

Sheet Analysis of Interest
B1: Приложение №1 к Рекомендациям по заполнению отчетности коммерческих банков по банковскому надзору представляемых Центральному банку Республики Узбекистан
A2: АНАЛИЗ ПРОЦЕНТНЫХ ДОХОДОВ И РАСХОДОВ | B2: Таблица-3 (Форма-0206IS)
A3: #FNP{date_end}
A4: Категория | B4: в тыс. сум
A5: 1 . ПРОЦЕНТНЫЕ ДОХОДЫ ПО ССУДАМ И ЛИЗИНГОВЫМ ОПЕРАЦИЯМ
A6: a. Ссуды ЦБРУ и лизинговые операции | B6: #FN1{414}
A7: б. Ссуды другим банкам и лизинговые операции | B7: #FN1{416,440,45101}
A8: в. Ссуды Правительству и лизинговые операции | B8: #FN1{418,442}
A9: г. Ссуды физическим лицам и лизинговые операции | B9: #FN1{420,421,441,443,45103}
A10: д. Ссуды государственным предприятиям и лизинговые операции | B10: #FN1{422,444,45107}
A11: е. Ссуды совместным предприятиям и лизинговые операции | B11: #FN1{424,445,45109}
A12: ж. Ссуды частным товариществам и корпорациям и лизинговые операции | B12: #FN1{426,446,45105,45113}
A13: з. Другие ссуды и лизинговые операции | B13: #FN1{419,423,425,431,436,437,439,447,45111,45115,45117,45119,45121}
A14: и. ИТОГО ПРОЦЕНТНЫХ ДОХОДОВ ПО ССУДАМ | B14: =SUM(B6:B13) -> 0
A16: 2. ПРОЦЕНТНЫЕ ДОХОДЫ ПО КОР.СЧЕТАМ
A17: a. К получению из ЦБРУ | B17: #FN1{402}
A18: б. К получению из других банков | B18: #FN1{404}
A19: в. ИТОГО ПРОЦЕНТНЫХ ДОХОДОВ ПО КОР. СЧЕТАМ | B19: =SUM(B17:B18) -> 0
A21: 3. ПРОЦЕНТНЫЕ ДОХОДЫ ПО СЧЕТАМ КУПЛИ-ПРОДАЖИ Ц/Б
A22: a. Государственные казначейские ценные бумаги | B22: #FN1{40601,40605,40701,40705}
A23: б. Облигации и ценные бумаги ЦБРУ | B23: #FN1{40609,40709}
A24: в. Ценные бумаги государственных корпораций | B24: #FN1{40613,40713}
A25: г. Еврооблигации | B25: #FN1{40617,40717}
A26: д. Частные ценные бумаги
A27: е. Другие ценные бумаги | B27: #FN1{40694,40794}
A28: ж. ИТОГО ПРОЦЕНТНЫХ ДОХОДОВ ПО СЧЕТАМ КУПЛИ-ПРОДАЖИ Ц/Б | B28: =SUM(B22:B27) -> 0
A30: 4. ПРОЦЕНТНЫЕ ДОХОДЫ ПО ИНВЕСТИЦИЯМ
A31: а. Государственные облигации | B31: #FN1{44801,44805}
A32: б. Облигации и ценные бумаги ЦБРУ | B32: #FN1{44809}
A33: в. Частные облигации | B33: #FN1{44813}
A34: г. Еврооблигации | B34: #FN1{44817}
A35: д. Другие ценные бумаги | B35: #FN1{44894}
A36: е. ИТОГО ПРОЦЕНТНЫХ ДОХОДОВ ПО ИНВЕСТИЦИЯМ | B36: =SUM(B31:B35) -> 0
A38: 5. ДРУГИЕ ПРОЦЕНТНЫЕ ДОХОДЫ
A39: а. Процентные доходы по соглашениям о покупке ц/б c обратным выкупом | B39: #FN1{450}
A40: б. Другие процентные доходы | B40: #FN1{408,410,412,449}
A42: 6. ИТОГО ПРОЦЕНТНЫХ ДОХОДОВ | B42: =B14+B19+B28+B36+B39+B40 -> #VALUE!
A44: 7. ПРОЦЕНТНЫЕ РАСХОДЫ ПО ДЕПОЗИТАМ
A45: A. Депозиты до востребования
A46: а. Правительство | B46: #FN1{50101,50103,50104,50105,50107}
A47: б. Физические лица | B47: #FN1{50106,50110}
A48: в. Государственные предприятия | B48: #FN1{50111}
A49: г. Совместные предприятия | B49: #FN1{50114}
A50: д. Частные товарищества и корпорации | B50: #FN1{50108}
A51: е. Другие депозиты | B51: #FN1{50116,50118,50121,50126}
A52: ж. Итого процентных расходов по депозитам до востребования | B52: =SUM(B46:B51) -> 0
A54: Б. Сберегательные депозиты
A55: а. Правительство | B55: #FN1{50601,50603,50604,50605,50607}
A56: б. Физические лица | B56: #FN1{50606}
A57: в. Государственные предприятия | B57: #FN1{50611}
A58: г. Совместные предприятия | B58: #FN1{50614}
A59: д. Частные товарищества и корпорации | B59: #FN1{50608}
A60: е. Другие депозиты | B60: #FN1{50616,50618,50621,50626,54204}
A61: ж. Итого процентных расходов по сберегательным депозитам | B61: =SUM(B55:B60) -> 0
A63: В. Срочные депозиты
A64: а. Правительство | B64: #FN1{51101,51103,51104,51105,51107}
A65: б. Физические лица | B65: #FN1{51106}
A66: в. Государственные предприятия | B66: #FN1{51111}
A67: г. Совместные предприятия | B67: #FN1{51114}
A68: д. Частные товарищества и корпорации | B68: #FN1{51108}
A69: е. Другие депозиты | B69: #FN1{51116,51118,51121,51126,54206}
A70: ж. Итого процентных расходов по срочным депозитам | B70: =SUM(B64:B69) -> 0
A72: Г. ИТОГО ПРОЦЕНТНЫХ РАСХОДОВ ПО ДЕПОЗИТАМ | B72: =B52+B61+B70 -> 0
A74: 8. ПРОЦЕНТНЫЕ РАСХОДЫ ПО ДРУГИМ ОБЯЗАТЕЛЬСТВАМ
A75: а. Процентные расходы по непогашенным акцептам | B75: #FN1{526}
A76: б. Процентные расходы по ссудам к оплате | B76: #FN1{531,541,54202}
A77: в. Процентные расходы по соглашениям о продаже ц/б с последующим выкупом | B77: #FN1{543}
A78: г. Другие процентные расходы | B78: #FN1{516,521,549,54208,54210}
A79: д. ИТОГО ПРОЦЕНТНЫХ РАСХОДОВ ПО ДРУГИМ ОБЯЗАТЕЛЬСТВАМ | B79: =SUM(B75:B78) -> 0
A81: 9. ИТОГО ПРОЦЕНТНЫХ РАСХОДОВ | B81: =B72+B79 -> 0
A83: Подпись Руководителя:
A84: Подпись Главного Бухгалтера:

Sheet Bank Capital Calc.
D1: Приложение №1 к Рекомендациям по заполнению отчетности коммерческих банков по банковскому надзору представляемых Центральному банку Республики Узбекистан
A2: РАСЧЕТ КАПИТАЛА БАНКА | E2: Таблица-4 (Форма-3004CAR)
D4: #FNP{date_end}
A5: No. | B5: Характеристики | C5: Капитал
C6: Основной | D6: Дополнительный {Уровень 2} | E6: Итого капитала
B7: {A} | C7: {Б} | D7: {В} | E7: {Г}
A8: I. | B8: КАПИТАЛ УРОВНЯ 1 (до вычетов)
A9: 1 | B9: Обыкновенные Акции
A10: a | B10: Полностью оплаченные обыкновенные акции | C10: #FN1{30306,30312,30318}
A11: б | B11: Минус: Обратно Выкупленные акции | C11: #FN1{30324}
A12: в | B12: Выпущенные, полностью оплаченные обыкновенные акции | E12: =C10-C11 -> #VALUE!
A13: 2 | B13: Некумулятивные бессрочные привилегированные акции
A14: а | B14: Полностью оплаченные привилегированные акции | D14: #FN1{30303,30309,30315}
A15: б | B15: Минус: Обратно Выкупленные акции | D15: #FN1{30321}
A16: в | B16: Выпущенные, полностью оплаченные привилегированные акции | E16: =D14-D15 -> #VALUE!
A17: 3 | B17: Добавленный капитал | C17: #FN1{30603} | E17: =C17 -> #FN1{30603}
A18: 4 | B18: Нераспределенная прибыль
A19: а | B19: Капитальные резервы | C19: #FN1{30903,30904,30910}
A20: б | B20: Нераспределенная прибыль | C20: #FN1{31203}
A21: в | B21: Минус: Убыток за текущий год | C21: #FN1A{31206}
A22: г | B22: Итого нераспределенная прибыль | E22: =C19+C20+C21 -> #VALUE!
A23: 5 | B23: Интерес меньшинства в консолидированных дочерних компаниях {согласно МБС} | E23: =C23 -> 0
A24: 6 | B24: Доля участия дочерних предприятий (выпущенные дочерними предприятиями и находящиеся во владении третьих лиц инструменты, приравненные к капиталу) | E24: =D24 -> 0
A25: 7 | B25: Резерв на девальвацию | C25: #FN1{30906} | E25: =C25 -> #FN1{30906}
A26: 8 | B26: Итого капитал уровня 1 до вычетов | C26: =SUM(C10:C25) -> 0 | D26: =SUM(D10:D25) -> 0 | E26: =C26+D26 -> 0
A27: II | B27: ВЫЧЕТЫ ИЗ СУММЫ КАПИТАЛА УРОВНЯ I
A28: 1 | B28: Нематериальные активы | C28: #FN1{166} | E28: =-C28 -> #VALUE!
A29: 2 | B29: Все инвестиции в капитал неконсолидированных хозяйствующих субъектов, в том числе в долговые обязательства, которые образуют капитал хозяйствующих субъектов | C29: #FN1{10719, 10779, 10821, 10879,10711, 10813, 159} | E29: =-C29 -> #VALUE!
A30: 3 | B30: Инвестиции в капитал других банков | C30: #FN1{158} | E30: =-C30 -> #VALUE!
A31: 4 | B31: Итого вычетов из суммы капитала Уровня 1 | C31: =SUM(C28:C30) -> 0 | E31: =SUM(E28:E30) -> #VALUE!
A32: III | B32: СКОРРЕКТИРОВАННЫЙ КАПИТАЛ УРОВНЯ I | E32: =E12+E16+E17+E22+E23+E24+E25+E31 -> #VALUE!
A34: IV | B34: КАПИТАЛ УРОВНЯ II
A36: 1 | B36: Прибыль за текущий год (при подтверждении аудиторами - 100%, в противном случае 50% от суммы) | C36: #FN1A{4,5,31206,30907,30909} | E36: =C36 -> #FN1A{4,5,31206,30907,30909}
A37: 2 | B37: Резервы, создаваемые на стандартные кредиты (активы), в размере не более 1.25% от общей суммы активов, взвешенных с учетом риска | C37: ='Loan Classification'!G16 -> 0 | E37: =C37 -> 0
A38: 3 | B38: Субординированный долг | E38: =C38 -> 0
A39: 4 | B39: Излишки оценочной стоимости прироста над первоначальной стоимостью | C39: =F39*D39 -> #VALUE! | D39: 0.45 | E39: =C39 -> #VALUE! | F39: #FN1{30908}
A40: 5 | B40: Другие инструменты капитала, в том числе обязательства смешанного типа (не более 1/3 части капитала 1 уровня после вычетов) | E40: =C40 -> 0
A41: 6 | B41: Вычеты превышения Капитала Уровня II над Капиталом Уровня I | E41: 0
A42: 7 | B42: Итого капитала Уровня II | C42: =SUM(C36:C41) -> #VALUE! | E42: =SUM(E36:E40) -> #VALUE!
A43: V | B43: СКОРРЕКТИРОВАННЫЙ КАПИТАЛ УРОВНЯ II | E43: =E42-E41 -> #VALUE!
A44: VI | B44: ИТОГО РЕГУЛЯТИВНЫЙ КАПИТАЛ | E44: =E32+E43 -> #VALUE!
A45: VII | B45: ОБЩАЯ СУММА АКТИВОВ, ВЗВЕШЕННЫХ С УЧЕТОМ РИСКА | E45: =SUM(E46:E48) -> #VALUE!
A46: 1 | B46: Сумма балансовых и забалансовых активов, взвешенных с учетом риска | E46: ='Calculation of Risk Weighted As'!H74 -> #VALUE!
A47: 2 | B47: Операционный риск | E47: ='Calculation of Risk'!C19 -> 0
A48: 3 | B48: Рыночный риск | E48: ='Calculation of Risk'!C25 -> #VALUE!
A49: VIII | B49: КОЭФФИЦИЕНТ КАПИТАЛА УРОВНЯ I (III/VII) | E49: =E32/E45 -> #VALUE!
A50: IX | B50: КОЭФФИЦИЕНТ ОБЩЕЙ СУММЫ КАПИТАЛА, ОСНОВАННОГО НА РИСКЕ (VI/VII) | E50: =E44/E45 -> #VALUE!
A51: X | B51: Активы для расчета левеража | E51: =E52+E53+E54-E55 -> #VALUE!
A52: 1 | B52: Общие активы | E52: =Balance!C36 -> #VALUE!
A53: 2 | B53: забалансовые инструменты
A54: 3 | B54: деривативные (производные) инструменты | E54: #FN1{92709,92732,92716,92736}
A55: 4 | B55: Минус: Нематериальные активы | E55: =+E28 -> #VALUE!
A56: XI | B56: Коэффициент левеража | E56: =E32/E51 -> #VALUE!
B58: Подпись Председателя правления:
B60: Подпись Главного Бухгалтера:

Sheet Calculation of Risk Weighted As
E1: Приложение №1 к Рекомендациям по заполнению отчетности коммерческих банков по банковскому надзору представляемых Центральному банку Республики Узбекистан
A2: РАСЧЕТ АКТИВОВ ВЗВЕШЕННЫХ С УЧЕТОМ РИСКА | F2: Таблица-5 (Форма-3006CAR)
A3: #FNP{date_end} | D3: 0
A5: # | B5: Характеристики | C5: 0 | D5: 0.2 | E5: 0.5 | F5: 1 | G5: 1.5 | I5: #FN1{119} | J5: FN1{119}
C6: Риск | D6: Риск | E6: Риск | F6: Риск | G6: Риск | I6: #FN1{121} | J6: FN1{121}
B7: (A) | C7: (Б) | D7: (В) | E7: (Г) | F7: (Д) | G7: (Е) | I7: #FN1{123} | J7: FN1{123}
B8: Балансовые Активы | I8: #FN1{145} | J8: FN1{145}
A9: 1. | B9: Касса (наличность и монеты) и Драгоценные металлы | C9: #FN1{10101-10107,10111,10198,109} | I9: #FN1{147} | J9: FN1{147}
A10: 2 | B10: Денежная наличность и другие платежные документы в пути | D10: #FN1{10109}
A11: 3 | B11: Корреспондентские и резервные счета в ЦБРУ | C11: #FN1{103,16103}
A12: 4 | B12: Корр. счета, кредиты и другие требования к другим банкам и депозитарным институтам | C12: #FN1{105,121,145}
A13: а | B13: требования к банкам стран с низким уровнем риска
A14: б | B14: требования к другим банкам | F14: =C12-D13 -> #VALUE!
A15: 5 | B15: Рыночные ценные бумаги, чистые | C15: #FN1{10701,10705,10709,10801,10805,10809}
A16: а. | B16: Ценные бумаги, выпущенные Правительством Республики Узбекистан и ЦБРУ | C16: =C15-C17 -> #VALUE!
A17: б | B17: Ценные бумаги, выпущенные правительствами и центральными банками стран, с низким уровня риска, а также другие требования к центральным банкам и правительствам этих стран
A18: в | B18: Другие ценные бумаги | F18: #FN1{10711,10715,10719,10779,10795}+#FN1{10813,10817,10821,10879,10889,10895}+#FN1{113,115,117,118}
A19: 6 | B19: Кредиты и другие активы или их части, обеспеченные наличными деньгами, хранящимися на отдельном блокированном депозитном счете. | C19: =I19+H19 -> #VALUE! | H19: #FNOBES{111,123,124,125,126,127,129,130,131,132,133;;;25;;E} | I19: #FNOBES{143,147,148,149,150,151,152,153,154,155,156,157;;;25;;E}
A20: 7 | B20: Все требования банка, деноминированные в местную валюту стран не входящих в группу стран с низким уровнем риска, к Центральным банкам и центральным правительствам этих стран
A21: 8 | B21: Активы, обеспеченные ценными бумагами выпущенными банками зарегистрированными в странах с низким уровнем риска
A22: 9. | B22: Требования банка к международным кредитным организациям, а также активы, гарантированные этими организациями
A23: 10. | B23: Активы или их части, обеспеченные залогом в виде ценных бумаг, оцененных по текущей рыночной стоимости и эмитированных международными финансовыми институтами
A24: 11. | B24: Кредиты и лизинг, чистые | C24: #FN1{11101,11195,11199,12301,12309,12399,12401,12409,12499,12501,12509,12599,12601,12609,12699,12701,12709,12799,12901,12909,12999,13001,13009,13099,13101,13109,13199,13201,13209,13299,13301,13309,13399}+#FN1{143,147,149,150,151,152,153,154,155}
A25: а) | B25: Прямые требования к Правительству и Центральному банку Республики Узбекистан | C25: #FN1{119,123,147}
A26: б) | B26: Активы или их части, обеспеченные ценными бумагами, которые оцененные по текущей рыночной стоимости и выпущенными или гарантированными Правительством Республики Узбекистан, Центральным банком Республики Узбекистан или Правительствами стран с низким уровнем риска. | D26: =H26+I26+J26+K26 -> #VALUE! | H26: #FNOBES{111,123,124,125,126,127,129,130,131,132,133;;;31;;E} | I26: #FNOBES{143,147,148,149,150,151,152,153,154,155,156,157;;;31;;E} | J26: #FNOBES{111,123,124,125,126,127,129,130,131,132,133;;;42;;E} | K26: #FNOBES{143,147,148,149,150,151,152,153,154,155,156,157;;;42;;E}
A27: в) | B27: Кредиты на недвижимость обеспеченные приобретаемым или строящимся домом (квартирой) | E27: =H27+I27+J27+K27 -> #VALUE! | H27: #FNOBES{111,123,124,125,126,127,129,130,131,132,133;;;21;;E} | I27: #FNOBES{143,147,148,149,150,151,152,153,154,155,156,157;;;21;;E} | J27: #FNOBES{111,123,124,125,126,127,129,130,131,132,133;;;22;;E} | K27: #FNOBES{143,147,148,149,150,151,152,153,154,155,156,157;;;22;;E}
A28: г) | B28: Реструктуризированные кредиты и кредиты в статусе "ненаращивания"
A29: д) | B29: Кредиты, по которым банк не имеет приоритетного права на залог
A30: е) | B30: Пересмотренные или пролонгированные кредиты и лизинги более одного раза | G30: #FN1{12109,12309,12409,12509,12609,12709,12909,13009,13109,13209,13309,15619}+#FN1{14705,14905,15005,15105,15205,15305,15405,15505}
A31: ж) | B31: все другие кредиты (кроме лизинга) | F31: =C24-C25-D26-E27-F28-F29 -> #VALUE!
A32: 12. | B32: Кредиты и лизинг в судебном разбирательстве | G32: #FN1{11105,157}
A33: 13. | B33: Просроченные кредиты и лизинг чистый | G33: #FN1{11103,12105,12305,12405,12505,12605,12705,12905,13005,13105,13205,13305,15617}
A34: 14 | B34: Финансовый лизинг | F34: #FN1{156}
A35: 15 | B35: Основные средства
A36: а) | B36: Основные средства, используемые в банковской деятельности (минус амортизация) | F36: #FN1{165}
A37: б) | B37: Недвижимое имущество принятое на баланс банка в целях полного или частичного погащения задолженности | G37: #FN1{16701, 16703}
A38: в) | B38: Недвижимое имущество банка, которым банк не пользуется более двух лет | G38: #FN1{16705, 16709}
A39: 16 | B39: Инвестиции в капитал неконсолидированных банковских и небанковских финансовых дочерних компаний и всех нефинансовых предприятий | C39: #FN1{158,159}
A40: 17 | B40: Все другие инвестиции, чистые | F40: 0
A41: 18 | B41: Нематериальные активы, включая гудвилл | C41: #FN1{166}
A42: 19 | B42: Другие активы в судебном разбирательстве и(или) не взысканные в установленном порядке | G42: #FN1{19995}
A43: 20 | B43: Другие активы, чистые | C43: 0 | F43: =Balance!C36-C44-D44-E44-F14-F18-F28-F29-F31-F34-F36-F40-G44 -> #VALUE!
A44: 21 | B44: Общая сумма балансовых активов согласно Инструкции | C44: =SUM(C9:C43)-C12-C15-C24 -> #VALUE! | D44: =SUM(D9:D43) -> #VALUE! | E44: =SUM(E9:E43) -> #VALUE! | F44: =SUM(F9:F43) -> #VALUE! | G44: =SUM(G9:G43) -> 0 | H44: =SUM(C44:G44) -> #VALUE!
A45: 22 | B45: Общая сумма балансовых рисковых активов, по группам риска | D45: =D44*D5 -> #VALUE! | E45: =E44*E5 -> #VALUE! | F45: =F44*F5 -> #VALUE! | G45: =G44*G5 -> 0
A46: 23 | B46: Общая сумма балансовых рисковых активов | G46: =SUM(D45:G45) -> #VALUE!
A49: # | B49: Характеристики | C49: Фактор пересчета кредита | D49: 0 | E49: 0.2 | F49: 0.5 | G49: 1 | H49: Значение риска
D50: Риск | E50: Риск | F50: Риск | G50: Риск
B52: (A) | C52: (Б) | D52: (В) | E52: (Г) | F52: (Д) | G52: (Е) | H52: (Ж)
B53: Забалансовые Активы
A54: 1 | B54: Обязательства по выдаче кредита | F54: #FN1{91809}
A55: a | B55: Более одного года | C55: 0.5 | H55: =C55*D$49*D55+C55*E$49*E55+C55*F$49*F55+C55*G$49*G55 -> 0
A56: б | B56: Год и менее | C56: 0.2 | E56: =F54-F55 -> #VALUE! | H56: =C56*D$49*D56+C56*E$49*E56+C56*F$49*F56+C56*G$49*G56 -> #VALUE!
A57: 2 | B57: Обязательства приобретения ценных бумаг и других активов (включая активы, проданные в соответствии с соглашениями о выкупе) | C57: 1 | F57: #FN1{92802} | H57: =C57*D$49*D57+C57*E$49*E57+C57*F$49*F57+C57*G$49*G57 -> #VALUE!
A58: 3 | B58: Гарантии и поручительства | C58: 1 | G58: #FN1{90993} | H58: =C58*D$49*D58+C58*E$49*E58+C58*F$49*F58+C58*G$49*G58 -> #VALUE!
A59: 4 | B59: Аккредитивы | G59: #FN1{90944,90951}
A60: a | B60: Прямые кредитные заменители | C60: 1 | G60: =G59-G61 -> #VALUE! | H60: =C60*D$49*D60+C60*E$49*E60+C60*F$49*F60+C60*G$49*G60 -> #VALUE!
A61: б | B61: Связанные со сделками | C61: 0.5 | H61: =C61*D$49*D61+C61*E$49*E61+C61*F$49*F61+C61*G$49*G61 -> 0
A62: в | B62: Связанные с торговлей (краткосрочные, самоликвидирующиеся, обеспеченные) | C62: 0.2 | G62: #FN1{90909,90916,90923,90930,90937,90958} | H62: =C62*D$49*D62+C62*E$49*E62+C62*F$49*F62+C62*G$49*G62 -> #VALUE!
A63: 5 | B63: Форвардные котракты, свопы, опционы и подобные обязательства
A64: a | B64: Контракты по процентной ставке | G64: #FN1{927}
A65: а1 | B65: Со оставшимся сроком погашения до одного года | C65: 0.005 | G65: =G64-G66-G67-G69-G70-G71 -> #VALUE! | H65: =C65*D$49*D65+C65*E$49*E65+C65*F$49*F65+C65*G$49*G65 -> #VALUE!
A66: а2 | B66: Со оставшимся сроком погашения от одного года до двух лет | C66: 0.01 | H66: =C66*D$49*D66+C66*E$49*E66+C66*F$49*F66+C66*G$49*G66 -> 0
A67: а3 | B67: Со оставшимся сроком погашения более двух лет до трех | C67: 0.02 | H67: =C67*D$49*D67+C67*E$49*E67+C67*F$49*F67+C67*G$49*G67 -> 0
A68: б | B68: Валютные котракты и золото
A69: б1 | B69: С первоначальным сроком погашения до одного года | C69: 0.02 | H69: =C69*D$49*D69+C69*E$49*E69+C69*F$49*F69+C69*G$49*G69 -> 0
A70: б2 | B70: С первоначальным сроком погашения от одного года до двух лет | C70: 0.05 | H70: =C70*D$49*D70+C70*E$49*E70+C70*F$49*F70+C70*G$49*G70 -> 0
A71: б3 | B71: С первоначальным сроком погашения свыше двух лет до трех лет | C71: 0.08 | H71: =C71*D$49*D71+C71*E$49*E71+C71*F$49*F71+C71*G$49*G71 -> 0
A72: 6 | B72: Общая сумма забалансовых активов | D72: =SUM(D55:D71) -> 0 | E72: =SUM(E55:E71) -> #VALUE! | F72: =SUM(F55:F71) -> 0 | G72: =SUM(G55:G71)-G64-G59 -> #VALUE!
A73: 7 | B73: Общая сумма забалансовых активов, взвешенных с учетом риска | H73: =SUM(H55:H71) -> #VALUE!
A74: 8 | B74: Общая сумма активов, взвешенных с учетом риска | H74: =G46+H73 -> #VALUE!
B76: Подпись Руководителя:
B77: Подпись Главного Бухгалтера:
B80: -ручное заполнение

Sheet Calculation of Risk
C1: Приложение №1 к Рекомендациям по заполнению отчетности коммерческих банков по банковскому надзору представляемых Центральному банку Республики Узбекистан
A2: РАСЧЕТ ПО ОПЕРАЦИОННЫМ И РЫНОЧНЫМ РИСКАМ
C3: Таблица-5А (Форма-3006CAR)
B4: #FNP{date_end}
A5: № | B5: Наименование показателя | C5: в тыс. сум
A6: 1. | B6: Валовый доход банка за 2012 год | C6: =SUM(C7:C9) -> 0
A7: а. | B7: процентные доходы
A8: б. | B8: процентные расходы
A9: в. | B9: другие доходы
A10: 2. | B10: Валовый доход банка за 2013 год | C10: =SUM(C11:C13) -> 0
A11: а. | B11: процентные доходы
A12: б. | B12: процентные расходы
A13: в. | B13: другие доходы
A14: 3. | B14: Валовый доход банка за 2014 год | C14: =SUM(C15:C17) -> 0
A15: а. | B15: процентные доходы
A16: б. | B16: процентные расходы
A17: в. | B17: другие доходы
A18: 4. | B18: Средний валовый доход банка (за последние три года) | C18: =(C6+C10+C14)/3 -> 0
A19: 5. | B19: Сумма операционных рисков | C19: =100/C26*C18*0.15 -> 0
A21: 6. | B21: Счета валютной позиции (счет 17101 (сумовая часть)) | C21: #FN13{17101;000}/1000
A22: 7. | B22: Продажа на условиях Своп и Форвард (счет 92709, 92732) | C22: #FN1{92709,92732}
A23: 8. | B23: Покупка на условиях Своп и Форвард (счет 92716, 92736) | C23: #FN1{92716,92736}
A24: 9. | B24: Открытая валютная позиция, всего | C24: =C21+(C22-C23) -> #VALUE!
A25: 10. | B25: Сумма рыночных рисков | C25: =100/C26*C24*0.1 -> #VALUE!
A26: 11. | B26: Действуюший минимальное требование к достаточности капитала | C26: 11.5
A28: Подпись Председателя правления:
A30: Подпись Главного Бухгалтера:

Sheet Changes in Equity
B1: Приложение №1 к Рекомендациям по заполнению отчетности коммерческих банков по банковскому надзору представляемых Центральному банку Республики Узбекистан
A2: ИЗМЕНЕНИЯ В АКЦИОНЕРНОМ КАПИТАЛЕ | B2: Таблица-6 (Форма-3106CSA)
A3: #FNP{date_end} | C3: #FN1D{303;B} | D3: #FN1D{303;E} | E3: =D3-C3 -> #VALUE! | F3: 303
A4: Категория | B4: в тыс. сум | C4: #FN1D{306;B} | D4: #FN1D{306;E} | E4: =D4-C4 -> #VALUE! | F4: 306
A5: 1. Итого собственного капитала первоначально определенного за прошлый год | B5: #FN1D{303,306,309,312;B} | C5: #FN1D{309;B} | D5: #FN1D{309;E} | E5: =D5-C5 -> #VALUE! | F5: 309
A6: 2. Исправления в собственном капитале не показанные в отчете за прошлый год, чистые | C6: #FN1D{312;B} | D6: #FN1D{312;E} | E6: =D6-C6 -> #VALUE! | F6: 312 | I6: fn1 303
A7: 3. Исправленный баланс на конец прошлого календарного года (сумма строк 1 и 2) | B7: =SUM(B5:B6) -> 0 | C7: =SUM(C3:C6) -> 0 | D7: =SUM(D3:D6) -> 0 | E7: =D7-C7 -> 0 | I7: 30300 | J7: 10101-b | K7: 10101-e
A8: 4. Чистый прибыль (убыток) по состоянию на дату от начала года | B8: #FN1{4,5}
A9: 5. Продажа, Обмен, Приобретение или выкуп акций, за текущий год (чистая выручка) | B9: =D9-C9 -> #VALUE! | C9: #FN1D{303,306;B} | D9: #FN1D{303,306;E} | E9: =D9-C9 -> #VALUE! | F9: 303.306 | I9: #FN1{30303} | J9: #FN1D{10101;B} | K9: #FN1D{10101E}
A10: 6. Изменения в оценочной стоимости прироста над первонач. стоимостью, за текущий год (чистые) | B10: =D10-C10 -> #VALUE! | C10: #FN1D{30908;B} | D10: #FN1D{30908;E} | E10: =D10-C10 -> #VALUE! | F10: 30908 | I10: #FN1{30306}
A11: 7. МИНУС: Денежные дивиденды объявленные по привилегированным акциям | I11: #FN1{30309}
A12: 8. МИНУС: Денежные дивиденды объявленные по обыкновенным акциям | I12: #FN1{30312}
A13: 9. Другие статьи влияющие на собственный капитал за текущий год (чистые) | I13: #FN1{30315}
A14: 10. Итого собственного капитала на конец текущего периода (сумма строк с 3 по 10) | B14: #FN1{303,306,309,312,4,5} | I14: #FN1{30318}
I15: #FN1{30331}
A16: Подпись Руководителя: | I16: #FN1{30324}
A17: Подпись Главного Бухгалтера: | I17: =I9+I10+I11+I12+I13+I14+I15+I16 -> #VALUE!
C22: ручной ввод

Sheet Recociliation
B1: Приложение №1 к Рекомендациям по заполнению отчетности коммерческих банков по банковскому надзору представляемых Центральному банку Республики Узбекистан
A2: ВЫВЕРКА НЕРАСПРЕДЕЛЕННОЙ ПРИБЫЛИ | B2: Таблица-7 (Форма-0208IS)
A3: #FNP{date_end} | B3: в тыс. сум
A4: 1. Нераспределенная прибыль, указанная в отчете за предыдущий календарный год | B4: #FN1D{30903,30904,30907,312,30905,30909;B}
A5: 2. Плюс или Минус: Предварит. корректировки не указанные в отчете к концу года
A6: 3. Равно: Откорректированная нераспределенная прибыль | B6: =SUM(B4:B5) -> 0
A7: 4. Плюс или Минус: Кумулятивная чистая прибыль (Убытки) в текущем году | B7: #FN1{4,5}
A8: 5. Минус: Денежные дивиденды объявленные по обыкновенным акциям
A9: 6. Минус: Денежные дивиденды объявленные по привилегированным акциям
A10: 7. Минус: Дивиденды в виде акций объявленные по обыкновенным акциям
A11: 8. Минус: Дивиденды в виде акций объявленные по привилегированным акциям
A12: 9. Другие статьи, влияющие на нераспределенную прибыль,Чистые | B12: =B13-B6-B7+B8+B9+B10+B11 -> #VALUE!
A13: 10. Равно: Текущий Баланс, Нераспределенная прибыль | B13: #FN1{4,5,30903,30904,30907,312,30905,30909}
A15: Подпись Руководителя:
A16: Подпись Главного Бухгалтера:
C17: ручной ввод

Sheet Loans Receivable
R1: Приложение №1 к Рекомендациям по заполнению отчетности коммерческих банков по банковскому надзору представляемых Центральному банку Республики Узбекистан
A2: Кредиты к получению по отраслям экономики, типам клиентов и по типу обеспечения | R2: Таблица-8 (Форма-1516LES)
B3: #FNP{date_end} | X3: Контроль
C5: сумма В и Г | D5: срочные+рестр | G5: просрочка + в суде | K5: из них | AU5: просрочка + в суде
B6: Отрасль экономики | C6: Сумма кредитов | D6: Начисляемые кредиты | E6: 15701 на основном ссудном счете | F6: Просрочка | G6: Неначисляемые кредиты | H6: Средняя процентная ставка | I6: Депозиты | J6: Гарантированные Правительством Республики Узбекистан | K6: Гарантированные Правительством Р Уз. в ин. валюте | L6: Транспортные средства | M6: Инвентарь | N6: Недвижимость | O6: Оборудование | P6: Векселя {облигации,31,32,33,34,35,36,37} | Q6: Акции | R6: Гарантия третьей стороны | S6: Поручительства третьей стороны | T6: Страховой полис | U6: Необеспеченные | V6: Другое обеспечение | AU6: Неначисляемые кредиты
A7: Код | B7: (А) | C7: (Б) | D7: (В) | G7: (Г) | H7: (Д) | I7: (Е) | J7: (Ж) | K7: (Ж1) | L7: (З) | M7: (И) | N7: (К) | O7: (Л) | P7: (М) | Q7: (Н) | R7: (О) | S7: (П) | T7: (Р) | U7: (С) | V7: (Т)
B8: Промышленность
A9: =A8+10 -> 10 | B9: Физические лица | C9: =D9+G9 -> #VALUE! | D9: #FNECTC{12501,12509,14901,14905,11101,13301,13309,14301,14305,15603;08;1;;E} | E9: #FNECTC{15701,15705;08;1;;E} | F9: #FNECTCP{12501,12509,14901,14905,11101,13301,13309,14301,14305,15603;08;1;;E} | G9: =E9+F9 -> #VALUE! | H9: #FN4{;12501-12509,14901,14905} | I9: #FNOBES{12501,12509,14901,14905,11101,13301,13309,14301,14305,15603;08;1;25;;E} | J9: #FNOBES{12501,12509,14901,14905,11101,13301,13309,14301,14305,15603;08;1;42;;E} | L9: #FNOBES{12501,12509,14901,14905,11101,13301,13309,14301,14305,15603;08;1;23;;E} | M9: #FNOBES{12501,12509,14901,14905,11101,13301,13309,14301,14305,15603;08;1;26;;E} | N9: #FNOBES{12501,12509,14901,14905,11101,13301,13309,14301,14305,15603;08;1;21,22;;E} | O9: #FNOBES{12501,12509,14901,14905,11101,13301,13309,14301,14305,15603;08;1;24;;E} | P9: #FNOBES{12501,12509,14901,14905,11101,13301,13309,14301,14305,15603;08;1;31,32,33,34,35,36,37;;E} | Q9: #FNOBES{12501,12509,14901,14905,11101,13301,13309,14301,14305,15603;08;1;29;;E} | R9: #FNOBES{12501,12509,14901,14905,11101,13301,13309,14301,14305,15603;08;1;43;;E} | S9: #FNOBES{12501,12509,14901,14905,11101,13301,13309,14301,14305,15603;08;1;41;;E} | T9: #FNOBES{12501,12509,14901,14905,11101,13301,13309,14301,14305,15603;08;1;51;;E} | U9: #FNOBES{12501,12509,14901,14905,11101,13301,13309,14301,14305,15603;08;1;61;;E} | V9: =C9-I9-J9-L9-M9-N9-O9-P9-Q9-R9-S9-T9-U9 -> #VALUE! | X9: =SUM(I9:V9) -> #VALUE! | Y9: =C9-X9 -> #VALUE! | AU9: #FNECTCP{11103,11105,12505,13305,15617,15703,15705;08;1;;E}
A10: =A9+10 -> 20 | B10: Гос. предприятия | C10: =D10+G10 -> #VALUE! | D10: #FNECTC{12701,12709,15101,15105,11101,13301,13309,14301,14305,15607;02;1;;E} | E10: #FNECTC{15701,15705;02;1;;E} | F10: #FNECTCP{12701,12709,15101,15105,11101,13301,13309,14301,14305,15607;02;1;;E} | G10: =E10+F10 -> #VALUE! | H10: #FN4{1;12701-12709,15101,15105} | I10: #FNOBES{12701,12709,15101,15105,11101,13301,13309,14301,14305,15607;02;1;25;;E} | J10: #FNOBES{12701,12709,15101,15105,11101,13301,13309,14301,14305,15607;02;1;42;;E} | L10: #FNOBES{12701,12709,15101,15105,11101,13301,13309,14301,14305,15607;02;1;23;;E} | M10: #FNOBES{12701,12709,15101,15105,11101,13301,13309,14301,14305,15607;02;1;26;;E} | N10: #FNOBES{12701,12709,15101,15105,11101,13301,13309,14301,14305,15607;02;1;21,22;;E} | O10: #FNOBES{12701,12709,15101,15105,11101,13301,13309,14301,14305,15607;02;1;24;;E} | P10: #FNOBES{12701,12709,15101,15105,11101,13301,13309,14301,14305,15607;02;1;31,32,33,34,35,36,37;;E} | Q10: #FNOBES{12701,12709,15101,15105,11101,13301,13309,14301,14305,15607;02;1;29;;E} | R10: #FNOBES{12701,12709,15101,15105,11101,13301,13309,14301,14305,15607;02;1;43;;E} | S10: #FNOBES{12701,12709,15101,15105,11101,13301,13309,14301,14305,15607;02;1;41;;E} | T10: #FNOBES{12701,12709,15101,15105,11101,13301,13309,14301,14305,15607;02;1;51;;E} | U10: #FNOBES{12701,12709,15101,15105,11101,13301,13309,14301,14305,15607;02;1;61;;E} | V10: =C10-I10-J10-L10-M10-N10-O10-P10-Q10-R10-S10-T10-U10 -> #VALUE! | X10: =SUM(I10:V10) -> #VALUE! | Y10: =C10-X10 -> #VALUE! | AU10: #FNECTCP{11103,11105,12705,13305,15617,15701,15705;02;1;;E}
A11: 30 | B11: Совместные предприятия | C11: =D11+G11 -> #VALUE! | D11: #FNECTC{12901,12909,15301,15305,11101,13301,13309,14301,14305,15609;10;1;;E} | E11: #FNECTC{15701,15705;10;1;;E} | F11: #FNECTCP{12901,12909,15301,15305,11101,13301,13309,14301,14305,15609;10;1;;E} | G11: =E11+F11 -> #VALUE! | H11: #FN4{1;12901-12909,15301,15305} | I11: #FNOBES{12901,12909,15301,15305,11101,13301,13309,14301,14305,15609;10;1;25;;E} | J11: #FNOBES{12901,12909,15301,15305,11101,13301,13309,14301,14305,15609;10;1;42;;E} | L11: #FNOBES{12901,12909,15301,15305,11101,13301,13309,14301,14305,15609;10;1;23;;E} | M11: #FNOBES{12901,12909,15301,15305,11101,13301,13309,14301,14305,15609;10;1;26;;E} | N11: #FNOBES{12901,12909,15301,15305,11101,13301,13309,14301,14305,15609;10;1;21,22;;E} | O11: #FNOBES{12901,12909,15301,15305,11101,13301,13309,14301,14305,15609;10;1;24;;E} | P11: #FNOBES{12901,12909,15301,15305,11101,13301,13309,14301,14305,15609;10;1;31,32,33,34,35,36,37;;E} | Q11: #FNOBES{12901,12909,15301,15305,11101,13301,13309,14301,14305,15609;10;1;29;;E} | R11: #FNOBES{12901,12909,15301,15305,11101,13301,13309,14301,14305,15609;10;1;43;;E} | S11: #FNOBES{12901,12909,15301,15305,11101,13301,13309,14301,14305,15609;10;1;41;;E} | T11: #FNOBES{12901,12909,15301,15305,11101,13301,13309,14301,14305,15609;10;1;51;;E} | U11: #FNOBES{12901,12909,15301,15305,11101,13301,13309,14301,14305,15609;10;1;61;;E} | V11: =C11-I11-J11-L11-M11-N11-O11-P11-Q11-R11-S11-T11-U11 -> #VALUE! | X11: =SUM(I11:V11) -> #VALUE! | Y11: =C11-X11 -> #VALUE! | AU11: #FNECTCP{11103,11105,12905,13305,15617,15701,15705;10;1;;E}
A12: 40 | B12: Частные товарищества и корпорации | C12: =D12+G12 -> #VALUE! | D12: #FNECTC{13101,13109,15501,15505,11101,13301,13309,14301,14305,15613;09;1;;E} | E12: #FNECTC{15701,15705;09;1;;E} | F12: #FNECTCP{13101,13109,15501,15505,11101,13301,13309,14301,14305,15613;09;1;;E} | G12: =E12+F12 -> #VALUE! | H12: #FN4{1;13101-13109,15501-15505} | I12: #FNOBES{13101,13109,15501,15505,11101,13301,13309,14301,14305,15613;09;1;25;;E} | J12: #FNOBES{13101,13109,15501,15505,11101,13301,13309,14301,14305,15613;09;1;42;;E} | L12: #FNOBES{13101,13109,15501,15505,11101,13301,13309,14301,14305,15613;09;1;23;;E} | M12: #FNOBES{13101,13109,15501,15505,11101,13301,13309,14301,14305,15613;09;1;26;;E} | N12: #FNOBES{13101,13109,15501,15505,11101,13301,13309,14301,14305,15613;09;1;21,22;;E} | O12: #FNOBES{13101,13109,15501,15505,11101,13301,13309,14301,14305,15613;09;1;24;;E} | P12: #FNOBES{13101,13109,15501,15505,11101,13301,13309,14301,14305,15613;09;1;31,32,33,34,35,36,37;;E} | Q12: #FNOBES{13101,13109,15501,15505,11101,13301,13309,14301,14305,15613;09;1;29;;E} | R12: #FNOBES{13101,13109,15501,15505,11101,13301,13309,14301,14305,15613;09;1;43;;E} | S12: #FNOBES{13101,13109,15501,15505,11101,13301,13309,14301,14305,15613;09;1;41;;E} | T12: #FNOBES{13101,13109,15501,15505,11101,13301,13309,14301,14305,15613;09;1;51;;E} | U12: #FNOBES{13101,13109,15501,15505,11101,13301,13309,14301,14305,15613;09;1;61;;E} | V12: =C12-I12-J12-L12-M12-N12-O12-P12-Q12-R12-S12-T12-U12 -> #VALUE! | X12: =SUM(I12:V12) -> #VALUE! | Y12: =C12-X12 -> #VALUE! | AU12: #FNECTCP{11103,11105,13105,13305,15617,15701,15705;09;1;;E}
A13: 50 | B13: Правительство | C13: =D13+G13 -> #VALUE! | D13: #FNECTC{12301,12309,14701,14705,11101,13301,13309,14301,14305;01;1;;E} | E13: #FNECTC{15701,15705;01;1;;E} | F13: #FNECTCP{12301,12309,14701,14705,11101,13301,13309,14301,14305;01;1;;E} | G13: =E13+F13 -> #VALUE! | H13: #FN4{1;12301-12309,14701,14705} | I13: #FNOBES{12301,12309,14701,14705,11101,13301,13309,14301,14305;01;1;25;;E} | J13: #FNOBES{12301,12309,14701,14705,11101,13301,13309,14301,14305;01;1;42;;E} | L13: #FNOBES{12301,12309,14701,14705,11101,13301,13309,14301,14305;01;1;23;;E} | M13: #FNOBES{12301,12309,14701,14705,11101,13301,13309,14301,14305;01;1;26;;E} | N13: #FNOBES{12301,12309,14701,14705,11101,13301,13309,14301,14305;01;1;21,22;;E} | O13: #FNOBES{12301,12309,14701,14705,11101,13301,13309,14301,14305;01;1;24;;E} | P13: #FNOBES{12301,12309,14701,14705,11101,13301,13309,14301,14305;01;1;31,32,33,34,35,36,37;;E} | Q13: #FNOBES{12301,12309,14701,14705,11101,13301,13309,14301,14305;01;1;29;;E} | R13: #FNOBES{12301,12309,14701,14705,11101,13301,13309,14301,14305;01;1;43;;E} | S13: #FNOBES{12301,12309,14701,14705,11101,13301,13309,14301,14305;01;1;41;;E} | T13: #FNOBES{12301,12309,14701,14705,11101,13301,13309,14301,14305;01;1;51;;E} | U13: #FNOBES{12301,12309,14701,14705,11101,13301,13309,14301,14305;01;1;61;;E} | V13: =C13-I13-J13-L13-M13-N13-O13-P13-Q13-R13-S13-T13-U13 -> #VALUE! | X13: =SUM(I13:V13) -> #VALUE! | Y13: =C13-X13 -> #VALUE! | AU13: #FNECTCP{11103,11105,12305,13305,15617,15701,15705;01;1;;E}
B14: Бюджетные организации | C14: =D14+G14 -> #VALUE! | D14: #FNECTC{12401,12409,14801,14809,11101,13301,13309,14301,14305;12;1;;E} | E14: #FNECTC{15701,15705;12;1;;E} | F14: #FNECTCP{12401,12409,14801,14809,11101,13301,13309,14301,14305;12;1;;E} | G14: =E14+F14 -> #VALUE! | H14: #FN4{1;12401-12409,14801,14809} | I14: #FNOBES{12401,12409,14801,14809,11101,13301,13309,14301,14305;12;1;25;;E} | J14: #FNOBES{12401,12409,14801,14809,11101,13301,13309,14301,14305;12;1;42;;E} | L14: #FNOBES{12401,12409,14801,14809,11101,13301,13309,14301,14305;12;1;23;;E} | M14: #FNOBES{12401,12409,14801,14809,11101,13301,13309,14301,14305;12;1;26;;E} | N14: #FNOBES{12401,12409,14801,14809,11101,13301,13309,14301,14305;12;1;21,22;;E} | O14: #FNOBES{12401,12409,14801,14809,11101,13301,13309,14301,14305;12;1;24;;E} | P14: #FNOBES{12401,12409,14801,14809,11101,13301,13309,14301,14305;12;1;31,32,33,34,35,36,37;;E} | Q14: #FNOBES{12401,12409,14801,14809,11101,13301,13309,14301,14305;12;1;29;;E} | R14: #FNOBES{12401,12409,14801,14809,11101,13301,13309,14301,14305;12;1;43;;E} | S14: #FNOBES{12401,12409,14801,14809,11101,13301,13309,14301,14305;12;1;41;;E} | T14: #FNOBES{12401,12409,14801,14809,11101,13301,13309,14301,14305;12;1;51;;E} | U14: #FNOBES{12401,12409,14801,14809,11101,13301,13309,14301,14305;12;1;61;;E} | V14: =C14-I14-J14-L14-M14-N14-O14-P14-Q14-R14-S14-T14-U14 -> #VALUE! | X14: =SUM(I14:V14) -> #VALUE! | Y14: =C14-X14 -> #VALUE! | AU14: #FNECTCP{11103,11105,12405,13305,15617,15701,15705;12;1;;E}
B15: Предприниматели без обр. юр.лица | C15: =D15+G15 -> #VALUE! | D15: #FNECTC{12601,12609,15001,15005,11101,13301,13309,14301,14305,15605;11;1;;E} | E15: #FNECTC{15701,15705;11;1;;E} | F15: #FNECTCP{12601,12609,15001,15005,11101,13301,13309,14301,14305,15605;11;1;;E} | G15: =E15+F15 -> #VALUE! | H15: #FN4{1;12601-12609,15001,15005} | I15: #FNOBES{12601,12609,15001,15005,11101,13301,13309,14301,14305,15605;11;1;25;;E} | J15: #FNOBES{12601,12609,15001,15005,11101,13301,13309,14301,14305,15605;11;1;42;;E} | L15: #FNOBES{12601,12609,15001,15005,11101,13301,13309,14301,14305,15605;11;1;23;;E} | M15: #FNOBES{12601,12609,15001,15005,11101,13301,13309,14301,14305,15605;11;1;26;;E} | N15: #FNOBES{12601,12609,15001,15005,11101,13301,13309,14301,14305,15605;11;1;21,22;;E} | O15: #FNOBES{12601,12609,15001,15005,11101,13301,13309,14301,14305,15605;11;1;24;;E} | P15: #FNOBES{12601,12609,15001,15005,11101,13301,13309,14301,14305,15605;11;1;31,32,33,34,35,36,37;;E} | Q15: #FNOBES{12601,12609,15001,15005,11101,13301,13309,14301,14305,15605;11;1;29;;E} | R15: #FNOBES{12601,12609,15001,15005,11101,13301,13309,14301,14305,15605;11;1;43;;E} | S15: #FNOBES{12601,12609,15001,15005,11101,13301,13309,14301,14305,15605;11;1;41;;E} | T15: #FNOBES{12601,12609,15001,15005,11101,13301,13309,14301,14305,15605;11;1;51;;E} | U15: #FNOBES{12601,12609,15001,15005,11101,13301,13309,14301,14305,15605;11;1;61;;E} | V15: =C15-I15-J15-L15-M15-N15-O15-P15-Q15-R15-S15-T15-U15 -> #VALUE! | X15: =SUM(I15:V15) -> #VALUE! | Y15: =C15-X15 -> #VALUE! | AU15: #FNECTCP{11103,11105,12605,13305,15617,15701,15705;11;1;;E}
B16: Негосударственные, некомерческие организации | C16: =D16+G16 -> #VALUE! | D16: #FNECTC{13001,13009,15201,15205,11101,13301,13309,14301,14305,15611;03;1;;E} | E16: #FNECTC{15701,15705;03;1;;E} | F16: #FNECTCP{13001,13009,15201,15205,11101,13301,13309,14301,14305,15611;03;1;;E} | G16: =E16+F16 -> #VALUE! | H16: #FN4{1;13001-13009,15201-15205} | I16: #FNOBES{13001,13009,15201,15205,11101,13301,13309,14301,14305,15611;03;1;25;;E} | J16: #FNOBES{13001,13009,15201,15205,11101,13301,13309,14301,14305,15611;03;1;42;;E} | L16: #FNOBES{13001,13009,15201,15205,11101,13301,13309,14301,14305,15611;03;1;23;;E} | M16: #FNOBES{13001,13009,15201,15205,11101,13301,13309,14301,14305,15611;03;1;26;;E} | N16: #FNOBES{13001,13009,15201,15205,11101,13301,13309,14301,14305,15611;03;1;21,22;;E} | O16: #FNOBES{13001,13009,15201,15205,11101,13301,13309,14301,14305,15611;03;1;24;;E} | P16: #FNOBES{13001,13009,15201,15205,11101,13301,13309,14301,14305,15611;03;1;31,32,33,34,35,36,37;;E} | Q16: #FNOBES{13001,13009,15201,15205,11101,13301,13309,14301,14305,15611;03;1;29;;E} | R16: #FNOBES{13001,13009,15201,15205,11101,13301,13309,14301,14305,15611;03;1;43;;E} | S16: #FNOBES{13001,13009,15201,15205,11101,13301,13309,14301,14305,15611;03;1;41;;E} | T16: #FNOBES{13001,13009,15201,15205,11101,13301,13309,14301,14305,15611;03;1;51;;E} | U16: #FNOBES{13001,13009,15201,15205,11101,13301,13309,14301,14305,15611;03;1;61;;E} | V16: =C16-I16-J16-L16-M16-N16-O16-P16-Q16-R16-S16-T16-U16 -> #VALUE! | X16: =SUM(I16:V16) -> #VALUE! | Y16: =C16-X16 -> #VALUE! | AU16: #FNECTCP{11103,11105,13005,13305,15617,15701,15705;03;1;;E}
B17: Небанковские финансовые институты | C17: =D17+G17 -> #VALUE! | D17: #FNECTC{13201,13209,15401,15405,11101,13301,13309,14301,14305;04;1;;E} | E17: #FNECTC{15701,15705;04;1;;E} | F17: #FNECTCP{13201,13209,15401,15405,11101,13301,13309,14301,14305;04;1;;E} | G17: =E17+F17 -> #VALUE! | H17: #FN4{1;13201-13209,15401-15405} | I17: #FNOBES{13201,13209,15401,15405,11101,13301,13309,14301,14305;04;1;25;;E} | J17: #FNOBES{13201,13209,15401,15405,11101,13301,13309,14301,14305;04;1;42;;E} | L17: #FNOBES{13201,13209,15401,15405,11101,13301,13309,14301,14305;04;1;23;;E} | M17: #FNOBES{13201,13209,15401,15405,11101,13301,13309,14301,14305;04;1;26;;E} | N17: #FNOBES{13201,13209,15401,15405,11101,13301,13309,14301,14305;04;1;21,22;;E} | O17: #FNOBES{13201,13209,15401,15405,11101,13301,13309,14301,14305;04;1;24;;E} | P17: #FNOBES{13201,13209,15401,15405,11101,13301,13309,14301,14305;04;1;31,32,33,34,35,36,37;;E} | Q17: #FNOBES{13201,13209,15401,15405,11101,13301,13309,14301,14305;04;1;29;;E} | R17: #FNOBES{13201,13209,15401,15405,11101,13301,13309,14301,14305;04;1;43;;E} | S17: #FNOBES{13201,13209,15401,15405,11101,13301,13309,14301,14305;04;1;41;;E} | T17: #FNOBES{13201,13209,15401,15405,11101,13301,13309,14301,14305;04;1;51;;E} | U17: #FNOBES{13201,13209,15401,15405,11101,13301,13309,14301,14305;04;1;61;;E} | V17: =C17-I17-J17-L17-M17-N17-O17-P17-Q17-R17-S17-T17-U17 -> #VALUE! | X17: =SUM(I17:V17) -> #VALUE! | Y17: =C17-X17 -> #VALUE! | AU17: #FNECTCP{11103,11105,13205,13305,15617,15701,15705;04;1;;E}
A18: 60 | B18: Прочие | C18: =SUM(C14:C17) -> #VALUE! | D18: =SUM(D14:D17) -> 0 | E18: =SUM(E14:E17) -> 0 | F18: =SUM(F14:F17) -> 0 | G18: =SUM(G14:G17) -> #VALUE! | H18: =IF(C18=0,0,(H14*(C14/C18))+(H15*(C15/C18))+(H16*(C16/C18))+(H17*(C17/C18))) -> #VALUE! | I18: =SUM(I14:I17) -> 0 | J18: =SUM(J14:J17) -> 0 | L18: =SUM(L14:L17) -> 0 | M18: =SUM(M14:M17) -> 0 | N18: =SUM(N14:N17) -> 0 | O18: =SUM(O14:O17) -> 0 | P18: =SUM(P14:P17) -> 0 | Q18: =SUM(Q14:Q17) -> 0 | R18: =SUM(R14:R17) -> 0 | S18: =SUM(S14:S17) -> 0 | ... U18: =SUM(U14:U17) -> 0 | V18: =C18-I18-J18-L18-M18-N18-O18-P18-Q18-R18-S18-T18-U18 -> #VALUE! | X18: =SUM(I18:V18) -> #VALUE! | Y18: =C18-X18 -> #VALUE!
A19: 70 | B19: Итого по промышленности | C19: =SUM(C9:C13)+C18 -> #VALUE! | D19: =SUM(D9:D13)+D18 -> 0 | E19: =SUM(E9:E13)+E18 -> 0 | F19: =SUM(F9:F13)+F18 -> 0 | G19: =SUM(G9:G13)+G18 -> #VALUE! | H19: =IF(C19=0,"",(H9*(C9/C19))+(H10*(C10/C19))+(H11*(C11/C19))+(H12*(C12/C19))+(H13*(C13/C19))) -> #VALUE! | I19: =SUM(I9:I13)+I18 -> 0 | J19: =SUM(J9:J13)+J18 -> 0 | L19: =SUM(L9:L13)+L18 -> 0 | M19: =SUM(M9:M13)+M18 -> 0 | N19: =SUM(N9:N13)+N18 -> 0 | O19: =SUM(O9:O13)+O18 -> 0 | P19: =SUM(P9:P13)+P18 -> 0 | Q19: =SUM(Q9:Q13)+Q18 -> 0 | R19: =SUM(R9:R13)+R18 -> 0 | S19: =SUM(S9:S13)+S18 -> 0 | ... U19: =SUM(U9:U13)+U18 -> 0 | V19: =C19-I19-J19-L19-M19-N19-O19-P19-Q19-R19-S19-T19-U19 -> #VALUE! | X19: =SUM(I19:V19) -> #VALUE! | Y19: =C19-X19 -> #VALUE! | AU19: =SUM(AU9:AU17) -> 0
B20: Сельское хозяйство
A21: 80 | B21: Физические лица | C21: =D21+G21 -> #VALUE! | D21: =D162 -> #FNECTC{12501,12509,14901,14905,11101,13301,13309,14301,14305,15603;08;2;;E} | E21: =E162 -> #FNECTC{15701,15705;08;2;;E} | F21: =F162 -> #FNECTCP{12501,12509,14901,14905,11101,13301,13309,14301,14305,15603;08;2;;E} | G21: =G162 -> #VALUE! | H21: =H162 -> #FN4{;12501-12509,14901,14905} | I21: =I162 -> #FNOBES{12501,12509,14901,14905,11101,13301,13309,14301,14305,15603;08;2;25;;E} | J21: =J162 -> #FNOBES{12501,12509,14901,14905,11101,13301,13309,14301,14305,15603;08;2;42;;E} | L21: =L162 -> #FNOBES{12501,12509,14901,14905,11101,13301,13309,14301,14305,15603;08;2;23;;E} | M21: =M162 -> #FNOBES{12501,12509,14901,14905,11101,13301,13309,14301,14305,15603;08;2;26;;E} | N21: =N162 -> #FNOBES{12501,12509,14901,14905,11101,13301,13309,14301,14305,15603;08;2;21,22;;E} | O21: =O162 -> #FNOBES{12501,12509,14901,14905,11101,13301,13309,14301,14305,15603;08;2;24;;E} | P21: =P162 -> #FNOBES{12501,12509,14901,14905,11101,13301,13309,14301,14305,15603;08;2;31,32,33,34,35,36,37;;E} | Q21: =Q162 -> #FNOBES{12501,12509,14901,14905,11101,13301,13309,14301,14305,15603;08;2;29;;E} | R21: =R162 -> #FNOBES{12501,12509,14901,14905,11101,13301,13309,14301,14305,15603;08;2;43;;E} | S21: =S162 -> #FNOBES{12501,12509,14901,14905,11101,13301,13309,14301,14305,15603;08;2;41;;E} | ... U21: =U162 -> #FNOBES{12501,12509,14901,14905,11101,13301,13309,14301,14305,15603;08;2;61;;E} | V21: =C21-I21-J21-L21-M21-N21-O21-P21-Q21-R21-S21-T21-U21 -> #VALUE! | X21: =SUM(I21:V21) -> #VALUE! | Y21: =C21-X21 -> #VALUE! | AU21: #FNECTCP{11103,11105,12505,13305,15617,15703,15705;08;2;;E}
A22: 90 | B22: Гос. предприятия | C22: =D22+G22 -> #VALUE! | D22: =D165 -> #VALUE! | E22: =E165 -> #VALUE! | F22: =F165 -> #VALUE! | G22: =G165 -> #VALUE! | H22: =H165 -> #VALUE! | I22: =I165 -> #VALUE! | J22: =J165 -> #VALUE! | L22: =L165 -> #VALUE! | M22: =M165 -> #VALUE! | N22: =N165 -> #VALUE! | O22: =O165 -> #VALUE! | P22: =P165 -> #VALUE! | Q22: =Q165 -> #VALUE! | R22: =R165 -> #VALUE! | S22: =S165 -> #VALUE! | ... U22: =U165 -> #VALUE! | V22: =C22-I22-J22-L22-M22-N22-O22-P22-Q22-R22-S22-T22-U22 -> #VALUE! | X22: =SUM(I22:V22) -> #VALUE! | Y22: =C22-X22 -> #VALUE! | AU22: #FNECTCP{11103,11105,12705,13305,15617,15701,15705;02;2;;E}
A23: 100 | B23: Совместные предприятия | C23: =D23+G23 -> #VALUE! | D23: =D168 -> #VALUE! | E23: =E168 -> #VALUE! | F23: =F168 -> #VALUE! | G23: =G168 -> #VALUE! | H23: =H168 -> #VALUE! | I23: =I168 -> #VALUE! | J23: =J168 -> #VALUE! | L23: =L168 -> #VALUE! | M23: =M168 -> #VALUE! | N23: =N168 -> #VALUE! | O23: =O168 -> #VALUE! | P23: =P168 -> #VALUE! | Q23: =Q168 -> #VALUE! | R23: =R168 -> #VALUE! | S23: =S168 -> #VALUE! | ... U23: =U168 -> #VALUE! | V23: =C23-I23-J23-L23-M23-N23-O23-P23-Q23-R23-S23-T23-U23 -> #VALUE! | X23: =SUM(I23:V23) -> #VALUE! | Y23: =C23-X23 -> #VALUE! | AU23: #FNECTCP{11103,11105,12905,13305,15617,15701,15705;10;2;;E}
A24: 110 | B24: Частные товарищества и корпорации | C24: =D24+G24 -> #VALUE! | D24: =D171 -> #VALUE! | E24: =E171 -> #VALUE! | F24: =F171 -> #VALUE! | G24: =G171 -> #VALUE! | H24: =H171 -> #VALUE! | I24: =I171 -> #VALUE! | J24: =J171 -> #VALUE! | L24: =L171 -> #VALUE! | M24: =M171 -> #VALUE! | N24: =N171 -> #VALUE! | O24: =O171 -> #VALUE! | P24: =P171 -> #VALUE! | Q24: =Q171 -> #VALUE! | R24: =R171 -> #VALUE! | S24: =S171 -> #VALUE! | ... U24: =U171 -> #VALUE! | V24: =C24-I24-J24-L24-M24-N24-O24-P24-Q24-R24-S24-T24-U24 -> #VALUE! | X24: =SUM(I24:V24) -> #VALUE! | Y24: =C24-X24 -> #VALUE! | AU24: #FNECTCP{11103,11105,13105,13305,15617,15701,15705;09;2;;E}
A25: 120 | B25: Фермерское хозяйство | C25: =D25+G25 -> 0 | D25: =D158 -> 0 | E25: =E158 -> 0 | F25: =F158 -> 0 | G25: =G158 -> 0 | H25: =H158 -> 0 | I25: =I158 -> 0 | J25: =J158 -> 0 | L25: =L158 -> 0 | M25: =M158 -> 0 | N25: =N158 -> 0 | O25: =O158 -> 0 | P25: =P158 -> 0 | Q25: =Q158 -> 0 | R25: =R158 -> 0 | S25: =S158 -> 0 | ... U25: =U158 -> 0 | V25: =C25-I25-J25-L25-M25-N25-O25-P25-Q25-R25-S25-T25-U25 -> 0
A26: 130 | B26: Правительство | C26: =D26+G26 -> #VALUE! | D26: =D145 -> #VALUE! | E26: =E145 -> #VALUE! | F26: =F145 -> #VALUE! | G26: =G145 -> #VALUE! | H26: =H145 -> #VALUE! | I26: =I145 -> #VALUE! | J26: =J145 -> #VALUE! | L26: =L145 -> #VALUE! | M26: =M145 -> #VALUE! | N26: =N145 -> #VALUE! | O26: =O145 -> #VALUE! | P26: =P145 -> #VALUE! | Q26: =Q145 -> #VALUE! | R26: =R145 -> #VALUE! | S26: =S145 -> #VALUE! | ... U26: =U145 -> #VALUE! | V26: =C26-I26-J26-L26-M26-N26-O26-P26-Q26-R26-S26-T26-U26 -> #VALUE! | X26: =SUM(I26:V26) -> #VALUE! | Y26: =C26-X26 -> #VALUE! | AU26: #FNECTCP{11103,11105,12305,13305,15617,15701,15705;01;2;;E}
B27: Бюджетные организации | C27: =D27+G27 -> #VALUE! | D27: =D154 -> #VALUE! | E27: =E154 -> #VALUE! | F27: =F154 -> #VALUE! | G27: =G154 -> #VALUE! | H27: =H154 -> #VALUE! | I27: =I154 -> #VALUE! | J27: =J154 -> #VALUE! | L27: =L154 -> #VALUE! | M27: =M154 -> #VALUE! | N27: =N154 -> #VALUE! | O27: =O154 -> #VALUE! | P27: =P154 -> #VALUE! | Q27: =Q154 -> #VALUE! | R27: =R154 -> #VALUE! | S27: =S154 -> #VALUE! | ... U27: =U154 -> #VALUE! | V27: =C27-I27-J27-L27-M27-N27-O27-P27-Q27-R27-S27-T27-U27 -> #VALUE! | X27: =SUM(I27:V27) -> #VALUE! | Y27: =C27-X27 -> #VALUE! | AU27: #FNECTCP{11103,11105,12405,13305,15617,15701,15705;12;2;;E}
B28: Предприниматели без обр. юр.лица | C28: =D28+G28 -> #VALUE! | D28: =D190 -> #VALUE! | E28: =E190 -> #VALUE! | F28: =F190 -> #VALUE! | G28: =G190 -> #VALUE! | H28: =H190 -> #VALUE! | I28: =I190 -> #VALUE! | J28: =J190 -> #VALUE! | L28: =L190 -> #VALUE! | M28: =M190 -> #VALUE! | N28: =N190 -> #VALUE! | O28: =O190 -> #VALUE! | P28: =P190 -> #VALUE! | Q28: =Q190 -> #VALUE! | R28: =R190 -> #VALUE! | S28: =S190 -> #VALUE! | ... U28: =U190 -> #VALUE! | V28: =C28-I28-J28-L28-M28-N28-O28-P28-Q28-R28-S28-T28-U28 -> #VALUE! | X28: =SUM(I28:V28) -> #VALUE! | Y28: =C28-X28 -> #VALUE! | AU28: #FNECTCP{11103,11105,12605,13305,15617,15701,15705;11;2;;E}
B29: Негосударственные, некомерческие организации | C29: =D29+G29 -> #VALUE! | D29: =D184 -> #VALUE! | E29: =E184 -> #VALUE! | F29: =F184 -> #VALUE! | G29: =G184 -> #VALUE! | H29: =H184 -> #VALUE! | I29: =I184 -> #VALUE! | J29: =J184 -> #VALUE! | L29: =L184 -> #VALUE! | M29: =M184 -> #VALUE! | N29: =N184 -> #VALUE! | O29: =O184 -> #VALUE! | P29: =P184 -> #VALUE! | Q29: =Q184 -> #VALUE! | R29: =R184 -> #VALUE! | S29: =S184 -> #VALUE! | ... U29: =U184 -> #VALUE! | V29: =C29-I29-J29-L29-M29-N29-O29-P29-Q29-R29-S29-T29-U29 -> #VALUE! | X29: =SUM(I29:V29) -> #VALUE! | Y29: =C29-X29 -> #VALUE! | AU29: #FNECTCP{11103,11105,13005,13305,15617,15701,15705;03;2;;E}
B30: Небанковские финансовые институты | C30: =D30+G30 -> #VALUE! | D30: =D181 -> #VALUE! | E30: =E181 -> #VALUE! | F30: =F181 -> #VALUE! | G30: =G181 -> #VALUE! | H30: =H181 -> #VALUE! | I30: =I181 -> #VALUE! | J30: =J181 -> #VALUE! | L30: =L181 -> #VALUE! | M30: =M181 -> #VALUE! | N30: =N181 -> #VALUE! | O30: =O181 -> #VALUE! | P30: =P181 -> #VALUE! | Q30: =Q181 -> #VALUE! | R30: =R181 -> #VALUE! | S30: =S181 -> #VALUE! | ... U30: =U181 -> #VALUE! | V30: =C30-I30-J30-L30-M30-N30-O30-P30-Q30-R30-S30-T30-U30 -> #VALUE! | X30: =SUM(I30:V30) -> #VALUE! | Y30: =C30-X30 -> #VALUE! | AU30: #FNECTCP{11103,11105,13205,13305,15617,15701,15705;04;2;;E}
A31: 140 | B31: Прочие | C31: =SUM(C27:C30) -> #VALUE! | D31: =SUM(D27:D30) -> #VALUE! | E31: =SUM(E27:E30) -> #VALUE! | F31: =SUM(F27:F30) -> #VALUE! | G31: =SUM(G27:G30) -> #VALUE! | H31: =IF(C31=0,0,(H27*(C27/C31))+(H28*(C28/C31))+(H29*(C29/C31))+(H30*(C30/C31))) -> #VALUE! | I31: =SUM(I27:I30) -> #VALUE! | J31: =SUM(J27:J30) -> #VALUE! | L31: =SUM(L27:L30) -> #VALUE! | M31: =SUM(M27:M30) -> #VALUE! | N31: =SUM(N27:N30) -> #VALUE! | O31: =SUM(O27:O30) -> #VALUE! | P31: =SUM(P27:P30) -> #VALUE! | Q31: =SUM(Q27:Q30) -> #VALUE! | R31: =SUM(R27:R30) -> #VALUE! | S31: =SUM(S27:S30) -> #VALUE! | ... U31: =SUM(U27:U30) -> #VALUE! | V31: =C31-I31-J31-L31-M31-N31-O31-P31-Q31-R31-S31-T31-U31 -> #VALUE! | X31: =SUM(I31:V31) -> #VALUE! | Y31: =C31-X31 -> #VALUE!
A32: 150 | B32: Итого по сельскому хозяйству | C32: =SUM(C21:C26)+C31 -> #VALUE! | D32: =SUM(D21:D26)+D31 -> #VALUE! | E32: =SUM(E21:E26)+E31 -> #VALUE! | F32: =SUM(F21:F26)+F31 -> #VALUE! | G32: =SUM(G21:G26)+G31 -> #VALUE! | H32: =IF(C32=0,"",(H21*(C21/C32))+(H22*(C22/C32))+(H23*(C23/C32))+(H24*(C24/C32))+(H25*(C25/C32))+(H26*(C26/C32))) -> #VALUE! | I32: =SUM(I21:I26)+I31 -> #VALUE! | J32: =SUM(J21:J26)+J31 -> #VALUE! | L32: =SUM(L21:L26)+L31 -> #VALUE! | M32: =SUM(M21:M26)+M31 -> #VALUE! | N32: =SUM(N21:N26)+N31 -> #VALUE! | O32: =SUM(O21:O26)+O31 -> #VALUE! | P32: =SUM(P21:P26)+P31 -> #VALUE! | Q32: =SUM(Q21:Q26)+Q31 -> #VALUE! | R32: =SUM(R21:R26)+R31 -> #VALUE! | S32: =SUM(S21:S26)+S31 -> #VALUE! | ... U32: =SUM(U21:U26)+U31 -> #VALUE! | V32: =C32-I32-J32-L32-M32-N32-O32-P32-Q32-R32-S32-T32-U32 -> #VALUE! | X32: =SUM(I32:V32) -> #VALUE! | Y32: =C32-X32 -> #VALUE! | AU32: =SUM(AU27:AU30) -> 0
B33: Транспорт и коммуникации
A34: 160 | B34: Физические лица | C34: =D34+G34 -> #VALUE! | D34: #FNECTC{12501,12509,14901,14905,11101,13301,13309,14301,14305,15603;08;5;;E} | E34: #FNECTC{15701,15705;08;5;;E} | F34: #FNECTCP{12501,12509,14901,14905,11101,13301,13309,14301,14305,15603;08;5;;E} | G34: =E34+F34 -> #VALUE! | H34: #FN4{;12501-12509,14901,14905} | I34: #FNOBES{12501,12509,14901,14905,11101,13301,13309,14301,14305,15603;08;5;25;;E} | J34: #FNOBES{12501,12509,14901,14905,11101,13301,13309,14301,14305,15603;08;5;42;;E} | L34: #FNOBES{12501,12509,14901,14905,11101,13301,13309,14301,14305,15603;08;5;23;;E} | M34: #FNOBES{12501,12509,14901,14905,11101,13301,13309,14301,14305,15603;08;5;26;;E} | N34: #FNOBES{12501,12509,14901,14905,11101,13301,13309,14301,14305,15603;08;5;21,22;;E} | O34: #FNOBES{12501,12509,14901,14905,11101,13301,13309,14301,14305,15603;08;5;24;;E} | P34: #FNOBES{12501,12509,14901,14905,11101,13301,13309,14301,14305,15603;08;5;31,32,33,34,35,36,37;;E} | Q34: #FNOBES{12501,12509,14901,14905,11101,13301,13309,14301,14305,15603;08;5;29;;E} | R34: #FNOBES{12501,12509,14901,14905,11101,13301,13309,14301,14305,15603;08;5;43;;E} | S34: #FNOBES{12501,12509,14901,14905,11101,13301,13309,14301,14305,15603;08;5;41;;E} | T34: #FNOBES{12501,12509,14901,14905,11101,13301,13309,14301,14305,15603;08;5;51;;E} | U34: #FNOBES{12501,12509,14901,14905,11101,13301,13309,14301,14305,15603;08;5;61;;E} | V34: =C34-I34-J34-L34-M34-N34-O34-P34-Q34-R34-S34-T34-U34 -> #VALUE! | X34: =SUM(I34:V34) -> #VALUE! | Y34: =C34-X34 -> #VALUE! | AU34: #FNECTCP{11103,11105,12505,13305,15617,15703,15705;08;5;;E}
A35: 170 | B35: Гос. предприятия | C35: =D35+G35 -> #VALUE! | D35: #FNECTC{12701,12709,15101,15105,11101,13301,13309,14301,14305,15607;02;5;;E} | E35: #FNECTC{15701,15705;02;5;;E} | F35: #FNECTCP{12701,12709,15101,15105,11101,13301,13309,14301,14305,15607;02;5;;E} | G35: =E35+F35 -> #VALUE! | H35: #FN4{5;12701-12709,15101,15105} | I35: #FNOBES{12701,12709,15101,15105,11101,13301,13309,14301,14305,15607;02;5;25;;E} | J35: #FNOBES{12701,12709,15101,15105,11101,13301,13309,14301,14305,15607;02;5;42;;E} | L35: #FNOBES{12701,12709,15101,15105,11101,13301,13309,14301,14305,15607;02;5;23;;E} | M35: #FNOBES{12701,12709,15101,15105,11101,13301,13309,14301,14305,15607;02;5;26;;E} | N35: #FNOBES{12701,12709,15101,15105,11101,13301,13309,14301,14305,15607;02;5;21,22;;E} | O35: #FNOBES{12701,12709,15101,15105,11101,13301,13309,14301,14305,15607;02;5;24;;E} | P35: #FNOBES{12701,12709,15101,15105,11101,13301,13309,14301,14305,15607;02;5;31,32,33,34,35,36,37;;E} | Q35: #FNOBES{12701,12709,15101,15105,11101,13301,13309,14301,14305,15607;02;5;29;;E} | R35: #FNOBES{12701,12709,15101,15105,11101,13301,13309,14301,14305,15607;02;5;43;;E} | S35: #FNOBES{12701,12709,15101,15105,11101,13301,13309,14301,14305,15607;02;5;41;;E} | T35: #FNOBES{12701,12709,15101,15105,11101,13301,13309,14301,14305,15607;02;5;51;;E} | U35: #FNOBES{12701,12709,15101,15105,11101,13301,13309,14301,14305,15607;02;5;61;;E} | V35: =C35-I35-J35-L35-M35-N35-O35-P35-Q35-R35-S35-T35-U35 -> #VALUE! | X35: =SUM(I35:V35) -> #VALUE! | Y35: =C35-X35 -> #VALUE! | AU35: #FNECTCP{11103,11105,12705,13305,15617,15701,15705;02;5;;E}
A36: 180 | B36: Совместные предприятия | C36: =D36+G36 -> #VALUE! | D36: #FNECTC{12901,12909,15301,15305,11101,13301,13309,14301,14305,15609;10;5;;E} | E36: #FNECTC{15701,15705;10;5;;E} | F36: #FNECTCP{12901,12909,15301,15305,11101,13301,13309,14301,14305,15609;10;5;;E} | G36: =E36+F36 -> #VALUE! | H36: #FN4{5;12901-12909,15301,15305} | I36: #FNOBES{12901,12909,15301,15305,11101,13301,13309,14301,14305,15609;10;5;25;;E} | J36: #FNOBES{12901,12909,15301,15305,11101,13301,13309,14301,14305,15609;10;5;42;;E} | L36: #FNOBES{12901,12909,15301,15305,11101,13301,13309,14301,14305,15609;10;5;23;;E} | M36: #FNOBES{12901,12909,15301,15305,11101,13301,13309,14301,14305,15609;10;5;26;;E} | N36: #FNOBES{12901,12909,15301,15305,11101,13301,13309,14301,14305,15609;10;5;21,22;;E} | O36: #FNOBES{12901,12909,15301,15305,11101,13301,13309,14301,14305,15609;10;5;24;;E} | P36: #FNOBES{12901,12909,15301,15305,11101,13301,13309,14301,14305,15609;10;5;31,32,33,34,35,36,37;;E} | Q36: #FNOBES{12901,12909,15301,15305,11101,13301,13309,14301,14305,15609;10;5;29;;E} | R36: #FNOBES{12901,12909,15301,15305,11101,13301,13309,14301,14305,15609;10;5;43;;E} | S36: #FNOBES{12901,12909,15301,15305,11101,13301,13309,14301,14305,15609;10;5;41;;E} | T36: #FNOBES{12901,12909,15301,15305,11101,13301,13309,14301,14305,15609;10;5;51;;E} | U36: #FNOBES{12901,12909,15301,15305,11101,13301,13309,14301,14305,15609;10;5;61;;E} | V36: =C36-I36-J36-L36-M36-N36-O36-P36-Q36-R36-S36-T36-U36 -> #VALUE! | X36: =SUM(I36:V36) -> #VALUE! | Y36: =C36-X36 -> #VALUE! | AU36: #FNECTCP{11103,11105,12905,13305,15617,15701,15705;10;5;;E}
A37: 190 | B37: Частные товарищества и корпорации | C37: =D37+G37 -> #VALUE! | D37: #FNECTC{13101,13109,15501,15505,11101,13301,13309,14301,14305,15613;09;5;;E} | E37: #FNECTC{15701,15705;09;5;;E} | F37: #FNECTCP{13101,13109,15501,15505,11101,13301,13309,14301,14305,15613;09;5;;E} | G37: =E37+F37 -> #VALUE! | H37: #FN4{5;13101-13109,15501-15505} | I37: #FNOBES{13101,13109,15501,15505,11101,13301,13309,14301,14305,15613;09;5;25;;E} | J37: #FNOBES{13101,13109,15501,15505,11101,13301,13309,14301,14305,15613;09;5;42;;E} | L37: #FNOBES{13101,13109,15501,15505,11101,13301,13309,14301,14305,15613;09;5;23;;E} | M37: #FNOBES{13101,13109,15501,15505,11101,13301,13309,14301,14305,15613;09;5;26;;E} | N37: #FNOBES{13101,13109,15501,15505,11101,13301,13309,14301,14305,15613;09;5;21,22;;E} | O37: #FNOBES{13101,13109,15501,15505,11101,13301,13309,14301,14305,15613;09;5;24;;E} | P37: #FNOBES{13101,13109,15501,15505,11101,13301,13309,14301,14305,15613;09;5;31,32,33,34,35,36,37;;E} | Q37: #FNOBES{13101,13109,15501,15505,11101,13301,13309,14301,14305,15613;09;5;29;;E} | R37: #FNOBES{13101,13109,15501,15505,11101,13301,13309,14301,14305,15613;09;5;43;;E} | S37: #FNOBES{13101,13109,15501,15505,11101,13301,13309,14301,14305,15613;09;5;41;;E} | T37: #FNOBES{13101,13109,15501,15505,11101,13301,13309,14301,14305,15613;09;5;51;;E} | U37: #FNOBES{13101,13109,15501,15505,11101,13301,13309,14301,14305,15613;09;5;61;;E} | V37: =C37-I37-J37-L37-M37-N37-O37-P37-Q37-R37-S37-T37-U37 -> #VALUE! | X37: =SUM(I37:V37) -> #VALUE! | Y37: =C37-X37 -> #VALUE! | AU37: #FNECTCP{11103,11105,13105,13305,15617,15701,15705;09;5;;E}
A38: 200 | B38: Правительство | C38: =D38+G38 -> #VALUE! | D38: #FNECTC{12301,12309,14701,14705,11101,13301,13309,14301,14305;01;5;;E} | E38: #FNECTC{15701,15705;01;5;;E} | F38: #FNECTCP{12301,12309,14701,14705,11101,13301,13309,14301,14305;01;5;;E} | G38: =E38+F38 -> #VALUE! | H38: #FN4{5;12301-12309,14701,14705} | I38: #FNOBES{12301,12309,14701,14705,11101,13301,13309,14301,14305;01;5;25;;E} | J38: #FNOBES{12301,12309,14701,14705,11101,13301,13309,14301,14305;01;5;42;;E} | L38: #FNOBES{12301,12309,14701,14705,11101,13301,13309,14301,14305;01;5;23;;E} | M38: #FNOBES{12301,12309,14701,14705,11101,13301,13309,14301,14305;01;5;26;;E} | N38: #FNOBES{12301,12309,14701,14705,11101,13301,13309,14301,14305;01;5;21,22;;E} | O38: #FNOBES{12301,12309,14701,14705,11101,13301,13309,14301,14305;01;5;24;;E} | P38: #FNOBES{12301,12309,14701,14705,11101,13301,13309,14301,14305;01;5;31,32,33,34,35,36,37;;E} | Q38: #FNOBES{12301,12309,14701,14705,11101,13301,13309,14301,14305;01;5;29;;E} | R38: #FNOBES{12301,12309,14701,14705,11101,13301,13309,14301,14305;01;5;43;;E} | S38: #FNOBES{12301,12309,14701,14705,11101,13301,13309,14301,14305;01;5;41;;E} | T38: #FNOBES{12301,12309,14701,14705,11101,13301,13309,14301,14305;01;5;51;;E} | U38: #FNOBES{12301,12309,14701,14705,11101,13301,13309,14301,14305;01;5;61;;E} | V38: =C38-I38-J38-L38-M38-N38-O38-P38-Q38-R38-S38-T38-U38 -> #VALUE! | X38: =SUM(I38:V38) -> #VALUE! | Y38: =C38-X38 -> #VALUE! | AU38: #FNECTCP{11103,11105,12305,13305,15617,15701,15705;01;5;;E}
B39: Бюджетные организации | C39: =D39+G39 -> #VALUE! | D39: #FNECTC{12401,12409,14801,14809,11101,13301,13309,14301,14305;12;5;;E} | E39: #FNECTC{15701,15705;12;5;;E} | F39: #FNECTCP{12401,12409,14801,14809,11101,13301,13309,14301,14305;12;5;;E} | G39: =E39+F39 -> #VALUE! | H39: #FN4{5;12401-12409,14801,14809} | I39: #FNOBES{12401,12409,14801,14809,11101,13301,13309,14301,14305;12;5;25;;E} | J39: #FNOBES{12401,12409,14801,14809,11101,13301,13309,14301,14305;12;5;42;;E} | L39: #FNOBES{12401,12409,14801,14809,11101,13301,13309,14301,14305;12;5;23;;E} | M39: #FNOBES{12401,12409,14801,14809,11101,13301,13309,14301,14305;12;5;26;;E} | N39: #FNOBES{12401,12409,14801,14809,11101,13301,13309,14301,14305;12;5;21,22;;E} | O39: #FNOBES{12401,12409,14801,14809,11101,13301,13309,14301,14305;12;5;24;;E} | P39: #FNOBES{12401,12409,14801,14809,11101,13301,13309,14301,14305;12;5;31,32,33,34,35,36,37;;E} | Q39: #FNOBES{12401,12409,14801,14809,11101,13301,13309,14301,14305;12;5;29;;E} | R39: #FNOBES{12401,12409,14801,14809,11101,13301,13309,14301,14305;12;5;43;;E} | S39: #FNOBES{12401,12409,14801,14809,11101,13301,13309,14301,14305;12;5;41;;E} | T39: #FNOBES{12401,12409,14801,14809,11101,13301,13309,14301,14305;12;5;51;;E} | U39: #FNOBES{12401,12409,14801,14809,11101,13301,13309,14301,14305;12;5;61;;E} | V39: =C39-I39-J39-L39-M39-N39-O39-P39-Q39-R39-S39-T39-U39 -> #VALUE! | X39: =SUM(I39:V39) -> #VALUE! | Y39: =C39-X39 -> #VALUE! | AU39: #FNECTCP{11103,11105,12405,13305,15617,15701,15705;12;5;;E}
B40: Предприниматели без обр. юр.лица | C40: =D40+G40 -> #VALUE! | D40: #FNECTC{12601,12609,15001,15005,11101,13301,13309,14301,14305,15605;11;5;;E} | E40: #FNECTC{15701,15705;11;5;;E} | F40: #FNECTCP{12601,12609,15001,15005,11101,13301,13309,14301,14305,15605;11;5;;E} | G40: =E40+F40 -> #VALUE! | H40: #FN4{5;12601-12609,15001,15005} | I40: #FNOBES{12601,12609,15001,15005,11101,13301,13309,14301,14305,15605;11;5;25;;E} | J40: #FNOBES{12601,12609,15001,15005,11101,13301,13309,14301,14305,15605;11;5;42;;E} | L40: #FNOBES{12601,12609,15001,15005,11101,13301,13309,14301,14305,15605;11;5;23;;E} | M40: #FNOBES{12601,12609,15001,15005,11101,13301,13309,14301,14305,15605;11;5;26;;E} | N40: #FNOBES{12601,12609,15001,15005,11101,13301,13309,14301,14305,15605;11;5;21,22;;E} | O40: #FNOBES{12601,12609,15001,15005,11101,13301,13309,14301,14305,15605;11;5;24;;E} | P40: #FNOBES{12601,12609,15001,15005,11101,13301,13309,14301,14305,15605;11;5;31,32,33,34,35,36,37;;E} | Q40: #FNOBES{12601,12609,15001,15005,11101,13301,13309,14301,14305,15605;11;5;29;;E} | R40: #FNOBES{12601,12609,15001,15005,11101,13301,13309,14301,14305,15605;11;5;43;;E} | S40: #FNOBES{12601,12609,15001,15005,11101,13301,13309,14301,14305,15605;11;5;41;;E} | T40: #FNOBES{12601,12609,15001,15005,11101,13301,13309,14301,14305,15605;11;5;51;;E} | U40: #FNOBES{12601,12609,15001,15005,11101,13301,13309,14301,14305,15605;11;5;61;;E} | V40: =C40-I40-J40-L40-M40-N40-O40-P40-Q40-R40-S40-T40-U40 -> #VALUE! | X40: =SUM(I40:V40) -> #VALUE! | Y40: =C40-X40 -> #VALUE! | AU40: #FNECTCP{11103,11105,12605,13305,15617,15701,15705;11;5;;E}
B41: Негосударственные, некомерческие организации | C41: =D41+G41 -> #VALUE! | D41: #FNECTC{13001,13009,15201,15205,11101,13301,13309,14301,14305,15611;03;5;;E} | E41: #FNECTC{15701,15705;03;5;;E} | F41: #FNECTCP{13001,13009,15201,15205,11101,13301,13309,14301,14305,15611;03;5;;E} | G41: =E41+F41 -> #VALUE! | H41: #FN4{5;13001-13009,15201-15205} | I41: #FNOBES{13001,13009,15201,15205,11101,13301,13309,14301,14305,15611;03;5;25;;E} | J41: #FNOBES{13001,13009,15201,15205,11101,13301,13309,14301,14305,15611;03;5;42;;E} | L41: #FNOBES{13001,13009,15201,15205,11101,13301,13309,14301,14305,15611;03;5;23;;E} | M41: #FNOBES{13001,13009,15201,15205,11101,13301,13309,14301,14305,15611;03;5;26;;E} | N41: #FNOBES{13001,13009,15201,15205,11101,13301,13309,14301,14305,15611;03;5;21,22;;E} | O41: #FNOBES{13001,13009,15201,15205,11101,13301,13309,14301,14305,15611;03;5;24;;E} | P41: #FNOBES{13001,13009,15201,15205,11101,13301,13309,14301,14305,15611;03;5;31,32,33,34,35,36,37;;E} | Q41: #FNOBES{13001,13009,15201,15205,11101,13301,13309,14301,14305,15611;03;5;29;;E} | R41: #FNOBES{13001,13009,15201,15205,11101,13301,13309,14301,14305,15611;03;5;43;;E} | S41: #FNOBES{13001,13009,15201,15205,11101,13301,13309,14301,14305,15611;03;5;41;;E} | T41: #FNOBES{13001,13009,15201,15205,11101,13301,13309,14301,14305,15611;03;5;51;;E} | U41: #FNOBES{13001,13009,15201,15205,11101,13301,13309,14301,14305,15611;03;5;61;;E} | V41: =C41-I41-J41-L41-M41-N41-O41-P41-Q41-R41-S41-T41-U41 -> #VALUE! | X41: =SUM(I41:V41) -> #VALUE! | Y41: =C41-X41 -> #VALUE! | AU41: #FNECTCP{11103,11105,13005,13305,15617,15701,15705;03;5;;E}
B42: Небанковские финансовые институты | C42: =D42+G42 -> #VALUE! | D42: #FNECTC{13201,13209,15401,15405,11101,13301,13309,14301,14305;04;5;;E} | E42: #FNECTC{15701,15705;04;5;;E} | F42: #FNECTCP{13201,13209,15401,15405,11101,13301,13309,14301,14305;04;5;;E} | G42: =E42+F42 -> #VALUE! | H42: #FN4{5;13201-13209,15401-15405} | I42: #FNOBES{13201,13209,15401,15405,11101,13301,13309,14301,14305;04;5;25;;E} | J42: #FNOBES{13201,13209,15401,15405,11101,13301,13309,14301,14305;04;5;42;;E} | L42: #FNOBES{13201,13209,15401,15405,11101,13301,13309,14301,14305;04;5;23;;E} | M42: #FNOBES{13201,13209,15401,15405,11101,13301,13309,14301,14305;04;5;26;;E} | N42: #FNOBES{13201,13209,15401,15405,11101,13301,13309,14301,14305;04;5;21,22;;E} | O42: #FNOBES{13201,13209,15401,15405,11101,13301,13309,14301,14305;04;5;24;;E} | P42: #FNOBES{13201,13209,15401,15405,11101,13301,13309,14301,14305;04;5;31,32,33,34,35,36,37;;E} | Q42: #FNOBES{13201,13209,15401,15405,11101,13301,13309,14301,14305;04;5;29;;E} | R42: #FNOBES{13201,13209,15401,15405,11101,13301,13309,14301,14305;04;5;43;;E} | S42: #FNOBES{13201,13209,15401,15405,11101,13301,13309,14301,14305;04;5;41;;E} | T42: #FNOBES{13201,13209,15401,15405,11101,13301,13309,14301,14305;04;5;51;;E} | U42: #FNOBES{13201,13209,15401,15405,11101,13301,13309,14301,14305;04;5;61;;E} | V42: =C42-I42-J42-L42-M42-N42-O42-P42-Q42-R42-S42-T42-U42 -> #VALUE! | X42: =SUM(I42:V42) -> #VALUE! | Y42: =C42-X42 -> #VALUE! | AU42: #FNECTCP{11103,11105,13205,13305,15617,15701,15705;04;5;;E}
A43: 210 | B43: Прочие | C43: =SUM(C39:C42) -> #VALUE! | D43: =SUM(D39:D42) -> 0 | E43: =SUM(E39:E42) -> 0 | F43: =SUM(F39:F42) -> 0 | G43: =SUM(G39:G42) -> #VALUE! | H43: =IF(C43=0,0,(H39*(C39/C43))+(H40*(C40/C43))+(H41*(C41/C43))+(H42*(C42/C43))) -> #VALUE! | I43: =SUM(I39:I42) -> 0 | J43: =SUM(J39:J42) -> 0 | L43: =SUM(L39:L42) -> 0 | M43: =SUM(M39:M42) -> 0 | N43: =SUM(N39:N42) -> 0 | O43: =SUM(O39:O42) -> 0 | P43: =SUM(P39:P42) -> 0 | Q43: =SUM(Q39:Q42) -> 0 | R43: =SUM(R39:R42) -> 0 | S43: =SUM(S39:S42) -> 0 | ... U43: =SUM(U39:U42) -> 0 | V43: =C43-I43-J43-L43-M43-N43-O43-P43-Q43-R43-S43-T43-U43 -> #VALUE! | X43: =SUM(I43:V43) -> #VALUE! | Y43: =C43-X43 -> #VALUE!
A44: 220 | B44: Итого по транспорту и коммуникациям | C44: =SUM(C34:C38)+C43 -> #VALUE! | D44: =SUM(D34:D38)+D43 -> 0 | E44: =SUM(E34:E38)+E43 -> 0 | F44: =SUM(F34:F38)+F43 -> 0 | G44: =SUM(G34:G38)+G43 -> #VALUE! | H44: =IF(C44=0,"",(H34*(C34/C44))+(H35*(C35/C44))+(H36*(C36/C44))+(H37*(C37/C44))+(H38*(C38/C44))) -> #VALUE! | I44: =SUM(I34:I38)+I43 -> 0 | J44: =SUM(J34:J38)+J43 -> 0 | L44: =SUM(L34:L38)+L43 -> 0 | M44: =SUM(M34:M38)+M43 -> 0 | N44: =SUM(N34:N38)+N43 -> 0 | O44: =SUM(O34:O38)+O43 -> 0 | P44: =SUM(P34:P38)+P43 -> 0 | Q44: =SUM(Q34:Q38)+Q43 -> 0 | R44: =SUM(R34:R38)+R43 -> 0 | S44: =SUM(S34:S38)+S43 -> 0 | ... U44: =SUM(U34:U38)+U43 -> 0 | V44: =C44-I44-J44-L44-M44-N44-O44-P44-Q44-R44-S44-T44-U44 -> #VALUE! | X44: =SUM(I44:V44) -> #VALUE! | Y44: =C44-X44 -> #VALUE! | AU44: =SUM(AU39:AU43) -> 0
B45: Строительство
A46: 230 | B46: Физические лица | C46: =D46+G46 -> #VALUE! | D46: #FNECTC{12501,12509,14901,14905,11101,13301,13309,14301,14305,15603;08;6;;E} | E46: #FNECTC{15701,15705;08;6;;E} | F46: #FNECTCP{12501,12509,14901,14905,11101,13301,13309,14301,14305,15603;08;6;;E} | G46: =E46+F46 -> #VALUE! | H46: #FN4{;12501-12509,14901,14905} | I46: #FNOBES{12501,12509,14901,14905,11101,13301,13309,14301,14305,15603;08;6;25;;E} | J46: #FNOBES{12501,12509,14901,14905,11101,13301,13309,14301,14305,15603;08;6;42;;E} | L46: #FNOBES{12501,12509,14901,14905,11101,13301,13309,14301,14305,15603;08;6;23;;E} | M46: #FNOBES{12501,12509,14901,14905,11101,13301,13309,14301,14305,15603;08;6;26;;E} | N46: #FNOBES{12501,12509,14901,14905,11101,13301,13309,14301,14305,15603;08;6;21,22;;E} | O46: #FNOBES{12501,12509,14901,14905,11101,13301,13309,14301,14305,15603;08;6;24;;E} | P46: #FNOBES{12501,12509,14901,14905,11101,13301,13309,14301,14305,15603;08;6;31,32,33,34,35,36,37;;E} | Q46: #FNOBES{12501,12509,14901,14905,11101,13301,13309,14301,14305,15603;08;6;29;;E} | R46: #FNOBES{12501,12509,14901,14905,11101,13301,13309,14301,14305,15603;08;6;43;;E} | S46: #FNOBES{12501,12509,14901,14905,11101,13301,13309,14301,14305,15603;08;6;41;;E} | T46: #FNOBES{12501,12509,14901,14905,11101,13301,13309,14301,14305,15603;08;6;51;;E} | U46: #FNOBES{12501,12509,14901,14905,11101,13301,13309,14301,14305,15603;08;6;61;;E} | V46: =C46-I46-J46-L46-M46-N46-O46-P46-Q46-R46-S46-T46-U46 -> #VALUE! | X46: =SUM(I46:V46) -> #VALUE! | Y46: =C46-X46 -> #VALUE! | AU46: #FNECTCP{11103,11105,12505,13305,15617,15703,15705;08;6;;E}
A47: 240 | B47: Гос. предприятия | C47: =D47+G47 -> #VALUE! | D47: #FNECTC{12701,12709,15101,15105,11101,13301,13309,14301,14305,15607;02;6;;E} | E47: #FNECTC{15701,15705;02;6;;E} | F47: #FNECTCP{12701,12709,15101,15105,11101,13301,13309,14301,14305,15607;02;6;;E} | G47: =E47+F47 -> #VALUE! | H47: #FN4{6;12701-12709,15101,15105} | I47: #FNOBES{12701,12709,15101,15105,11101,13301,13309,14301,14305,15607;02;6;25;;E} | J47: #FNOBES{12701,12709,15101,15105,11101,13301,13309,14301,14305,15607;02;6;42;;E} | L47: #FNOBES{12701,12709,15101,15105,11101,13301,13309,14301,14305,15607;02;6;23;;E} | M47: #FNOBES{12701,12709,15101,15105,11101,13301,13309,14301,14305,15607;02;6;26;;E} | N47: #FNOBES{12701,12709,15101,15105,11101,13301,13309,14301,14305,15607;02;6;21,22;;E} | O47: #FNOBES{12701,12709,15101,15105,11101,13301,13309,14301,14305,15607;02;6;24;;E} | P47: #FNOBES{12701,12709,15101,15105,11101,13301,13309,14301,14305,15607;02;6;31,32,33,34,35,36,37;;E} | Q47: #FNOBES{12701,12709,15101,15105,11101,13301,13309,14301,14305,15607;02;6;29;;E} | R47: #FNOBES{12701,12709,15101,15105,11101,13301,13309,14301,14305,15607;02;6;43;;E} | S47: #FNOBES{12701,12709,15101,15105,11101,13301,13309,14301,14305,15607;02;6;41;;E} | T47: #FNOBES{12701,12709,15101,15105,11101,13301,13309,14301,14305,15607;02;6;51;;E} | U47: #FNOBES{12701,12709,15101,15105,11101,13301,13309,14301,14305,15607;02;6;61;;E} | V47: =C47-I47-J47-L47-M47-N47-O47-P47-Q47-R47-S47-T47-U47 -> #VALUE! | X47: =SUM(I47:V47) -> #VALUE! | Y47: =C47-X47 -> #VALUE! | AU47: #FNECTCP{11103,11105,12705,13305,15617,15701,15705;02;6;;E}
A48: 250 | B48: Совместные предприятия | C48: =D48+G48 -> #VALUE! | D48: #FNECTC{12901,12909,15301,15305,11101,13301,13309,14301,14305,15609;10;6;;E} | E48: #FNECTC{15701,15705;10;6;;E} | F48: #FNECTCP{12901,12909,15301,15305,11101,13301,13309,14301,14305,15609;10;6;;E} | G48: =E48+F48 -> #VALUE! | H48: #FN4{6;12901-12909,15301,15305} | I48: #FNOBES{12901,12909,15301,15305,11101,13301,13309,14301,14305,15609;10;6;25;;E} | J48: #FNOBES{12901,12909,15301,15305,11101,13301,13309,14301,14305,15609;10;6;42;;E} | L48: #FNOBES{12901,12909,15301,15305,11101,13301,13309,14301,14305,15609;10;6;23;;E} | M48: #FNOBES{12901,12909,15301,15305,11101,13301,13309,14301,14305,15609;10;6;26;;E} | N48: #FNOBES{12901,12909,15301,15305,11101,13301,13309,14301,14305,15609;10;6;21,22;;E} | O48: #FNOBES{12901,12909,15301,15305,11101,13301,13309,14301,14305,15609;10;6;24;;E} | P48: #FNOBES{12901,12909,15301,15305,11101,13301,13309,14301,14305,15609;10;6;31,32,33,34,35,36,37;;E} | Q48: #FNOBES{12901,12909,15301,15305,11101,13301,13309,14301,14305,15609;10;6;29;;E} | R48: #FNOBES{12901,12909,15301,15305,11101,13301,13309,14301,14305,15609;10;6;43;;E} | S48: #FNOBES{12901,12909,15301,15305,11101,13301,13309,14301,14305,15609;10;6;41;;E} | T48: #FNOBES{12901,12909,15301,15305,11101,13301,13309,14301,14305,15609;10;6;51;;E} | U48: #FNOBES{12901,12909,15301,15305,11101,13301,13309,14301,14305,15609;10;6;61;;E} | V48: =C48-I48-J48-L48-M48-N48-O48-P48-Q48-R48-S48-T48-U48 -> #VALUE! | X48: =SUM(I48:V48) -> #VALUE! | Y48: =C48-X48 -> #VALUE! | AU48: #FNECTCP{11103,11105,12905,13305,15617,15701,15705;10;6;;E}
A49: 260 | B49: Частные товарищества и корпорации | C49: =D49+G49 -> #VALUE! | D49: #FNECTC{13101,13109,15501,15505,11101,13301,13309,14301,14305,15613;09;6;;E} | E49: #FNECTC{15701,15705;09;6;;E} | F49: #FNECTCP{13101,13109,15501,15505,11101,13301,13309,14301,14305,15613;09;6;;E} | G49: =E49+F49 -> #VALUE! | H49: #FN4{6;13101-13109,15501-15505} | I49: #FNOBES{13101,13109,15501,15505,11101,13301,13309,14301,14305,15613;09;6;25;;E} | J49: #FNOBES{13101,13109,15501,15505,11101,13301,13309,14301,14305,15613;09;6;42;;E} | L49: #FNOBES{13101,13109,15501,15505,11101,13301,13309,14301,14305,15613;09;6;23;;E} | M49: #FNOBES{13101,13109,15501,15505,11101,13301,13309,14301,14305,15613;09;6;26;;E} | N49: #FNOBES{13101,13109,15501,15505,11101,13301,13309,14301,14305,15613;09;6;21,22;;E} | O49: #FNOBES{13101,13109,15501,15505,11101,13301,13309,14301,14305,15613;09;6;24;;E} | P49: #FNOBES{13101,13109,15501,15505,11101,13301,13309,14301,14305,15613;09;6;31,32,33,34,35,36,37;;E} | Q49: #FNOBES{13101,13109,15501,15505,11101,13301,13309,14301,14305,15613;09;6;29;;E} | R49: #FNOBES{13101,13109,15501,15505,11101,13301,13309,14301,14305,15613;09;6;43;;E} | S49: #FNOBES{13101,13109,15501,15505,11101,13301,13309,14301,14305,15613;09;6;41;;E} | T49: #FNOBES{13101,13109,15501,15505,11101,13301,13309,14301,14305,15613;09;6;51;;E} | U49: #FNOBES{13101,13109,15501,15505,11101,13301,13309,14301,14305,15613;09;6;61;;E} | V49: =C49-I49-J49-L49-M49-N49-O49-P49-Q49-R49-S49-T49-U49 -> #VALUE! | X49: =SUM(I49:V49) -> #VALUE! | Y49: =C49-X49 -> #VALUE! | AU49: #FNECTCP{11103,11105,13105,13305,15617,15701,15705;09;6;;E}
A50: 270 | B50: Правительство | C50: =D50+G50 -> #VALUE! | D50: #FNECTC{12301,12309,14701,14705,11101,13301,13309,14301,14305;01;6;;E} | E50: #FNECTC{15701,15705;01;6;;E} | F50: #FNECTCP{12301,12309,14701,14705,11101,13301,13309,14301,14305;01;6;;E} | G50: =E50+F50 -> #VALUE! | H50: #FN4{6;12301-12309,14701,14705} | I50: #FNOBES{12301,12309,14701,14705,11101,13301,13309,14301,14305;01;6;25;;E} | J50: #FNOBES{12301,12309,14701,14705,11101,13301,13309,14301,14305;01;6;42;;E} | L50: #FNOBES{12301,12309,14701,14705,11101,13301,13309,14301,14305;01;6;23;;E} | M50: #FNOBES{12301,12309,14701,14705,11101,13301,13309,14301,14305;01;6;26;;E} | N50: #FNOBES{12301,12309,14701,14705,11101,13301,13309,14301,14305;01;6;21,22;;E} | O50: #FNOBES{12301,12309,14701,14705,11101,13301,13309,14301,14305;01;6;24;;E} | P50: #FNOBES{12301,12309,14701,14705,11101,13301,13309,14301,14305;01;6;31,32,33,34,35,36,37;;E} | Q50: #FNOBES{12301,12309,14701,14705,11101,13301,13309,14301,14305;01;6;29;;E} | R50: #FNOBES{12301,12309,14701,14705,11101,13301,13309,14301,14305;01;6;43;;E} | S50: #FNOBES{12301,12309,14701,14705,11101,13301,13309,14301,14305;01;6;41;;E} | T50: #FNOBES{12301,12309,14701,14705,11101,13301,13309,14301,14305;01;6;51;;E} | U50: #FNOBES{12301,12309,14701,14705,11101,13301,13309,14301,14305;01;6;61;;E} | V50: =C50-I50-J50-L50-M50-N50-O50-P50-Q50-R50-S50-T50-U50 -> #VALUE! | X50: =SUM(I50:V50) -> #VALUE! | Y50: =C50-X50 -> #VALUE! | AU50: #FNECTCP{11103,11105,12305,13305,15617,15701,15705;01;6;;E}
B51: Бюджетные организации | C51: =D51+G51 -> #VALUE! | D51: #FNECTC{12401,12409,14801,14809,11101,13301,13309,14301,14305;12;6;;E} | E51: #FNECTC{15701,15705;12;6;;E} | F51: #FNECTCP{12401,12409,14801,14809,11101,13301,13309,14301,14305;12;6;;E} | G51: =E51+F51 -> #VALUE! | H51: #FN4{6;12401-12409,14801,14809} | I51: #FNOBES{12401,12409,14801,14809,11101,13301,13309,14301,14305;12;6;25;;E} | J51: #FNOBES{12401,12409,14801,14809,11101,13301,13309,14301,14305;12;6;42;;E} | L51: #FNOBES{12401,12409,14801,14809,11101,13301,13309,14301,14305;12;6;23;;E} | M51: #FNOBES{12401,12409,14801,14809,11101,13301,13309,14301,14305;12;6;26;;E} | N51: #FNOBES{12401,12409,14801,14809,11101,13301,13309,14301,14305;12;6;21,22;;E} | O51: #FNOBES{12401,12409,14801,14809,11101,13301,13309,14301,14305;12;6;24;;E} | P51: #FNOBES{12401,12409,14801,14809,11101,13301,13309,14301,14305;12;6;31,32,33,34,35,36,37;;E} | Q51: #FNOBES{12401,12409,14801,14809,11101,13301,13309,14301,14305;12;6;29;;E} | R51: #FNOBES{12401,12409,14801,14809,11101,13301,13309,14301,14305;12;6;43;;E} | S51: #FNOBES{12401,12409,14801,14809,11101,13301,13309,14301,14305;12;6;41;;E} | T51: #FNOBES{12401,12409,14801,14809,11101,13301,13309,14301,14305;12;6;51;;E} | U51: #FNOBES{12401,12409,14801,14809,11101,13301,13309,14301,14305;12;6;61;;E} | V51: =C51-I51-J51-L51-M51-N51-O51-P51-Q51-R51-S51-T51-U51 -> #VALUE! | X51: =SUM(I51:V51) -> #VALUE! | Y51: =C51-X51 -> #VALUE! | AU51: #FNECTCP{11103,11105,12405,13305,15617,15701,15705;12;6;;E}
B52: Предприниматели без обр. юр.лица | C52: =D52+G52 -> #VALUE! | D52: #FNECTC{12601,12609,15001,15005,11101,13301,13309,14301,14305,15605;11;6;;E} | E52: #FNECTC{15701,15705;11;6;;E} | F52: #FNECTCP{12601,12609,15001,15005,11101,13301,13309,14301,14305,15605;11;6;;E} | G52: =E52+F52 -> #VALUE! | H52: #FN4{6;12601-12609,15001,15005} | I52: #FNOBES{12601,12609,15001,15005,11101,13301,13309,14301,14305,15605;11;6;25;;E} | J52: #FNOBES{12601,12609,15001,15005,11101,13301,13309,14301,14305,15605;11;6;42;;E} | L52: #FNOBES{12601,12609,15001,15005,11101,13301,13309,14301,14305,15605;11;6;23;;E} | M52: #FNOBES{12601,12609,15001,15005,11101,13301,13309,14301,14305,15605;11;6;26;;E} | N52: #FNOBES{12601,12609,15001,15005,11101,13301,13309,14301,14305,15605;11;6;21,22;;E} | O52: #FNOBES{12601,12609,15001,15005,11101,13301,13309,14301,14305,15605;11;6;24;;E} | P52: #FNOBES{12601,12609,15001,15005,11101,13301,13309,14301,14305,15605;11;6;31,32,33,34,35,36,37;;E} | Q52: #FNOBES{12601,12609,15001,15005,11101,13301,13309,14301,14305,15605;11;6;29;;E} | R52: #FNOBES{12601,12609,15001,15005,11101,13301,13309,14301,14305,15605;11;6;43;;E} | S52: #FNOBES{12601,12609,15001,15005,11101,13301,13309,14301,14305,15605;11;6;41;;E} | T52: #FNOBES{12601,12609,15001,15005,11101,13301,13309,14301,14305,15605;11;6;51;;E} | U52: #FNOBES{12601,12609,15001,15005,11101,13301,13309,14301,14305,15605;11;6;61;;E} | V52: =C52-I52-J52-L52-M52-N52-O52-P52-Q52-R52-S52-T52-U52 -> #VALUE! | X52: =SUM(I52:V52) -> #VALUE! | Y52: =C52-X52 -> #VALUE! | AU52: #FNECTCP{11103,11105,12605,13305,15617,15701,15705;11;6;;E}
B53: Негосударственные, некомерческие организации | C53: =D53+G53 -> #VALUE! | D53: #FNECTC{13001,13009,15201,15205,11101,13301,13309,14301,14305,15611;03;6;;E} | E53: #FNECTC{15701,15705;03;6;;E} | F53: #FNECTCP{13001,13009,15201,15205,11101,13301,13309,14301,14305,15611;03;6;;E} | G53: =E53+F53 -> #VALUE! | H53: #FN4{6;13001-13009,15201-15205} | I53: #FNOBES{13001,13009,15201,15205,11101,13301,13309,14301,14305,15611;03;6;25;;E} | J53: #FNOBES{13001,13009,15201,15205,11101,13301,13309,14301,14305,15611;03;6;42;;E} | L53: #FNOBES{13001,13009,15201,15205,11101,13301,13309,14301,14305,15611;03;6;23;;E} | M53: #FNOBES{13001,13009,15201,15205,11101,13301,13309,14301,14305,15611;03;6;26;;E} | N53: #FNOBES{13001,13009,15201,15205,11101,13301,13309,14301,14305,15611;03;6;21,22;;E} | O53: #FNOBES{13001,13009,15201,15205,11101,13301,13309,14301,14305,15611;03;6;24;;E} | P53: #FNOBES{13001,13009,15201,15205,11101,13301,13309,14301,14305,15611;03;6;31,32,33,34,35,36,37;;E} | Q53: #FNOBES{13001,13009,15201,15205,11101,13301,13309,14301,14305,15611;03;6;29;;E} | R53: #FNOBES{13001,13009,15201,15205,11101,13301,13309,14301,14305,15611;03;6;43;;E} | S53: #FNOBES{13001,13009,15201,15205,11101,13301,13309,14301,14305,15611;03;6;41;;E} | T53: #FNOBES{13001,13009,15201,15205,11101,13301,13309,14301,14305,15611;03;6;51;;E} | U53: #FNOBES{13001,13009,15201,15205,11101,13301,13309,14301,14305,15611;03;6;61;;E} | V53: =C53-I53-J53-L53-M53-N53-O53-P53-Q53-R53-S53-T53-U53 -> #VALUE! | X53: =SUM(I53:V53) -> #VALUE! | Y53: =C53-X53 -> #VALUE! | AU53: #FNECTCP{11103,11105,13005,13305,15617,15701,15705;03;6;;E}
B54: Небанковские финансовые институты | C54: =D54+G54 -> #VALUE! | D54: #FNECTC{13201,13209,15401,15405,11101,13301,13309,14301,14305;04;6;;E} | E54: #FNECTC{15701,15705;04;6;;E} | F54: #FNECTCP{13201,13209,15401,15405,11101,13301,13309,14301,14305;04;6;;E} | G54: =E54+F54 -> #VALUE! | H54: #FN4{6;13201-13209,15401-15405} | I54: #FNOBES{13201,13209,15401,15405,11101,13301,13309,14301,14305;04;6;25;;E} | J54: #FNOBES{13201,13209,15401,15405,11101,13301,13309,14301,14305;04;6;42;;E} | L54: #FNOBES{13201,13209,15401,15405,11101,13301,13309,14301,14305;04;6;23;;E} | M54: #FNOBES{13201,13209,15401,15405,11101,13301,13309,14301,14305;04;6;26;;E} | N54: #FNOBES{13201,13209,15401,15405,11101,13301,13309,14301,14305;04;6;21,22;;E} | O54: #FNOBES{13201,13209,15401,15405,11101,13301,13309,14301,14305;04;6;24;;E} | P54: #FNOBES{13201,13209,15401,15405,11101,13301,13309,14301,14305;04;6;31,32,33,34,35,36,37;;E} | Q54: #FNOBES{13201,13209,15401,15405,11101,13301,13309,14301,14305;04;6;29;;E} | R54: #FNOBES{13201,13209,15401,15405,11101,13301,13309,14301,14305;04;6;43;;E} | S54: #FNOBES{13201,13209,15401,15405,11101,13301,13309,14301,14305;04;6;41;;E} | T54: #FNOBES{13201,13209,15401,15405,11101,13301,13309,14301,14305;04;6;51;;E} | U54: #FNOBES{13201,13209,15401,15405,11101,13301,13309,14301,14305;04;6;61;;E} | V54: =C54-I54-J54-L54-M54-N54-O54-P54-Q54-R54-S54-T54-U54 -> #VALUE! | X54: =SUM(I54:V54) -> #VALUE! | Y54: =C54-X54 -> #VALUE! | AU54: #FNECTCP{11103,11105,13205,13305,15617,15701,15705;04;6;;E}
A55: 280 | B55: Прочие | C55: =SUM(C51:C54) -> #VALUE! | D55: =SUM(D51:D54) -> 0 | E55: =SUM(E51:E54) -> 0 | F55: =SUM(F51:F54) -> 0 | G55: =SUM(G51:G54) -> #VALUE! | H55: =IF(C55=0,0,(H51*(C51/C55))+(H52*(C52/C55))+(H53*(C53/C55))+(H54*(C54/C55))) -> #VALUE! | I55: =SUM(I51:I54) -> 0 | J55: =SUM(J51:J54) -> 0 | L55: =SUM(L51:L54) -> 0 | M55: =SUM(M51:M54) -> 0 | N55: =SUM(N51:N54) -> 0 | O55: =SUM(O51:O54) -> 0 | P55: =SUM(P51:P54) -> 0 | Q55: =SUM(Q51:Q54) -> 0 | R55: =SUM(R51:R54) -> 0 | S55: =SUM(S51:S54) -> 0 | ... U55: =SUM(U51:U54) -> 0 | V55: =C55-I55-J55-L55-M55-N55-O55-P55-Q55-R55-S55-T55-U55 -> #VALUE! | X55: =SUM(I55:V55) -> #VALUE! | Y55: =C55-X55 -> #VALUE!
A56: 290 | B56: Итого по строительству | C56: =SUM(C46:C50)+C55 -> #VALUE! | D56: =SUM(D46:D50)+D55 -> 0 | E56: =SUM(E46:E50)+E55 -> 0 | F56: =SUM(F46:F50)+F55 -> 0 | G56: =SUM(G46:G50)+G55 -> #VALUE! | H56: =IF(C56=0,"",(H46*(C46/C56))+(H47*(C47/C56))+(H48*(C48/C56))+(H49*(C49/C56))+(H50*(C50/C56))) -> #VALUE! | I56: =SUM(I46:I50)+I55 -> 0 | J56: =SUM(J46:J50)+J55 -> 0 | L56: =SUM(L46:L50)+L55 -> 0 | M56: =SUM(M46:M50)+M55 -> 0 | N56: =SUM(N46:N50)+N55 -> 0 | O56: =SUM(O46:O50)+O55 -> 0 | P56: =SUM(P46:P50)+P55 -> 0 | Q56: =SUM(Q46:Q50)+Q55 -> 0 | R56: =SUM(R46:R50)+R55 -> 0 | S56: =SUM(S46:S50)+S55 -> 0 | ... U56: =SUM(U46:U50)+U55 -> 0 | V56: =C56-I56-J56-L56-M56-N56-O56-P56-Q56-R56-S56-T56-U56 -> #VALUE! | X56: =SUM(I56:V56) -> #VALUE! | Y56: =C56-X56 -> #VALUE! | AU56: =SUM(AU51:AU55) -> 0
B57: Торговля и общественное питание
A58: 300 | B58: Физические лица | C58: =D58+G58 -> #VALUE! | D58: #FNECTC{12501,12509,14901,14905,11101,13301,13309,14301,14305,15603;08;7;;E} | E58: #FNECTC{15701,15705;08;7;;E} | F58: #FNECTCP{12501,12509,14901,14905,11101,13301,13309,14301,14305,15603;08;7;;E} | G58: =E58+F58 -> #VALUE! | H58: #FN4{;12501-12509,14901,14905} | I58: #FNOBES{12501,12509,14901,14905,11101,13301,13309,14301,14305,15603;08;7;25;;E} | J58: #FNOBES{12501,12509,14901,14905,11101,13301,13309,14301,14305,15603;08;7;42;;E} | L58: #FNOBES{12501,12509,14901,14905,11101,13301,13309,14301,14305,15603;08;7;23;;E} | M58: #FNOBES{12501,12509,14901,14905,11101,13301,13309,14301,14305,15603;08;7;26;;E} | N58: #FNOBES{12501,12509,14901,14905,11101,13301,13309,14301,14305,15603;08;7;21,22;;E} | O58: #FNOBES{12501,12509,14901,14905,11101,13301,13309,14301,14305,15603;08;7;24;;E} | P58: #FNOBES{12501,12509,14901,14905,11101,13301,13309,14301,14305,15603;08;7;31,32,33,34,35,36,37;;E} | Q58: #FNOBES{12501,12509,14901,14905,11101,13301,13309,14301,14305,15603;08;7;29;;E} | R58: #FNOBES{12501,12509,14901,14905,11101,13301,13309,14301,14305,15603;08;7;43;;E} | S58: #FNOBES{12501,12509,14901,14905,11101,13301,13309,14301,14305,15603;08;7;41;;E} | T58: #FNOBES{12501,12509,14901,14905,11101,13301,13309,14301,14305,15603;08;7;51;;E} | U58: #FNOBES{12501,12509,14901,14905,11101,13301,13309,14301,14305,15603;08;7;61;;E} | V58: =C58-I58-J58-L58-M58-N58-O58-P58-Q58-R58-S58-T58-U58 -> #VALUE! | X58: =SUM(I58:V58) -> #VALUE! | Y58: =C58-X58 -> #VALUE! | AU58: #FNECTCP{11103,11105,12505,13305,15617,15703,15705;08;7;;E}
A59: 310 | B59: Гос. предприятия | C59: =D59+G59 -> #VALUE! | D59: #FNECTC{12701,12709,15101,15105,11101,13301,13309,14301,14305,15607;02;7;;E} | E59: #FNECTC{15701,15705;02;7;;E} | F59: #FNECTCP{12701,12709,15101,15105,11101,13301,13309,14301,14305,15607;02;7;;E} | G59: =E59+F59 -> #VALUE! | H59: #FN4{7;12701-12709,15101,15105} | I59: #FNOBES{12701,12709,15101,15105,11101,13301,13309,14301,14305,15607;02;7;25;;E} | J59: #FNOBES{12701,12709,15101,15105,11101,13301,13309,14301,14305,15607;02;7;42;;E} | L59: #FNOBES{12701,12709,15101,15105,11101,13301,13309,14301,14305,15607;02;7;23;;E} | M59: #FNOBES{12701,12709,15101,15105,11101,13301,13309,14301,14305,15607;02;7;26;;E} | N59: #FNOBES{12701,12709,15101,15105,11101,13301,13309,14301,14305,15607;02;7;21,22;;E} | O59: #FNOBES{12701,12709,15101,15105,11101,13301,13309,14301,14305,15607;02;7;24;;E} | P59: #FNOBES{12701,12709,15101,15105,11101,13301,13309,14301,14305,15607;02;7;31,32,33,34,35,36,37;;E} | Q59: #FNOBES{12701,12709,15101,15105,11101,13301,13309,14301,14305,15607;02;7;29;;E} | R59: #FNOBES{12701,12709,15101,15105,11101,13301,13309,14301,14305,15607;02;7;43;;E} | S59: #FNOBES{12701,12709,15101,15105,11101,13301,13309,14301,14305,15607;02;7;41;;E} | T59: #FNOBES{12701,12709,15101,15105,11101,13301,13309,14301,14305,15607;02;7;51;;E} | U59: #FNOBES{12701,12709,15101,15105,11101,13301,13309,14301,14305,15607;02;7;61;;E} | V59: =C59-I59-J59-L59-M59-N59-O59-P59-Q59-R59-S59-T59-U59 -> #VALUE! | X59: =SUM(I59:V59) -> #VALUE! | Y59: =C59-X59 -> #VALUE! | AU59: #FNECTCP{11103,11105,12705,13305,15617,15701,15705;02;7;;E}
A60: 320 | B60: Совместные предприятия | C60: =D60+G60 -> #VALUE! | D60: #FNECTC{12901,12909,15301,15305,11101,13301,13309,14301,14305,15609;10;7;;E} | E60: #FNECTC{15701,15705;10;7;;E} | F60: #FNECTCP{12901,12909,15301,15305,11101,13301,13309,14301,14305,15609;10;7;;E} | G60: =E60+F60 -> #VALUE! | H60: #FN4{7;12901-12909,15301,15305} | I60: #FNOBES{12901,12909,15301,15305,11101,13301,13309,14301,14305,15609;10;7;25;;E} | J60: #FNOBES{12901,12909,15301,15305,11101,13301,13309,14301,14305,15609;10;7;42;;E} | L60: #FNOBES{12901,12909,15301,15305,11101,13301,13309,14301,14305,15609;10;7;23;;E} | M60: #FNOBES{12901,12909,15301,15305,11101,13301,13309,14301,14305,15609;10;7;26;;E} | N60: #FNOBES{12901,12909,15301,15305,11101,13301,13309,14301,14305,15609;10;7;21,22;;E} | O60: #FNOBES{12901,12909,15301,15305,11101,13301,13309,14301,14305,15609;10;7;24;;E} | P60: #FNOBES{12901,12909,15301,15305,11101,13301,13309,14301,14305,15609;10;7;31,32,33,34,35,36,37;;E} | Q60: #FNOBES{12901,12909,15301,15305,11101,13301,13309,14301,14305,15609;10;7;29;;E} | R60: #FNOBES{12901,12909,15301,15305,11101,13301,13309,14301,14305,15609;10;7;43;;E} | S60: #FNOBES{12901,12909,15301,15305,11101,13301,13309,14301,14305,15609;10;7;41;;E} | T60: #FNOBES{12901,12909,15301,15305,11101,13301,13309,14301,14305,15609;10;7;51;;E} | U60: #FNOBES{12901,12909,15301,15305,11101,13301,13309,14301,14305,15609;10;7;61;;E} | V60: =C60-I60-J60-L60-M60-N60-O60-P60-Q60-R60-S60-T60-U60 -> #VALUE! | X60: =SUM(I60:V60) -> #VALUE! | Y60: =C60-X60 -> #VALUE! | AU60: #FNECTCP{11103,11105,12905,13305,15617,15701,15705;10;7;;E}
A61: 330 | B61: Частные товарищества и корпорации | C61: =D61+G61 -> #VALUE! | D61: #FNECTC{13101,13109,15501,15505,11101,13301,13309,14301,14305,15613;09;7;;E} | E61: #FNECTC{15701,15705;09;7;;E} | F61: #FNECTCP{13101,13109,15501,15505,11101,13301,13309,14301,14305,15613;09;7;;E} | G61: =E61+F61 -> #VALUE! | H61: #FN4{7;13101-13109,15501-15505} | I61: #FNOBES{13101,13109,15501,15505,11101,13301,13309,14301,14305,15613;09;7;25;;E} | J61: #FNOBES{13101,13109,15501,15505,11101,13301,13309,14301,14305,15613;09;7;42;;E} | L61: #FNOBES{13101,13109,15501,15505,11101,13301,13309,14301,14305,15613;09;7;23;;E} | M61: #FNOBES{13101,13109,15501,15505,11101,13301,13309,14301,14305,15613;09;7;26;;E} | N61: #FNOBES{13101,13109,15501,15505,11101,13301,13309,14301,14305,15613;09;7;21,22;;E} | O61: #FNOBES{13101,13109,15501,15505,11101,13301,13309,14301,14305,15613;09;7;24;;E} | P61: #FNOBES{13101,13109,15501,15505,11101,13301,13309,14301,14305,15613;09;7;31,32,33,34,35,36,37;;E} | Q61: #FNOBES{13101,13109,15501,15505,11101,13301,13309,14301,14305,15613;09;7;29;;E} | R61: #FNOBES{13101,13109,15501,15505,11101,13301,13309,14301,14305,15613;09;7;43;;E} | S61: #FNOBES{13101,13109,15501,15505,11101,13301,13309,14301,14305,15613;09;7;41;;E} | T61: #FNOBES{13101,13109,15501,15505,11101,13301,13309,14301,14305,15613;09;7;51;;E} | U61: #FNOBES{13101,13109,15501,15505,11101,13301,13309,14301,14305,15613;09;7;61;;E} | V61: =C61-I61-J61-L61-M61-N61-O61-P61-Q61-R61-S61-T61-U61 -> #VALUE! | X61: =SUM(I61:V61) -> #VALUE! | Y61: =C61-X61 -> #VALUE! | AU61: #FNECTCP{11103,11105,13105,13305,15617,15701,15705;09;7;;E}
A62: 340 | B62: Правительство | C62: =D62+G62 -> #VALUE! | D62: #FNECTC{12301,12309,14701,14705,11101,13301,13309,14301,14305;01;7;;E} | E62: #FNECTC{15701,15705;01;7;;E} | F62: #FNECTCP{12301,12309,14701,14705,11101,13301,13309,14301,14305;01;7;;E} | G62: =E62+F62 -> #VALUE! | H62: #FN4{7;12301-12309,14701,14705} | I62: #FNOBES{12301,12309,14701,14705,11101,13301,13309,14301,14305;01;7;25;;E} | J62: #FNOBES{12301,12309,14701,14705,11101,13301,13309,14301,14305;01;7;42;;E} | L62: #FNOBES{12301,12309,14701,14705,11101,13301,13309,14301,14305;01;7;23;;E} | M62: #FNOBES{12301,12309,14701,14705,11101,13301,13309,14301,14305;01;7;26;;E} | N62: #FNOBES{12301,12309,14701,14705,11101,13301,13309,14301,14305;01;7;21,22;;E} | O62: #FNOBES{12301,12309,14701,14705,11101,13301,13309,14301,14305;01;7;24;;E} | P62: #FNOBES{12301,12309,14701,14705,11101,13301,13309,14301,14305;01;7;31,32,33,34,35,36,37;;E} | Q62: #FNOBES{12301,12309,14701,14705,11101,13301,13309,14301,14305;01;7;29;;E} | R62: #FNOBES{12301,12309,14701,14705,11101,13301,13309,14301,14305;01;7;43;;E} | S62: #FNOBES{12301,12309,14701,14705,11101,13301,13309,14301,14305;01;7;41;;E} | T62: #FNOBES{12301,12309,14701,14705,11101,13301,13309,14301,14305;01;7;51;;E} | U62: #FNOBES{12301,12309,14701,14705,11101,13301,13309,14301,14305;01;7;61;;E} | V62: =C62-I62-J62-L62-M62-N62-O62-P62-Q62-R62-S62-T62-U62 -> #VALUE! | X62: =SUM(I62:V62) -> #VALUE! | Y62: =C62-X62 -> #VALUE! | AU62: #FNECTCP{11103,11105,12305,13305,15617,15701,15705;01;7;;E}
B63: Бюджетные организации | C63: =D63+G63 -> #VALUE! | D63: #FNECTC{12401,12409,14801,14809,11101,13301,13309,14301,14305;12;7;;E} | E63: #FNECTC{15701,15705;12;7;;E} | F63: #FNECTCP{12401,12409,14801,14809,11101,13301,13309,14301,14305;12;7;;E} | G63: =E63+F63 -> #VALUE! | H63: #FN4{7;12401-12409,14801,14809} | I63: #FNOBES{12401,12409,14801,14809,11101,13301,13309,14301,14305;12;7;25;;E} | J63: #FNOBES{12401,12409,14801,14809,11101,13301,13309,14301,14305;12;7;42;;E} | L63: #FNOBES{12401,12409,14801,14809,11101,13301,13309,14301,14305;12;7;23;;E} | M63: #FNOBES{12401,12409,14801,14809,11101,13301,13309,14301,14305;12;7;26;;E} | N63: #FNOBES{12401,12409,14801,14809,11101,13301,13309,14301,14305;12;7;21,22;;E} | O63: #FNOBES{12401,12409,14801,14809,11101,13301,13309,14301,14305;12;7;24;;E} | P63: #FNOBES{12401,12409,14801,14809,11101,13301,13309,14301,14305;12;7;31,32,33,34,35,36,37;;E} | Q63: #FNOBES{12401,12409,14801,14809,11101,13301,13309,14301,14305;12;7;29;;E} | R63: #FNOBES{12401,12409,14801,14809,11101,13301,13309,14301,14305;12;7;43;;E} | S63: #FNOBES{12401,12409,14801,14809,11101,13301,13309,14301,14305;12;7;41;;E} | T63: #FNOBES{12401,12409,14801,14809,11101,13301,13309,14301,14305;12;7;51;;E} | U63: #FNOBES{12401,12409,14801,14809,11101,13301,13309,14301,14305;12;7;61;;E} | V63: =C63-I63-J63-L63-M63-N63-O63-P63-Q63-R63-S63-T63-U63 -> #VALUE! | X63: =SUM(I63:V63) -> #VALUE! | Y63: =C63-X63 -> #VALUE! | AU63: #FNECTCP{11103,11105,12405,13305,15617,15701,15705;12;7;;E}
B64: Предприниматели без обр. юр.лица | C64: =D64+G64 -> #VALUE! | D64: #FNECTC{12601,12609,15001,15005,11101,13301,13309,14301,14305,15605;11;7;;E} | E64: #FNECTC{15701,15705;11;7;;E} | F64: #FNECTCP{12601,12609,15001,15005,11101,13301,13309,14301,14305,15605;11;7;;E} | G64: =E64+F64 -> #VALUE! | H64: #FN4{7;12601-12609,15001,15005} | I64: #FNOBES{12601,12609,15001,15005,11101,13301,13309,14301,14305,15605;11;7;25;;E} | J64: #FNOBES{12601,12609,15001,15005,11101,13301,13309,14301,14305,15605;11;7;42;;E} | L64: #FNOBES{12601,12609,15001,15005,11101,13301,13309,14301,14305,15605;11;7;23;;E} | M64: #FNOBES{12601,12609,15001,15005,11101,13301,13309,14301,14305,15605;11;7;26;;E} | N64: #FNOBES{12601,12609,15001,15005,11101,13301,13309,14301,14305,15605;11;7;21,22;;E} | O64: #FNOBES{12601,12609,15001,15005,11101,13301,13309,14301,14305,15605;11;7;24;;E} | P64: #FNOBES{12601,12609,15001,15005,11101,13301,13309,14301,14305,15605;11;7;31,32,33,34,35,36,37;;E} | Q64: #FNOBES{12601,12609,15001,15005,11101,13301,13309,14301,14305,15605;11;7;29;;E} | R64: #FNOBES{12601,12609,15001,15005,11101,13301,13309,14301,14305,15605;11;7;43;;E} | S64: #FNOBES{12601,12609,15001,15005,11101,13301,13309,14301,14305,15605;11;7;41;;E} | T64: #FNOBES{12601,12609,15001,15005,11101,13301,13309,14301,14305,15605;11;7;51;;E} | U64: #FNOBES{12601,12609,15001,15005,11101,13301,13309,14301,14305,15605;11;7;61;;E} | V64: =C64-I64-J64-L64-M64-N64-O64-P64-Q64-R64-S64-T64-U64 -> #VALUE! | X64: =SUM(I64:V64) -> #VALUE! | Y64: =C64-X64 -> #VALUE! | AU64: #FNECTCP{11103,11105,12605,13305,15617,15701,15705;11;7;;E}
B65: Негосударственные, некомерческие организации | C65: =D65+G65 -> #VALUE! | D65: #FNECTC{13001,13009,15201,15205,11101,13301,13309,14301,14305,15611;03;7;;E} | E65: #FNECTC{15701,15705;03;7;;E} | F65: #FNECTCP{13001,13009,15201,15205,11101,13301,13309,14301,14305,15611;03;7;;E} | G65: =E65+F65 -> #VALUE! | H65: #FN4{7;13001-13009,15201-15205} | I65: #FNOBES{13001,13009,15201,15205,11101,13301,13309,14301,14305,15611;03;7;25;;E} | J65: #FNOBES{13001,13009,15201,15205,11101,13301,13309,14301,14305,15611;03;7;42;;E} | L65: #FNOBES{13001,13009,15201,15205,11101,13301,13309,14301,14305,15611;03;7;23;;E} | M65: #FNOBES{13001,13009,15201,15205,11101,13301,13309,14301,14305,15611;03;7;26;;E} | N65: #FNOBES{13001,13009,15201,15205,11101,13301,13309,14301,14305,15611;03;7;21,22;;E} | O65: #FNOBES{13001,13009,15201,15205,11101,13301,13309,14301,14305,15611;03;7;24;;E} | P65: #FNOBES{13001,13009,15201,15205,11101,13301,13309,14301,14305,15611;03;7;31,32,33,34,35,36,37;;E} | Q65: #FNOBES{13001,13009,15201,15205,11101,13301,13309,14301,14305,15611;03;7;29;;E} | R65: #FNOBES{13001,13009,15201,15205,11101,13301,13309,14301,14305,15611;03;7;43;;E} | S65: #FNOBES{13001,13009,15201,15205,11101,13301,13309,14301,14305,15611;03;7;41;;E} | T65: #FNOBES{13001,13009,15201,15205,11101,13301,13309,14301,14305,15611;03;7;51;;E} | U65: #FNOBES{13001,13009,15201,15205,11101,13301,13309,14301,14305,15611;03;7;61;;E} | V65: =C65-I65-J65-L65-M65-N65-O65-P65-Q65-R65-S65-T65-U65 -> #VALUE! | X65: =SUM(I65:V65) -> #VALUE! | Y65: =C65-X65 -> #VALUE! | AU65: #FNECTCP{11103,11105,13005,13305,15617,15701,15705;03;7;;E}
B66: Небанковские финансовые институты | C66: =D66+G66 -> #VALUE! | D66: #FNECTC{13201,13209,15401,15405,11101,13301,13309,14301,14305;04;7;;E} | E66: #FNECTC{15701,15705;04;7;;E} | F66: #FNECTCP{13201,13209,15401,15405,11101,13301,13309,14301,14305;04;7;;E} | G66: =E66+F66 -> #VALUE! | H66: #FN4{7;13201-13209,15401-15405} | I66: #FNOBES{13201,13209,15401,15405,11101,13301,13309,14301,14305;04;7;25;;E} | J66: #FNOBES{13201,13209,15401,15405,11101,13301,13309,14301,14305;04;7;42;;E} | L66: #FNOBES{13201,13209,15401,15405,11101,13301,13309,14301,14305;04;7;23;;E} | M66: #FNOBES{13201,13209,15401,15405,11101,13301,13309,14301,14305;04;7;26;;E} | N66: #FNOBES{13201,13209,15401,15405,11101,13301,13309,14301,14305;04;7;21,22;;E} | O66: #FNOBES{13201,13209,15401,15405,11101,13301,13309,14301,14305;04;7;24;;E} | P66: #FNOBES{13201,13209,15401,15405,11101,13301,13309,14301,14305;04;7;31,32,33,34,35,36,37;;E} | Q66: #FNOBES{13201,13209,15401,15405,11101,13301,13309,14301,14305;04;7;29;;E} | R66: #FNOBES{13201,13209,15401,15405,11101,13301,13309,14301,14305;04;7;43;;E} | S66: #FNOBES{13201,13209,15401,15405,11101,13301,13309,14301,14305;04;7;41;;E} | T66: #FNOBES{13201,13209,15401,15405,11101,13301,13309,14301,14305;04;7;51;;E} | U66: #FNOBES{13201,13209,15401,15405,11101,13301,13309,14301,14305;04;7;61;;E} | V66: =C66-I66-J66-L66-M66-N66-O66-P66-Q66-R66-S66-T66-U66 -> #VALUE! | X66: =SUM(I66:V66) -> #VALUE! | Y66: =C66-X66 -> #VALUE! | AU66: #FNECTCP{11103,11105,13205,13305,15617,15701,15705;04;7;;E}
A67: 350 | B67: Прочие | C67: =SUM(C63:C66) -> #VALUE! | D67: =SUM(D63:D66) -> 0 | E67: =SUM(E63:E66) -> 0 | F67: =SUM(F63:F66) -> 0 | G67: =SUM(G63:G66) -> #VALUE! | H67: =IF(C67=0,0,(H63*(C63/C67))+(H64*(C64/C67))+(H65*(C65/C67))+(H66*(C66/C67))) -> #VALUE! | I67: =SUM(I63:I66) -> 0 | J67: =SUM(J63:J66) -> 0 | L67: =SUM(L63:L66) -> 0 | M67: =SUM(M63:M66) -> 0 | N67: =SUM(N63:N66) -> 0 | O67: =SUM(O63:O66) -> 0 | P67: =SUM(P63:P66) -> 0 | Q67: =SUM(Q63:Q66) -> 0 | R67: =SUM(R63:R66) -> 0 | S67: =SUM(S63:S66) -> 0 | ... U67: =SUM(U63:U66) -> 0 | V67: =C67-I67-J67-L67-M67-N67-O67-P67-Q67-R67-S67-T67-U67 -> #VALUE! | X67: =SUM(I67:V67) -> #VALUE! | Y67: =C67-X67 -> #VALUE!
A68: 360 | B68: Итого по торговле и общественному питанию | C68: =SUM(C58:C62)+C67 -> #VALUE! | D68: =SUM(D58:D62)+D67 -> 0 | E68: =SUM(E58:E62)+E67 -> 0 | F68: =SUM(F58:F62)+F67 -> 0 | G68: =SUM(G58:G62)+G67 -> #VALUE! | H68: =IF(C68=0,"",(H58*(C58/C68))+(H59*(C59/C68))+(H60*(C60/C68))+(H61*(C61/C68))+(H62*(C62/C68))) -> #VALUE! | I68: =SUM(I58:I62)+I67 -> 0 | J68: =SUM(J58:J62)+J67 -> 0 | L68: =SUM(L58:L62)+L67 -> 0 | M68: =SUM(M58:M62)+M67 -> 0 | N68: =SUM(N58:N62)+N67 -> 0 | O68: =SUM(O58:O62)+O67 -> 0 | P68: =SUM(P58:P62)+P67 -> 0 | Q68: =SUM(Q58:Q62)+Q67 -> 0 | R68: =SUM(R58:R62)+R67 -> 0 | S68: =SUM(S58:S62)+S67 -> 0 | ... U68: =SUM(U58:U62)+U67 -> 0 | V68: =C68-I68-J68-L68-M68-N68-O68-P68-Q68-R68-S68-T68-U68 -> #VALUE! | X68: =SUM(I68:V68) -> #VALUE! | Y68: =C68-X68 -> #VALUE! | AU68: =SUM(AU63:AU67) -> 0
B69: Материально-техническое снабжение и сбыт
A70: 370 | B70: Физические лица | C70: =D70+G70 -> #VALUE! | D70: #FNECTC{12501,12509,14901,14905,11101,13301,13309,14301,14305,15603;08;8;;E} | E70: #FNECTC{15701,15705;08;8;;E} | F70: #FNECTCP{12501,12509,14901,14905,11101,13301,13309,14301,14305,15603;08;8;;E} | G70: =E70+F70 -> #VALUE! | H70: #FN4{;12501-12509,14901,14905} | I70: #FNOBES{12501,12509,14901,14905,11101,13301,13309,14301,14305,15603;08;8;25;;E} | J70: #FNOBES{12501,12509,14901,14905,11101,13301,13309,14301,14305,15603;08;8;42;;E} | L70: #FNOBES{12501,12509,14901,14905,11101,13301,13309,14301,14305,15603;08;8;23;;E} | M70: #FNOBES{12501,12509,14901,14905,11101,13301,13309,14301,14305,15603;08;8;26;;E} | N70: #FNOBES{12501,12509,14901,14905,11101,13301,13309,14301,14305,15603;08;8;21,22;;E} | O70: #FNOBES{12501,12509,14901,14905,11101,13301,13309,14301,14305,15603;08;8;24;;E} | P70: #FNOBES{12501,12509,14901,14905,11101,13301,13309,14301,14305,15603;08;8;31,32,33,34,35,36,37;;E} | Q70: #FNOBES{12501,12509,14901,14905,11101,13301,13309,14301,14305,15603;08;8;29;;E} | R70: #FNOBES{12501,12509,14901,14905,11101,13301,13309,14301,14305,15603;08;8;43;;E} | S70: #FNOBES{12501,12509,14901,14905,11101,13301,13309,14301,14305,15603;08;8;41;;E} | T70: #FNOBES{12501,12509,14901,14905,11101,13301,13309,14301,14305,15603;08;8;51;;E} | U70: #FNOBES{12501,12509,14901,14905,11101,13301,13309,14301,14305,15603;08;8;61;;E} | V70: =C70-I70-J70-L70-M70-N70-O70-P70-Q70-R70-S70-T70-U70 -> #VALUE! | X70: =SUM(I70:V70) -> #VALUE! | Y70: =C70-X70 -> #VALUE! | AU70: #FNECTCP{11103,11105,12505,13305,15617,15703,15705;08;8;;E}
A71: 380 | B71: Гос. предприятия | C71: =D71+G71 -> #VALUE! | D71: #FNECTC{12701,12709,15101,15105,11101,13301,13309,14301,14305,15607;02;8;;E} | E71: #FNECTC{15701,15705;02;8;;E} | F71: #FNECTCP{12701,12709,15101,15105,11101,13301,13309,14301,14305,15607;02;8;;E} | G71: =E71+F71 -> #VALUE! | H71: #FN4{8;12701-12709,15101,15105} | I71: #FNOBES{12701,12709,15101,15105,11101,13301,13309,14301,14305,15607;02;8;25;;E} | J71: #FNOBES{12701,12709,15101,15105,11101,13301,13309,14301,14305,15607;02;8;42;;E} | L71: #FNOBES{12701,12709,15101,15105,11101,13301,13309,14301,14305,15607;02;8;23;;E} | M71: #FNOBES{12701,12709,15101,15105,11101,13301,13309,14301,14305,15607;02;8;26;;E} | N71: #FNOBES{12701,12709,15101,15105,11101,13301,13309,14301,14305,15607;02;8;21,22;;E} | O71: #FNOBES{12701,12709,15101,15105,11101,13301,13309,14301,14305,15607;02;8;24;;E} | P71: #FNOBES{12701,12709,15101,15105,11101,13301,13309,14301,14305,15607;02;8;31,32,33,34,35,36,37;;E} | Q71: #FNOBES{12701,12709,15101,15105,11101,13301,13309,14301,14305,15607;02;8;29;;E} | R71: #FNOBES{12701,12709,15101,15105,11101,13301,13309,14301,14305,15607;02;8;43;;E} | S71: #FNOBES{12701,12709,15101,15105,11101,13301,13309,14301,14305,15607;02;8;41;;E} | T71: #FNOBES{12701,12709,15101,15105,11101,13301,13309,14301,14305,15607;02;8;51;;E} | U71: #FNOBES{12701,12709,15101,15105,11101,13301,13309,14301,14305,15607;02;8;61;;E} | V71: =C71-I71-J71-L71-M71-N71-O71-P71-Q71-R71-S71-T71-U71 -> #VALUE! | X71: =SUM(I71:V71) -> #VALUE! | Y71: =C71-X71 -> #VALUE! | AU71: #FNECTCP{11103,11105,12705,13305,15617,15701,15705;02;8;;E}
A72: 390 | B72: Совместные предприятия | C72: =D72+G72 -> #VALUE! | D72: #FNECTC{12901,12909,15301,15305,11101,13301,13309,14301,14305,15609;10;8;;E} | E72: #FNECTC{15701,15705;10;8;;E} | F72: #FNECTCP{12901,12909,15301,15305,11101,13301,13309,14301,14305,15609;10;8;;E} | G72: =E72+F72 -> #VALUE! | H72: #FN4{8;12901-12909,15301,15305} | I72: #FNOBES{12901,12909,15301,15305,11101,13301,13309,14301,14305,15609;10;8;25;;E} | J72: #FNOBES{12901,12909,15301,15305,11101,13301,13309,14301,14305,15609;10;8;42;;E} | L72: #FNOBES{12901,12909,15301,15305,11101,13301,13309,14301,14305,15609;10;8;23;;E} | M72: #FNOBES{12901,12909,15301,15305,11101,13301,13309,14301,14305,15609;10;8;26;;E} | N72: #FNOBES{12901,12909,15301,15305,11101,13301,13309,14301,14305,15609;10;8;21,22;;E} | O72: #FNOBES{12901,12909,15301,15305,11101,13301,13309,14301,14305,15609;10;8;24;;E} | P72: #FNOBES{12901,12909,15301,15305,11101,13301,13309,14301,14305,15609;10;8;31,32,33,34,35,36,37;;E} | Q72: #FNOBES{12901,12909,15301,15305,11101,13301,13309,14301,14305,15609;10;8;29;;E} | R72: #FNOBES{12901,12909,15301,15305,11101,13301,13309,14301,14305,15609;10;8;43;;E} | S72: #FNOBES{12901,12909,15301,15305,11101,13301,13309,14301,14305,15609;10;8;41;;E} | T72: #FNOBES{12901,12909,15301,15305,11101,13301,13309,14301,14305,15609;10;8;51;;E} | U72: #FNOBES{12901,12909,15301,15305,11101,13301,13309,14301,14305,15609;10;8;61;;E} | V72: =C72-I72-J72-L72-M72-N72-O72-P72-Q72-R72-S72-T72-U72 -> #VALUE! | X72: =SUM(I72:V72) -> #VALUE! | Y72: =C72-X72 -> #VALUE! | AU72: #FNECTCP{11103,11105,12905,13305,15617,15701,15705;10;8;;E}
A73: 400 | B73: Частные товарищества и корпорации | C73: =D73+G73 -> #VALUE! | D73: #FNECTC{13101,13109,15501,15505,11101,13301,13309,14301,14305,15613;09;8;;E} | E73: #FNECTC{15701,15705;09;8;;E} | F73: #FNECTCP{13101,13109,15501,15505,11101,13301,13309,14301,14305,15613;09;8;;E} | G73: =E73+F73 -> #VALUE! | H73: #FN4{8;13101-13109,15501-15505} | I73: #FNOBES{13101,13109,15501,15505,11101,13301,13309,14301,14305,15613;09;8;25;;E} | J73: #FNOBES{13101,13109,15501,15505,11101,13301,13309,14301,14305,15613;09;8;42;;E} | L73: #FNOBES{13101,13109,15501,15505,11101,13301,13309,14301,14305,15613;09;8;23;;E} | M73: #FNOBES{13101,13109,15501,15505,11101,13301,13309,14301,14305,15613;09;8;26;;E} | N73: #FNOBES{13101,13109,15501,15505,11101,13301,13309,14301,14305,15613;09;8;21,22;;E} | O73: #FNOBES{13101,13109,15501,15505,11101,13301,13309,14301,14305,15613;09;8;24;;E} | P73: #FNOBES{13101,13109,15501,15505,11101,13301,13309,14301,14305,15613;09;8;31,32,33,34,35,36,37;;E} | Q73: #FNOBES{13101,13109,15501,15505,11101,13301,13309,14301,14305,15613;09;8;29;;E} | R73: #FNOBES{13101,13109,15501,15505,11101,13301,13309,14301,14305,15613;09;8;43;;E} | S73: #FNOBES{13101,13109,15501,15505,11101,13301,13309,14301,14305,15613;09;8;41;;E} | T73: #FNOBES{13101,13109,15501,15505,11101,13301,13309,14301,14305,15613;09;8;51;;E} | U73: #FNOBES{13101,13109,15501,15505,11101,13301,13309,14301,14305,15613;09;8;61;;E} | V73: =C73-I73-J73-L73-M73-N73-O73-P73-Q73-R73-S73-T73-U73 -> #VALUE! | X73: =SUM(I73:V73) -> #VALUE! | Y73: =C73-X73 -> #VALUE! | AU73: #FNECTCP{11103,11105,13105,13305,15617,15701,15705;09;8;;E}
A74: 410 | B74: Правительство | C74: =D74+G74 -> #VALUE! | D74: #FNECTC{12301,12309,14701,14705,11101,13301,13309,14301,14305;01;8;;E} | E74: #FNECTC{15701,15705;01;8;;E} | F74: #FNECTCP{12301,12309,14701,14705,11101,13301,13309,14301,14305;01;8;;E} | G74: =E74+F74 -> #VALUE! | H74: #FN4{8;12301-12309,14701,14705} | I74: #FNOBES{12301,12309,14701,14705,11101,13301,13309,14301,14305;01;8;25;;E} | J74: #FNOBES{12301,12309,14701,14705,11101,13301,13309,14301,14305;01;8;42;;E} | L74: #FNOBES{12301,12309,14701,14705,11101,13301,13309,14301,14305;01;8;23;;E} | M74: #FNOBES{12301,12309,14701,14705,11101,13301,13309,14301,14305;01;8;26;;E} | N74: #FNOBES{12301,12309,14701,14705,11101,13301,13309,14301,14305;01;8;21,22;;E} | O74: #FNOBES{12301,12309,14701,14705,11101,13301,13309,14301,14305;01;8;24;;E} | P74: #FNOBES{12301,12309,14701,14705,11101,13301,13309,14301,14305;01;8;31,32,33,34,35,36,37;;E} | Q74: #FNOBES{12301,12309,14701,14705,11101,13301,13309,14301,14305;01;8;29;;E} | R74: #FNOBES{12301,12309,14701,14705,11101,13301,13309,14301,14305;01;8;43;;E} | S74: #FNOBES{12301,12309,14701,14705,11101,13301,13309,14301,14305;01;8;41;;E} | T74: #FNOBES{12301,12309,14701,14705,11101,13301,13309,14301,14305;01;8;51;;E} | U74: #FNOBES{12301,12309,14701,14705,11101,13301,13309,14301,14305;01;8;61;;E} | V74: =C74-I74-J74-L74-M74-N74-O74-P74-Q74-R74-S74-T74-U74 -> #VALUE! | X74: =SUM(I74:V74) -> #VALUE! | Y74: =C74-X74 -> #VALUE! | AU74: #FNECTCP{11103,11105,12305,13305,15617,15701,15705;01;8;;E}
B75: Бюджетные организации | C75: =D75+G75 -> #VALUE! | D75: #FNECTC{12401,12409,14801,14809,11101,13301,13309,14301,14305;12;8;;E} | E75: #FNECTC{15701,15705;12;8;;E} | F75: #FNECTCP{12401,12409,14801,14809,11101,13301,13309,14301,14305;12;8;;E} | G75: =E75+F75 -> #VALUE! | H75: #FN4{8;12401-12409,14801,14809} | I75: #FNOBES{12401,12409,14801,14809,11101,13301,13309,14301,14305;12;8;25;;E} | J75: #FNOBES{12401,12409,14801,14809,11101,13301,13309,14301,14305;12;8;42;;E} | L75: #FNOBES{12401,12409,14801,14809,11101,13301,13309,14301,14305;12;8;23;;E} | M75: #FNOBES{12401,12409,14801,14809,11101,13301,13309,14301,14305;12;8;26;;E} | N75: #FNOBES{12401,12409,14801,14809,11101,13301,13309,14301,14305;12;8;21,22;;E} | O75: #FNOBES{12401,12409,14801,14809,11101,13301,13309,14301,14305;12;8;24;;E} | P75: #FNOBES{12401,12409,14801,14809,11101,13301,13309,14301,14305;12;8;31,32,33,34,35,36,37;;E} | Q75: #FNOBES{12401,12409,14801,14809,11101,13301,13309,14301,14305;12;8;29;;E} | R75: #FNOBES{12401,12409,14801,14809,11101,13301,13309,14301,14305;12;8;43;;E} | S75: #FNOBES{12401,12409,14801,14809,11101,13301,13309,14301,14305;12;8;41;;E} | T75: #FNOBES{12401,12409,14801,14809,11101,13301,13309,14301,14305;12;8;51;;E} | U75: #FNOBES{12401,12409,14801,14809,11101,13301,13309,14301,14305;12;8;61;;E} | V75: =C75-I75-J75-L75-M75-N75-O75-P75-Q75-R75-S75-T75-U75 -> #VALUE! | X75: =SUM(I75:V75) -> #VALUE! | Y75: =C75-X75 -> #VALUE! | AU75: #FNECTCP{11103,11105,12405,13305,15617,15701,15705;12;8;;E}
B76: Предприниматели без обр. юр.лица | C76: =D76+G76 -> #VALUE! | D76: #FNECTC{12601,12609,15001,15005,11101,13301,13309,14301,14305,15605;11;8;;E} | E76: #FNECTC{15701,15705;11;8;;E} | F76: #FNECTCP{12601,12609,15001,15005,11101,13301,13309,14301,14305,15605;11;8;;E} | G76: =E76+F76 -> #VALUE! | H76: #FN4{8;12601-12609,15001,15005} | I76: #FNOBES{12601,12609,15001,15005,11101,13301,13309,14301,14305,15605;11;8;25;;E} | J76: #FNOBES{12601,12609,15001,15005,11101,13301,13309,14301,14305,15605;11;8;42;;E} | L76: #FNOBES{12601,12609,15001,15005,11101,13301,13309,14301,14305,15605;11;8;23;;E} | M76: #FNOBES{12601,12609,15001,15005,11101,13301,13309,14301,14305,15605;11;8;26;;E} | N76: #FNOBES{12601,12609,15001,15005,11101,13301,13309,14301,14305,15605;11;8;21,22;;E} | O76: #FNOBES{12601,12609,15001,15005,11101,13301,13309,14301,14305,15605;11;8;24;;E} | P76: #FNOBES{12601,12609,15001,15005,11101,13301,13309,14301,14305,15605;11;8;31,32,33,34,35,36,37;;E} | Q76: #FNOBES{12601,12609,15001,15005,11101,13301,13309,14301,14305,15605;11;8;29;;E} | R76: #FNOBES{12601,12609,15001,15005,11101,13301,13309,14301,14305,15605;11;8;43;;E} | S76: #FNOBES{12601,12609,15001,15005,11101,13301,13309,14301,14305,15605;11;8;41;;E} | T76: #FNOBES{12601,12609,15001,15005,11101,13301,13309,14301,14305,15605;11;8;51;;E} | U76: #FNOBES{12601,12609,15001,15005,11101,13301,13309,14301,14305,15605;11;8;61;;E} | V76: =C76-I76-J76-L76-M76-N76-O76-P76-Q76-R76-S76-T76-U76 -> #VALUE! | X76: =SUM(I76:V76) -> #VALUE! | Y76: =C76-X76 -> #VALUE! | AU76: #FNECTCP{11103,11105,12605,13305,15617,15701,15705;11;8;;E}
B77: Негосударственные, некомерческие организации | C77: =D77+G77 -> #VALUE! | D77: #FNECTC{13001,13009,15201,15205,11101,13301,13309,14301,14305,15611;03;8;;E} | E77: #FNECTC{15701,15705;03;8;;E} | F77: #FNECTCP{13001,13009,15201,15205,11101,13301,13309,14301,14305,15611;03;8;;E} | G77: =E77+F77 -> #VALUE! | H77: #FN4{8;13001-13009,15201-15205} | I77: #FNOBES{13001,13009,15201,15205,11101,13301,13309,14301,14305,15611;03;8;25;;E} | J77: #FNOBES{13001,13009,15201,15205,11101,13301,13309,14301,14305,15611;03;8;42;;E} | L77: #FNOBES{13001,13009,15201,15205,11101,13301,13309,14301,14305,15611;03;8;23;;E} | M77: #FNOBES{13001,13009,15201,15205,11101,13301,13309,14301,14305,15611;03;8;26;;E} | N77: #FNOBES{13001,13009,15201,15205,11101,13301,13309,14301,14305,15611;03;8;21,22;;E} | O77: #FNOBES{13001,13009,15201,15205,11101,13301,13309,14301,14305,15611;03;8;24;;E} | P77: #FNOBES{13001,13009,15201,15205,11101,13301,13309,14301,14305,15611;03;8;31,32,33,34,35,36,37;;E} | Q77: #FNOBES{13001,13009,15201,15205,11101,13301,13309,14301,14305,15611;03;8;29;;E} | R77: #FNOBES{13001,13009,15201,15205,11101,13301,13309,14301,14305,15611;03;8;43;;E} | S77: #FNOBES{13001,13009,15201,15205,11101,13301,13309,14301,14305,15611;03;8;41;;E} | T77: #FNOBES{13001,13009,15201,15205,11101,13301,13309,14301,14305,15611;03;8;51;;E} | U77: #FNOBES{13001,13009,15201,15205,11101,13301,13309,14301,14305,15611;03;8;61;;E} | V77: =C77-I77-J77-L77-M77-N77-O77-P77-Q77-R77-S77-T77-U77 -> #VALUE! | X77: =SUM(I77:V77) -> #VALUE! | Y77: =C77-X77 -> #VALUE! | AU77: #FNECTCP{11103,11105,13005,13305,15617,15701,15705;03;8;;E}
B78: Небанковские финансовые институты | C78: =D78+G78 -> #VALUE! | D78: #FNECTC{13201,13209,15401,15405,11101,13301,13309,14301,14305;04;8;;E} | E78: #FNECTC{15701,15705;04;8;;E} | F78: #FNECTCP{13201,13209,15401,15405,11101,13301,13309,14301,14305;04;8;;E} | G78: =E78+F78 -> #VALUE! | H78: #FN4{8;13201-13209,15401-15405} | I78: #FNOBES{13201,13209,15401,15405,11101,13301,13309,14301,14305;04;8;25;;E} | J78: #FNOBES{13201,13209,15401,15405,11101,13301,13309,14301,14305;04;8;42;;E} | L78: #FNOBES{13201,13209,15401,15405,11101,13301,13309,14301,14305;04;8;23;;E} | M78: #FNOBES{13201,13209,15401,15405,11101,13301,13309,14301,14305;04;8;26;;E} | N78: #FNOBES{13201,13209,15401,15405,11101,13301,13309,14301,14305;04;8;21,22;;E} | O78: #FNOBES{13201,13209,15401,15405,11101,13301,13309,14301,14305;04;8;24;;E} | P78: #FNOBES{13201,13209,15401,15405,11101,13301,13309,14301,14305;04;8;31,32,33,34,35,36,37;;E} | Q78: #FNOBES{13201,13209,15401,15405,11101,13301,13309,14301,14305;04;8;29;;E} | R78: #FNOBES{13201,13209,15401,15405,11101,13301,13309,14301,14305;04;8;43;;E} | S78: #FNOBES{13201,13209,15401,15405,11101,13301,13309,14301,14305;04;8;41;;E} | T78: #FNOBES{13201,13209,15401,15405,11101,13301,13309,14301,14305;04;8;51;;E} | U78: #FNOBES{13201,13209,15401,15405,11101,13301,13309,14301,14305;04;8;61;;E} | V78: =C78-I78-J78-L78-M78-N78-O78-P78-Q78-R78-S78-T78-U78 -> #VALUE! | X78: =SUM(I78:V78) -> #VALUE! | Y78: =C78-X78 -> #VALUE! | AU78: #FNECTCP{11103,11105,13205,13305,15617,15701,15705;04;8;;E}
A79: 420 | B79: Прочие | C79: =SUM(C75:C78) -> #VALUE! | D79: =SUM(D75:D78) -> 0 | E79: =SUM(E75:E78) -> 0 | F79: =SUM(F75:F78) -> 0 | G79: =SUM(G75:G78) -> #VALUE! | H79: =IF(C79=0,0,(H75*(C75/C79))+(H76*(C76/C79))+(H77*(C77/C79))+(H78*(C78/C79))) -> #VALUE! | I79: =SUM(I75:I78) -> 0 | J79: =SUM(J75:J78) -> 0 | L79: =SUM(L75:L78) -> 0 | M79: =SUM(M75:M78) -> 0 | N79: =SUM(N75:N78) -> 0 | O79: =SUM(O75:O78) -> 0 | P79: =SUM(P75:P78) -> 0 | Q79: =SUM(Q75:Q78) -> 0 | R79: =SUM(R75:R78) -> 0 | S79: =SUM(S75:S78) -> 0 | ... U79: =SUM(U75:U78) -> 0 | V79: =C79-I79-J79-L79-M79-N79-O79-P79-Q79-R79-S79-T79-U79 -> #VALUE! | X79: =SUM(I79:V79) -> #VALUE! | Y79: =C79-X79 -> #VALUE!
A80: 430 | B80: Итого по материально-техническому снабжению и сбыту | C80: =SUM(C70:C74)+C79 -> #VALUE! | D80: =SUM(D70:D74)+D79 -> 0 | E80: =SUM(E70:E74)+E79 -> 0 | F80: =SUM(F70:F74)+F79 -> 0 | G80: =SUM(G70:G74)+G79 -> #VALUE! | H80: =IF(C80=0,"",(H70*(C70/C80))+(H71*(C71/C80))+(H72*(C72/C80))+(H73*(C73/C80))+(H74*(C74/C80))) -> #VALUE! | I80: =SUM(I70:I74)+I79 -> 0 | J80: =SUM(J70:J74)+J79 -> 0 | L80: =SUM(L70:L74)+L79 -> 0 | M80: =SUM(M70:M74)+M79 -> 0 | N80: =SUM(N70:N74)+N79 -> 0 | O80: =SUM(O70:O74)+O79 -> 0 | P80: =SUM(P70:P74)+P79 -> 0 | Q80: =SUM(Q70:Q74)+Q79 -> 0 | R80: =SUM(R70:R74)+R79 -> 0 | S80: =SUM(S70:S74)+S79 -> 0 | ... U80: =SUM(U70:U74)+U79 -> 0 | V80: =C80-I80-J80-L80-M80-N80-O80-P80-Q80-R80-S80-T80-U80 -> #VALUE! | X80: =SUM(I80:V80) -> #VALUE! | Y80: =C80-X80 -> #VALUE! | AU80: =SUM(AU75:AU79) -> 0
B81: Жилищно-коммунальные услуги
A82: 440 | B82: Физические лица | C82: =D82+G82 -> #VALUE! | D82: #FNECTC{12501,12509,14901,14905,11101,13301,13309,14301,14305,15603;08;9;;E} | E82: #FNECTC{15701,15705;08;9;;E} | F82: #FNECTCP{12501,12509,14901,14905,11101,13301,13309,14301,14305,15603;08;9;;E} | G82: =E82+F82 -> #VALUE! | H82: #FN4{;12501-12509,14901,14905} | I82: #FNOBES{12501,12509,14901,14905,11101,13301,13309,14301,14305,15603;08;9;25;;E} | J82: #FNOBES{12501,12509,14901,14905,11101,13301,13309,14301,14305,15603;08;9;42;;E} | L82: #FNOBES{12501,12509,14901,14905,11101,13301,13309,14301,14305,15603;08;9;23;;E} | M82: #FNOBES{12501,12509,14901,14905,11101,13301,13309,14301,14305,15603;08;9;26;;E} | N82: #FNOBES{12501,12509,14901,14905,11101,13301,13309,14301,14305,15603;08;9;21,22;;E} | O82: #FNOBES{12501,12509,14901,14905,11101,13301,13309,14301,14305,15603;08;9;24;;E} | P82: #FNOBES{12501,12509,14901,14905,11101,13301,13309,14301,14305,15603;08;9;31,32,33,34,35,36,37;;E} | Q82: #FNOBES{12501,12509,14901,14905,11101,13301,13309,14301,14305,15603;08;9;29;;E} | R82: #FNOBES{12501,12509,14901,14905,11101,13301,13309,14301,14305,15603;08;9;43;;E} | S82: #FNOBES{12501,12509,14901,14905,11101,13301,13309,14301,14305,15603;08;9;41;;E} | T82: #FNOBES{12501,12509,14901,14905,11101,13301,13309,14301,14305,15603;08;9;51;;E} | U82: #FNOBES{12501,12509,14901,14905,11101,13301,13309,14301,14305,15603;08;9;61;;E} | V82: =C82-I82-J82-L82-M82-N82-O82-P82-Q82-R82-S82-T82-U82 -> #VALUE! | X82: =SUM(I82:V82) -> #VALUE! | Y82: =C82-X82 -> #VALUE! | AU82: #FNECTCP{11103,11105,12505,13305,15617,15703,15705;08;9;;E}
A83: 450 | B83: Гос. предприятия | C83: =D83+G83 -> #VALUE! | D83: #FNECTC{12701,12709,15101,15105,11101,13301,13309,14301,14305,15607;02;9;;E} | E83: #FNECTC{15701,15705;02;9;;E} | F83: #FNECTCP{12701,12709,15101,15105,11101,13301,13309,14301,14305,15607;02;9;;E} | G83: =E83+F83 -> #VALUE! | H83: #FN4{9;12701-12709,15101,15105} | I83: #FNOBES{12701,12709,15101,15105,11101,13301,13309,14301,14305,15607;02;9;25;;E} | J83: #FNOBES{12701,12709,15101,15105,11101,13301,13309,14301,14305,15607;02;9;42;;E} | L83: #FNOBES{12701,12709,15101,15105,11101,13301,13309,14301,14305,15607;02;9;23;;E} | M83: #FNOBES{12701,12709,15101,15105,11101,13301,13309,14301,14305,15607;02;9;26;;E} | N83: #FNOBES{12701,12709,15101,15105,11101,13301,13309,14301,14305,15607;02;9;21,22;;E} | O83: #FNOBES{12701,12709,15101,15105,11101,13301,13309,14301,14305,15607;02;9;24;;E} | P83: #FNOBES{12701,12709,15101,15105,11101,13301,13309,14301,14305,15607;02;9;31,32,33,34,35,36,37;;E} | Q83: #FNOBES{12701,12709,15101,15105,11101,13301,13309,14301,14305,15607;02;9;29;;E} | R83: #FNOBES{12701,12709,15101,15105,11101,13301,13309,14301,14305,15607;02;9;43;;E} | S83: #FNOBES{12701,12709,15101,15105,11101,13301,13309,14301,14305,15607;02;9;41;;E} | T83: #FNOBES{12701,12709,15101,15105,11101,13301,13309,14301,14305,15607;02;9;51;;E} | U83: #FNOBES{12701,12709,15101,15105,11101,13301,13309,14301,14305,15607;02;9;61;;E} | V83: =C83-I83-J83-L83-M83-N83-O83-P83-Q83-R83-S83-T83-U83 -> #VALUE! | X83: =SUM(I83:V83) -> #VALUE! | Y83: =C83-X83 -> #VALUE! | AU83: #FNECTCP{11103,11105,12705,13305,15617,15701,15705;02;9;;E}
A84: 560 | B84: Совместные предприятия | C84: =D84+G84 -> #VALUE! | D84: #FNECTC{12901,12909,15301,15305,11101,13301,13309,14301,14305,15609;10;9;;E} | E84: #FNECTC{15701,15705;10;9;;E} | F84: #FNECTCP{12901,12909,15301,15305,11101,13301,13309,14301,14305,15609;10;9;;E} | G84: =E84+F84 -> #VALUE! | H84: #FN4{9;12901-12909,15301,15305} | I84: #FNOBES{12901,12909,15301,15305,11101,13301,13309,14301,14305,15609;10;9;25;;E} | J84: #FNOBES{12901,12909,15301,15305,11101,13301,13309,14301,14305,15609;10;9;42;;E} | L84: #FNOBES{12901,12909,15301,15305,11101,13301,13309,14301,14305,15609;10;9;23;;E} | M84: #FNOBES{12901,12909,15301,15305,11101,13301,13309,14301,14305,15609;10;9;26;;E} | N84: #FNOBES{12901,12909,15301,15305,11101,13301,13309,14301,14305,15609;10;9;21,22;;E} | O84: #FNOBES{12901,12909,15301,15305,11101,13301,13309,14301,14305,15609;10;9;24;;E} | P84: #FNOBES{12901,12909,15301,15305,11101,13301,13309,14301,14305,15609;10;9;31,32,33,34,35,36,37;;E} | Q84: #FNOBES{12901,12909,15301,15305,11101,13301,13309,14301,14305,15609;10;9;29;;E} | R84: #FNOBES{12901,12909,15301,15305,11101,13301,13309,14301,14305,15609;10;9;43;;E} | S84: #FNOBES{12901,12909,15301,15305,11101,13301,13309,14301,14305,15609;10;9;41;;E} | T84: #FNOBES{12901,12909,15301,15305,11101,13301,13309,14301,14305,15609;10;9;51;;E} | U84: #FNOBES{12901,12909,15301,15305,11101,13301,13309,14301,14305,15609;10;9;61;;E} | V84: =C84-I84-J84-L84-M84-N84-O84-P84-Q84-R84-S84-T84-U84 -> #VALUE! | X84: =SUM(I84:V84) -> #VALUE! | Y84: =C84-X84 -> #VALUE! | AU84: #FNECTCP{11103,11105,12905,13305,15617,15701,15705;10;9;;E}
A85: 470 | B85: Частные товарищества и корпорации | C85: =D85+G85 -> #VALUE! | D85: #FNECTC{13101,13109,15501,15505,11101,13301,13309,14301,14305,15613;09;9;;E} | E85: #FNECTC{15701,15705;09;9;;E} | F85: #FNECTCP{13101,13109,15501,15505,11101,13301,13309,14301,14305,15613;09;9;;E} | G85: =E85+F85 -> #VALUE! | H85: #FN4{9;13101-13109,15501-15505} | I85: #FNOBES{13101,13109,15501,15505,11101,13301,13309,14301,14305,15613;09;9;25;;E} | J85: #FNOBES{13101,13109,15501,15505,11101,13301,13309,14301,14305,15613;09;9;42;;E} | L85: #FNOBES{13101,13109,15501,15505,11101,13301,13309,14301,14305,15613;09;9;23;;E} | M85: #FNOBES{13101,13109,15501,15505,11101,13301,13309,14301,14305,15613;09;9;26;;E} | N85: #FNOBES{13101,13109,15501,15505,11101,13301,13309,14301,14305,15613;09;9;21,22;;E} | O85: #FNOBES{13101,13109,15501,15505,11101,13301,13309,14301,14305,15613;09;9;24;;E} | P85: #FNOBES{13101,13109,15501,15505,11101,13301,13309,14301,14305,15613;09;9;31,32,33,34,35,36,37;;E} | Q85: #FNOBES{13101,13109,15501,15505,11101,13301,13309,14301,14305,15613;09;9;29;;E} | R85: #FNOBES{13101,13109,15501,15505,11101,13301,13309,14301,14305,15613;09;9;43;;E} | S85: #FNOBES{13101,13109,15501,15505,11101,13301,13309,14301,14305,15613;09;9;41;;E} | T85: #FNOBES{13101,13109,15501,15505,11101,13301,13309,14301,14305,15613;09;9;51;;E} | U85: #FNOBES{13101,13109,15501,15505,11101,13301,13309,14301,14305,15613;09;9;61;;E} | V85: =C85-I85-J85-L85-M85-N85-O85-P85-Q85-R85-S85-T85-U85 -> #VALUE! | X85: =SUM(I85:V85) -> #VALUE! | Y85: =C85-X85 -> #VALUE! | AU85: #FNECTCP{11103,11105,13105,13305,15617,15701,15705;09;9;;E}
A86: 480 | B86: Правительство | C86: =D86+G86 -> #VALUE! | D86: #FNECTC{12301,12309,14701,14705,11101,13301,13309,14301,14305;01;9;;E} | E86: #FNECTC{15701,15705;01;9;;E} | F86: #FNECTCP{12301,12309,14701,14705,11101,13301,13309,14301,14305;01;9;;E} | G86: =E86+F86 -> #VALUE! | H86: #FN4{9;12301-12309,14701,14705} | I86: #FNOBES{12301,12309,14701,14705,11101,13301,13309,14301,14305;01;9;25;;E} | J86: #FNOBES{12301,12309,14701,14705,11101,13301,13309,14301,14305;01;9;42;;E} | L86: #FNOBES{12301,12309,14701,14705,11101,13301,13309,14301,14305;01;9;23;;E} | M86: #FNOBES{12301,12309,14701,14705,11101,13301,13309,14301,14305;01;9;26;;E} | N86: #FNOBES{12301,12309,14701,14705,11101,13301,13309,14301,14305;01;9;21,22;;E} | O86: #FNOBES{12301,12309,14701,14705,11101,13301,13309,14301,14305;01;9;24;;E} | P86: #FNOBES{12301,12309,14701,14705,11101,13301,13309,14301,14305;01;9;31,32,33,34,35,36,37;;E} | Q86: #FNOBES{12301,12309,14701,14705,11101,13301,13309,14301,14305;01;9;29;;E} | R86: #FNOBES{12301,12309,14701,14705,11101,13301,13309,14301,14305;01;9;43;;E} | S86: #FNOBES{12301,12309,14701,14705,11101,13301,13309,14301,14305;01;9;41;;E} | T86: #FNOBES{12301,12309,14701,14705,11101,13301,13309,14301,14305;01;9;51;;E} | U86: #FNOBES{12301,12309,14701,14705,11101,13301,13309,14301,14305;01;9;61;;E} | V86: =C86-I86-J86-L86-M86-N86-O86-P86-Q86-R86-S86-T86-U86 -> #VALUE! | X86: =SUM(I86:V86) -> #VALUE! | Y86: =C86-X86 -> #VALUE! | AU86: #FNECTCP{11103,11105,12305,13305,15617,15701,15705;01;9;;E}
B87: Бюджетные организации | C87: =D87+G87 -> #VALUE! | D87: #FNECTC{12401,12409,14801,14809,11101,13301,13309,14301,14305;12;9;;E} | E87: #FNECTC{15701,15705;12;9;;E} | F87: #FNECTCP{12401,12409,14801,14809,11101,13301,13309,14301,14305;12;9;;E} | G87: =E87+F87 -> #VALUE! | H87: #FN4{9;12401-12409,14801,14809} | I87: #FNOBES{12401,12409,14801,14809,11101,13301,13309,14301,14305;12;9;25;;E} | J87: #FNOBES{12401,12409,14801,14809,11101,13301,13309,14301,14305;12;9;42;;E} | L87: #FNOBES{12401,12409,14801,14809,11101,13301,13309,14301,14305;12;9;23;;E} | M87: #FNOBES{12401,12409,14801,14809,11101,13301,13309,14301,14305;12;9;26;;E} | N87: #FNOBES{12401,12409,14801,14809,11101,13301,13309,14301,14305;12;9;21,22;;E} | O87: #FNOBES{12401,12409,14801,14809,11101,13301,13309,14301,14305;12;9;24;;E} | P87: #FNOBES{12401,12409,14801,14809,11101,13301,13309,14301,14305;12;9;31,32,33,34,35,36,37;;E} | Q87: #FNOBES{12401,12409,14801,14809,11101,13301,13309,14301,14305;12;9;29;;E} | R87: #FNOBES{12401,12409,14801,14809,11101,13301,13309,14301,14305;12;9;43;;E} | S87: #FNOBES{12401,12409,14801,14809,11101,13301,13309,14301,14305;12;9;41;;E} | T87: #FNOBES{12401,12409,14801,14809,11101,13301,13309,14301,14305;12;9;51;;E} | U87: #FNOBES{12401,12409,14801,14809,11101,13301,13309,14301,14305;12;9;61;;E} | V87: =C87-I87-J87-L87-M87-N87-O87-P87-Q87-R87-S87-T87-U87 -> #VALUE! | X87: =SUM(I87:V87) -> #VALUE! | Y87: =C87-X87 -> #VALUE! | AU87: #FNECTCP{11103,11105,12405,13305,15617,15701,15705;12;9;;E}
B88: Предприниматели без обр. юр.лица | C88: =D88+G88 -> #VALUE! | D88: #FNECTC{12601,12609,15001,15005,11101,13301,13309,14301,14305,15605;11;9;;E} | E88: #FNECTC{15701,15705;11;9;;E} | F88: #FNECTCP{12601,12609,15001,15005,11101,13301,13309,14301,14305,15605;11;9;;E} | G88: =E88+F88 -> #VALUE! | H88: #FN4{9;12601-12609,15001,15005} | I88: #FNOBES{12601,12609,15001,15005,11101,13301,13309,14301,14305,15605;11;9;25;;E} | J88: #FNOBES{12601,12609,15001,15005,11101,13301,13309,14301,14305,15605;11;9;42;;E} | L88: #FNOBES{12601,12609,15001,15005,11101,13301,13309,14301,14305,15605;11;9;23;;E} | M88: #FNOBES{12601,12609,15001,15005,11101,13301,13309,14301,14305,15605;11;9;26;;E} | N88: #FNOBES{12601,12609,15001,15005,11101,13301,13309,14301,14305,15605;11;9;21,22;;E} | O88: #FNOBES{12601,12609,15001,15005,11101,13301,13309,14301,14305,15605;11;9;24;;E} | P88: #FNOBES{12601,12609,15001,15005,11101,13301,13309,14301,14305,15605;11;9;31,32,33,34,35,36,37;;E} | Q88: #FNOBES{12601,12609,15001,15005,11101,13301,13309,14301,14305,15605;11;9;29;;E} | R88: #FNOBES{12601,12609,15001,15005,11101,13301,13309,14301,14305,15605;11;9;43;;E} | S88: #FNOBES{12601,12609,15001,15005,11101,13301,13309,14301,14305,15605;11;9;41;;E} | T88: #FNOBES{12601,12609,15001,15005,11101,13301,13309,14301,14305,15605;11;9;51;;E} | U88: #FNOBES{12601,12609,15001,15005,11101,13301,13309,14301,14305,15605;11;9;61;;E} | V88: =C88-I88-J88-L88-M88-N88-O88-P88-Q88-R88-S88-T88-U88 -> #VALUE! | X88: =SUM(I88:V88) -> #VALUE! | Y88: =C88-X88 -> #VALUE! | AU88: #FNECTCP{11103,11105,12605,13305,15617,15701,15705;11;9;;E}
B89: Негосударственные, некомерческие организации | C89: =D89+G89 -> #VALUE! | D89: #FNECTC{13001,13009,15201,15205,11101,13301,13309,14301,14305,15611;03;9;;E} | E89: #FNECTC{15701,15705;03;9;;E} | F89: #FNECTCP{13001,13009,15201,15205,11101,13301,13309,14301,14305,15611;03;9;;E} | G89: =E89+F89 -> #VALUE! | H89: #FN4{9;13001-13009,15201-15205} | I89: #FNOBES{13001,13009,15201,15205,11101,13301,13309,14301,14305,15611;03;9;25;;E} | J89: #FNOBES{13001,13009,15201,15205,11101,13301,13309,14301,14305,15611;03;9;42;;E} | L89: #FNOBES{13001,13009,15201,15205,11101,13301,13309,14301,14305,15611;03;9;23;;E} | M89: #FNOBES{13001,13009,15201,15205,11101,13301,13309,14301,14305,15611;03;9;26;;E} | N89: #FNOBES{13001,13009,15201,15205,11101,13301,13309,14301,14305,15611;03;9;21,22;;E} | O89: #FNOBES{13001,13009,15201,15205,11101,13301,13309,14301,14305,15611;03;9;24;;E} | P89: #FNOBES{13001,13009,15201,15205,11101,13301,13309,14301,14305,15611;03;9;31,32,33,34,35,36,37;;E} | Q89: #FNOBES{13001,13009,15201,15205,11101,13301,13309,14301,14305,15611;03;9;29;;E} | R89: #FNOBES{13001,13009,15201,15205,11101,13301,13309,14301,14305,15611;03;9;43;;E} | S89: #FNOBES{13001,13009,15201,15205,11101,13301,13309,14301,14305,15611;03;9;41;;E} | T89: #FNOBES{13001,13009,15201,15205,11101,13301,13309,14301,14305,15611;03;9;51;;E} | U89: #FNOBES{13001,13009,15201,15205,11101,13301,13309,14301,14305,15611;03;9;61;;E} | V89: =C89-I89-J89-L89-M89-N89-O89-P89-Q89-R89-S89-T89-U89 -> #VALUE! | X89: =SUM(I89:V89) -> #VALUE! | Y89: =C89-X89 -> #VALUE! | AU89: #FNECTCP{11103,11105,13005,13305,15617,15701,15705;03;9;;E}
B90: Небанковские финансовые институты | C90: =D90+G90 -> #VALUE! | D90: #FNECTC{13201,13209,15401,15405,11101,13301,13309,14301,14305;04;9;;E} | E90: #FNECTC{15701,15705;04;9;;E} | F90: #FNECTCP{13201,13209,15401,15405,11101,13301,13309,14301,14305;04;9;;E} | G90: =E90+F90 -> #VALUE! | H90: #FN4{9;13201-13209,15401-15405} | I90: #FNOBES{13201,13209,15401,15405,11101,13301,13309,14301,14305;04;9;25;;E} | J90: #FNOBES{13201,13209,15401,15405,11101,13301,13309,14301,14305;04;9;42;;E} | L90: #FNOBES{13201,13209,15401,15405,11101,13301,13309,14301,14305;04;9;23;;E} | M90: #FNOBES{13201,13209,15401,15405,11101,13301,13309,14301,14305;04;9;26;;E} | N90: #FNOBES{13201,13209,15401,15405,11101,13301,13309,14301,14305;04;9;21,22;;E} | O90: #FNOBES{13201,13209,15401,15405,11101,13301,13309,14301,14305;04;9;24;;E} | P90: #FNOBES{13201,13209,15401,15405,11101,13301,13309,14301,14305;04;9;31,32,33,34,35,36,37;;E} | Q90: #FNOBES{13201,13209,15401,15405,11101,13301,13309,14301,14305;04;9;29;;E} | R90: #FNOBES{13201,13209,15401,15405,11101,13301,13309,14301,14305;04;9;43;;E} | S90: #FNOBES{13201,13209,15401,15405,11101,13301,13309,14301,14305;04;9;41;;E} | T90: #FNOBES{13201,13209,15401,15405,11101,13301,13309,14301,14305;04;9;51;;E} | U90: #FNOBES{13201,13209,15401,15405,11101,13301,13309,14301,14305;04;9;61;;E} | V90: =C90-I90-J90-L90-M90-N90-O90-P90-Q90-R90-S90-T90-U90 -> #VALUE! | X90: =SUM(I90:V90) -> #VALUE! | Y90: =C90-X90 -> #VALUE! | AU90: #FNECTCP{11103,11105,13205,13305,15617,15701,15705;04;9;;E}
A91: 490 | B91: Прочие | C91: =SUM(C87:C90) -> #VALUE! | D91: =SUM(D87:D90) -> 0 | E91: =SUM(E87:E90) -> 0 | F91: =SUM(F87:F90) -> 0 | G91: =SUM(G87:G90) -> #VALUE! | H91: =IF(C91=0,0,(H87*(C87/C91))+(H88*(C88/C91))+(H89*(C89/C91))+(H90*(C90/C91))) -> #VALUE! | I91: =SUM(I87:I90) -> 0 | J91: =SUM(J87:J90) -> 0 | L91: =SUM(L87:L90) -> 0 | M91: =SUM(M87:M90) -> 0 | N91: =SUM(N87:N90) -> 0 | O91: =SUM(O87:O90) -> 0 | P91: =SUM(P87:P90) -> 0 | Q91: =SUM(Q87:Q90) -> 0 | R91: =SUM(R87:R90) -> 0 | S91: =SUM(S87:S90) -> 0 | ... U91: =SUM(U87:U90) -> 0 | V91: =C91-I91-J91-L91-M91-N91-O91-P91-Q91-R91-S91-T91-U91 -> #VALUE! | X91: =SUM(I91:V91) -> #VALUE! | Y91: =C91-X91 -> #VALUE!
A92: 500 | B92: Итого по жилищно-коммунальным услугам | C92: =SUM(C82:C86)+C91 -> #VALUE! | D92: =SUM(D82:D86)+D91 -> 0 | E92: =SUM(E82:E86)+E91 -> 0 | F92: =SUM(F82:F86)+F91 -> 0 | G92: =SUM(G82:G86)+G91 -> #VALUE! | H92: =IF(C92=0,"",(H82*(C82/C92))+(H82*(C82/C92))+(H84*(C84/C92))+(H85*(C85/C92))+(H86*(C86/C92))) -> #VALUE! | I92: =SUM(I82:I86)+I91 -> 0 | J92: =SUM(J82:J86)+J91 -> 0 | L92: =SUM(L82:L86)+L91 -> 0 | M92: =SUM(M82:M86)+M91 -> 0 | N92: =SUM(N82:N86)+N91 -> 0 | O92: =SUM(O82:O86)+O91 -> 0 | P92: =SUM(P82:P86)+P91 -> 0 | Q92: =SUM(Q82:Q86)+Q91 -> 0 | R92: =SUM(R82:R86)+R91 -> 0 | S92: =SUM(S82:S86)+S91 -> 0 | ... U92: =SUM(U82:U86)+U91 -> 0 | V92: =C92-I92-J92-L92-M92-N92-O92-P92-Q92-R92-S92-T92-U92 -> #VALUE! | X92: =SUM(I92:V92) -> #VALUE! | Y92: =C92-X92 -> #VALUE! | AU92: =SUM(AU87:AU91) -> 0
B93: Другие отрасли
A94: 510 | B94: Физические лица | C94: =D94+G94 -> #VALUE! | D94: =D107-D9-D21-D34-D46-D58-D70-D82 -> #VALUE! | E94: =E107-E9-E21-E34-E46-E58-E70-E82 -> #VALUE! | F94: =F107-F9-F21-F34-F46-F58-F70-F82 -> #VALUE! | G94: =G107-G9-G21-G34-G46-G58-G70-G82 -> #VALUE! | H94: =IF(ABS(C94)<0.01,0,((H107*C107-H9*C9-H21*C21-H34*C34-H46*C46-H58*C58-H70*C70-H82*C82)/C94)) -> #VALUE! | I94: =I107-I9-I21-I34-I46-I58-I70-I82 -> #VALUE! | J94: =J107-J9-J21-J34-J46-J58-J70-J82 -> #VALUE! | L94: =L107-L9-L21-L34-L46-L58-L70-L82 -> #VALUE! | M94: =M107-M9-M21-M34-M46-M58-M70-M82 -> #VALUE! | N94: =N107-N9-N21-N34-N46-N58-N70-N82 -> #VALUE! | O94: =O107-O9-O21-O34-O46-O58-O70-O82 -> #VALUE! | P94: =P107-P9-P21-P34-P46-P58-P70-P82 -> #VALUE! | Q94: =Q107-Q9-Q21-Q34-Q46-Q58-Q70-Q82 -> #VALUE! | R94: =R107-R9-R21-R34-R46-R58-R70-R82 -> #VALUE! | S94: =S107-S9-S21-S34-S46-S58-S70-S82 -> #VALUE! | ... U94: =U107-U9-U21-U34-U46-U58-U70-U82 -> #VALUE! | V94: =C94-I94-J94-L94-M94-N94-O94-P94-Q94-R94-S94-T94-U94 -> #VALUE! | X94: =SUM(I94:V94) -> #VALUE! | Y94: =C94-X94 -> #VALUE! | AU94: =AU107-AU9-#REF!-AU34-AU46-AU58-AU70-AU82 -> #VALUE!
A95: 520 | B95: Гос. предприятия | C95: =D95+G95 -> #VALUE! | D95: =D108-D10-D163-D35-D47-D59-D71-D83 -> #VALUE! | E95: =E108-E10-E163-E35-E47-E59-E71-E83 -> #VALUE! | F95: =F108-F10-F163-F35-F47-F59-F71-F83 -> #VALUE! | G95: =G108-G10-G163-G35-G47-G59-G71-G83 -> #VALUE! | H95: =IF(ABS(C95)<0.01,0,((H108*C108-H10*C10-H22*C22-H35*C35-H47*C47-H59*C59-H71*C71-H83*C83)/C95)) -> #VALUE! | I95: =I108-I10-I163-I35-I47-I59-I71-I83 -> #VALUE! | J95: =J108-J10-J163-J35-J47-J59-J71-J83 -> #VALUE! | L95: =L108-L10-L163-L35-L47-L59-L71-L83 -> #VALUE! | M95: =M108-M10-M163-M35-M47-M59-M71-M83 -> #VALUE! | N95: =N108-N10-N163-N35-N47-N59-N71-N83 -> #VALUE! | O95: =O108-O10-O163-O35-O47-O59-O71-O83 -> #VALUE! | P95: =P108-P10-P163-P35-P47-P59-P71-P83 -> #VALUE! | Q95: =Q108-Q10-Q163-Q35-Q47-Q59-Q71-Q83 -> #VALUE! | R95: =R108-R10-R163-R35-R47-R59-R71-R83 -> #VALUE! | S95: =S108-S10-S163-S35-S47-S59-S71-S83 -> #VALUE! | ... U95: =U108-U10-U163-U35-U47-U59-U71-U83 -> #VALUE! | V95: =C95-I95-J95-L95-M95-N95-O95-P95-Q95-R95-S95-T95-U95 -> #VALUE! | X95: =SUM(I95:V95) -> #VALUE! | Y95: =C95-X95 -> #VALUE! | AU95: =AU108-AU10-#REF!-AU35-AU47-AU59-AU71-AU83 -> #VALUE!
A96: 530 | B96: Совместные предприятия | C96: =D96+G96 -> #VALUE! | D96: =D109-D11-D166-D36-D48-D60-D72-D84 -> #VALUE! | E96: =E109-E11-E166-E36-E48-E60-E72-E84 -> #VALUE! | F96: =F109-F11-F166-F36-F48-F60-F72-F84 -> #VALUE! | G96: =G109-G11-G166-G36-G48-G60-G72-G84 -> #VALUE! | H96: =IF(ABS(C96)<0.01,0,((H109*C109-H11*C11-H23*C23-H36*C36-H48*C48-H60*C60-H72*C72-H84*C84)/C96)) -> #VALUE! | I96: =I109-I11-I166-I36-I48-I60-I72-I84 -> #VALUE! | J96: =J109-J11-J166-J36-J48-J60-J72-J84 -> #VALUE! | L96: =L109-L11-L166-L36-L48-L60-L72-L84 -> #VALUE! | M96: =M109-M11-M166-M36-M48-M60-M72-M84 -> #VALUE! | N96: =N109-N11-N166-N36-N48-N60-N72-N84 -> #VALUE! | O96: =O109-O11-O166-O36-O48-O60-O72-O84 -> #VALUE! | P96: =P109-P11-P166-P36-P48-P60-P72-P84 -> #VALUE! | Q96: =Q109-Q11-Q166-Q36-Q48-Q60-Q72-Q84 -> #VALUE! | R96: =R109-R11-R166-R36-R48-R60-R72-R84 -> #VALUE! | S96: =S109-S11-S166-S36-S48-S60-S72-S84 -> #VALUE! | ... U96: =U109-U11-U166-U36-U48-U60-U72-U84 -> #VALUE! | V96: =C96-I96-J96-L96-M96-N96-O96-P96-Q96-R96-S96-T96-U96 -> #VALUE! | X96: =SUM(I96:V96) -> #VALUE! | Y96: =C96-X96 -> #VALUE! | AU96: =AU109-#REF!-#REF!-AU36-AU48-AU60-#REF!-AU84 -> #VALUE!
A97: 540 | B97: Частные товарищества и корпорации | C97: =D97+G97 -> #VALUE! | D97: =D110-D12-D169-D37-D49-D61-D73-D85 -> #VALUE! | E97: =E110-E12-E169-E37-E49-E61-E73-E85 -> #VALUE! | F97: =F110-F12-F169-F37-F49-F61-F73-F85 -> #VALUE! | G97: =G110-G12-G169-G37-G49-G61-G73-G85 -> #VALUE! | H97: =IF(ABS(C97)<0.01,0,((H110*C110-H12*C12-H24*C24-H37*C37-H49*C49-H61*C61-H73*C73-H85*C85)/C97)) -> #VALUE! | I97: =I110-I12-I169-I37-I49-I61-I73-I85 -> #VALUE! | J97: =J110-J12-J169-J37-J49-J61-J73-J85 -> #VALUE! | L97: =L110-L12-L169-L37-L49-L61-L73-L85 -> #VALUE! | M97: =M110-M12-M169-M37-M49-M61-M73-M85 -> #VALUE! | N97: =N110-N12-N169-N37-N49-N61-N73-N85 -> #VALUE! | O97: =O110-O12-O169-O37-O49-O61-O73-O85 -> #VALUE! | P97: =P110-P12-P169-P37-P49-P61-P73-P85 -> #VALUE! | Q97: =Q110-Q12-Q169-Q37-Q49-Q61-Q73-Q85 -> #VALUE! | R97: =R110-R12-R169-R37-R49-R61-R73-R85 -> #VALUE! | S97: =S110-S12-S169-S37-S49-S61-S73-S85 -> #VALUE! | ... U97: =U110-U12-U169-U37-U49-U61-U73-U85 -> #VALUE! | V97: =C97-I97-J97-L97-M97-N97-O97-P97-Q97-R97-S97-T97-U97 -> #VALUE! | X97: =SUM(I97:V97) -> #VALUE! | Y97: =C97-X97 -> #VALUE! | AU97: =AU110-#REF!-#REF!-AU37-AU49-AU61-#REF!-AU85 -> #VALUE!
A98: 550 | B98: Центральный банк | C98: =D98+G98 -> #VALUE! | D98: =D113 -> #FN1{11901} | E98: =E113 -> 0 | F98: =F113 -> 0 | G98: =G113 -> 0 | H98: =H113 -> 0 | I98: =I113 -> 0 | J98: =J113 -> 0 | L98: =L113 -> 0 | M98: =M113 -> 0 | N98: =N113 -> 0 | O98: =O113 -> 0 | P98: =P113 -> 0 | Q98: =Q113 -> 0 | R98: =R113 -> 0 | S98: =S113 -> 0 | ... V98: =V113 -> #VALUE! | X98: =SUM(I98:V98) -> #VALUE! | Y98: =C98-X98 -> #VALUE!
A99: 560 | B99: Другие банки | C99: =D99+G99 -> #VALUE! | D99: =D112 -> #VALUE! | E99: =E172 -> #FNECTC{15701,15705;07;2;;E} | F99: =F172 -> #FNECTCP{12101,12109,14501,14505,11101,13301,13309,14301,14305,15601;07;2;;E} | G99: =G172 -> #VALUE! | H99: =H112 -> #VALUE! | I99: =I172 -> #FNOBES{12101,12109,14501,14505,11101,13301,13309,14301,14305,15601;07;2;25;;E} | J99: =J172 -> #FNOBES{12101,12109,14501,14505,11101,13301,13309,14301,14305,15601;07;2;42;;E} | L99: =L172 -> #FNOBES{12101,12109,14501,14505,11101,13301,13309,14301,14305,15601;07;2;23;;E} | M99: =M172 -> #FNOBES{12101,12109,14501,14505,11101,13301,13309,14301,14305,15601;07;2;26;;E} | N99: =N172 -> #FNOBES{12101,12109,14501,14505,11101,13301,13309,14301,14305,15601;07;2;21,22;;E} | O99: =O172 -> #FNOBES{12101,12109,14501,14505,11101,13301,13309,14301,14305,15601;07;2;24;;E} | P99: =P172 -> #FNOBES{12101,12109,14501,14505,11101,13301,13309,14301,14305,15601;07;2;31,32,33,34,35,36,37;;E} | Q99: =Q172 -> #FNOBES{12101,12109,14501,14505,11101,13301,13309,14301,14305,15601;07;2;29;;E} | R99: =R172 -> #FNOBES{12101,12109,14501,14505,11101,13301,13309,14301,14305,15601;07;2;43;;E} | S99: =S172 -> #FNOBES{12101,12109,14501,14505,11101,13301,13309,14301,14305,15601;07;2;41;;E} | ... V99: =V172 -> #VALUE! | X99: =SUM(I99:V99) -> #VALUE! | Y99: =C99-X99 -> #VALUE! | AU99: =#REF! -> #REF!
A100: 570 | B100: Правительство | C100: =D100+G100 -> #VALUE! | D100: =D114-D13-D179-D38-D50-D62-D74-D86 -> #VALUE! | E100: =E114-E13-E179-E38-E50-E62-E74-E86 -> #VALUE! | F100: =F114-F13-F179-F38-F50-F62-F74-F86 -> #VALUE! | G100: =G114-G13-G179-G38-G50-G62-G74-G86 -> #VALUE! | H100: =IF(ABS(C100)<0.01,0,((H114*C114-H13*C13-H26*C26-H38*C38-H50*C50-H62*C62-H74*C74-H86*C86)/C100)) -> #VALUE! | I100: =I114-I13-I179-I38-I50-I62-I74-I86 -> #VALUE! | J100: =J114-J13-J179-J38-J50-J62-J74-J86 -> #VALUE! | L100: =L114-L13-L179-L38-L50-L62-L74-L86 -> #VALUE! | M100: =M114-M13-M179-M38-M50-M62-M74-M86 -> #VALUE! | N100: =N114-N13-N179-N38-N50-N62-N74-N86 -> #VALUE! | O100: =O114-O13-O179-O38-O50-O62-O74-O86 -> #VALUE! | P100: =P114-P13-P179-P38-P50-P62-P74-P86 -> #VALUE! | Q100: =Q114-Q13-Q179-Q38-Q50-Q62-Q74-Q86 -> #VALUE! | R100: =R114-R13-R179-R38-R50-R62-R74-R86 -> #VALUE! | S100: =S114-S13-S179-S38-S50-S62-S74-S86 -> #VALUE! | ... U100: =U114-U13-U179-U38-U50-U62-U74-U86 -> #VALUE! | V100: =C100-I100-J100-L100-M100-N100-O100-P100-Q100-R100-S100-T100-U100 -> #VALUE! | X100: =SUM(I100:V100) -> #VALUE! | Y100: =C100-X100 -> #VALUE! | AU100: =AU114-#REF!-#REF!-AU38-AU50-AU62-AU74-AU86 -> #VALUE!
A101: 580 | B101: Небанковские финансовые институты | C101: =D101+G101 -> #VALUE! | D101: =D115-D17-D179-D54-D66-D78-D90 -> #VALUE! | E101: =E115-E17-E179-E54-E66-E78-E90 -> #VALUE! | F101: =F115-F17-F179-F54-F66-F78-F90 -> #VALUE! | G101: =G115-G17-G179-G54-G66-G78-G90 -> #VALUE! | H101: =IF(ABS(C101)<0.01,0,((H115*C115-H17*C17-H30*C30-H42*C42-H54*C54-H66*C66-H78*C78-H90*C90)/C101)) -> #VALUE! | I101: =I115-I17-I179-I54-I66-I78-I90 -> #VALUE! | J101: =J115-J17-J179-J54-J66-J78-J90 -> #VALUE! | L101: =L115-L17-L179-L54-L66-L78-L90 -> #VALUE! | M101: =M115-M17-M179-M54-M66-M78-M90 -> #VALUE! | N101: =N115-N17-N179-N54-N66-N78-N90 -> #VALUE! | O101: =O115-O17-O179-O54-O66-O78-O90 -> #VALUE! | P101: =P115-P17-P179-P54-P66-P78-P90 -> #VALUE! | Q101: =Q115-Q17-Q179-Q54-Q66-Q78-Q90 -> #VALUE! | R101: =R115-R17-R179-R54-R66-R78-R90 -> #VALUE! | S101: =S115-S17-S179-S54-S66-S78-S90 -> #VALUE! | ... U101: =U115-U17-U179-U54-U66-U78-U90 -> #VALUE! | V101: =C101-I101-J101-L101-M101-N101-O101-P101-Q101-R101-S101-T101-U101 -> #VALUE! | X101: =SUM(I101:V101) -> #VALUE! | Y101: =C101-X101 -> #VALUE! | AU101: =AU115-AU17-AU30-AU42-AU54-AU66-AU78-AU90 -> #VALUE!
...

Sheet Aging Analysis
O1: Приложение №1 к Рекомендациям по заполнению отчетности коммерческих банков по банковскому надзору представляемых Центральному банку Республики Узбекистан
A2: Анализ просроченных ссуд к получению и лизинговых операций | P2: Таблица-9 (Форма-1604LOA)
A3: #FNP{date_end}
C5: Всего задолжность по ссудам | E5: Реструктуризированные кредиты | G5: Просроченная задолжность | K5: Анализ временной задолженности | S5: Контроль
I7: из них | L7: 31-60 | M7: 61-90 | N7: 91-180 | O7: 181-365 | P7: 366 дней- | Q7: Свыше 2
A8: № | B8: Характеристики | D8: % | F8: % | G8: Всего | H8: % | I8: прсроч. | J8: в суде | K8: 1-30 дней | L8: дней | M8: дней | N8: дней | O8: дней | P8: 2лет | Q8: лет
B9: {А} | C9: {Б} | D9: {В} | E9: {Г} | F9: {Д} | G9: {Е} | H9: {Ж} | K9: {З} | L9: {И} | M9: {К} | N9: {Л} | O9: {М} | P9: {Н} | Q9: {О}
B10: По типу клиента
A11: 1 | B11: Центральный банк | C11: ='Loans Receivable'!C113 -> #VALUE! | D11: =C11/C$24 -> #VALUE! | F11: =IF(E$24=0,"",E11/E$24) -> #VALUE! | H11: =IF($G$24=0,"",G11/$G$24) -> #VALUE! | S11: =SUM(K11:Q11) -> 0
A12: 2 | B12: Другие банки | C12: ='Loans Receivable'!C112 -> #VALUE! | D12: =C12/C$24 -> #VALUE! | E12: #FNECTC{12109,14505,13309,14305,15619;07;;;E} | F12: =E12/E$24 -> #VALUE! | G12: =I12+J12 -> #VALUE! | H12: =G12/G$24 -> #VALUE! | I12: ='Loans Receivable'!F112 -> #VALUE! | J12: ='Loans Receivable'!E112 -> #VALUE! | K12: #FN5{;12105;1-30} | L12: #FN5{;12105;31-60} | M12: #FN5{;12105;61-90} | N12: #FN5{;12105;91-180} | O12: #FN5{;12105;181-365} | P12: #FN5{;12105;366-730} | Q12: =G12-P12-O12-N12-M12-L12-K12 -> #VALUE! | S12: =SUM(K12:Q12) -> #VALUE!
A13: 3 | B13: Правительство | C13: ='Loans Receivable'!C114 -> #VALUE! | D13: =C13/C$24 -> #VALUE! | E13: #FNECTC{12309,14705,13309,14305,15619;01;;;E} | F13: =E13/E$24 -> #VALUE! | G13: =I13+J13 -> #VALUE! | H13: =G13/G$24 -> #VALUE! | I13: ='Loans Receivable'!F114 -> #VALUE! | J13: ='Loans Receivable'!E114 -> #VALUE! | K13: #FN5{;12305;1-30} | L13: #FN5{;12305;31-60} | M13: #FN5{;12305;61-90} | N13: #FN5{;12305;91-180} | O13: #FN5{;12305;181-365} | P13: #FN5{;12305;366-730} | Q13: =G13-P13-O13-N13-M13-L13-K13 -> #VALUE! | S13: =SUM(K13:Q13) -> #VALUE!
A14: 4 | B14: Физические лица | C14: ='Loans Receivable'!C107 -> #VALUE! | D14: =C14/C$24 -> #VALUE! | E14: #FNECTC{12509,14905,13309,14305,15619;08;;;E} | F14: =E14/E$24 -> #VALUE! | G14: =I14+J14 -> #VALUE! | H14: =G14/G$24 -> #VALUE! | I14: ='Loans Receivable'!F107 -> #FNECTCP{12501,12509,14901,14905,11101,13301,13309,14301,14305,15603;08;;;E} | J14: ='Loans Receivable'!E107 -> #FNECTC{15701,15705;08;;;E} | K14: #FN5{;12505;1-30} | L14: #FN5{;12505;31-60} | M14: #FN5{;12505;61-90} | N14: #FN5{;12505;91-180} | O14: #FN5{;12505;181-365} | P14: #FN5{;12505;366-730} | Q14: =G14-P14-O14-N14-M14-L14-K14 -> #VALUE! | S14: =SUM(K14:Q14) -> #VALUE!
A15: 5 | B15: Государственные предприятия | C15: ='Loans Receivable'!C108 -> #VALUE! | D15: =C15/C$24 -> #VALUE! | E15: #FNECTC{12709,15105,13309,14305,15619;02;;;E} | F15: =E15/E$24 -> #VALUE! | G15: =I15+J15 -> #VALUE! | H15: =G15/G$24 -> #VALUE! | I15: ='Loans Receivable'!F108 -> #VALUE! | J15: ='Loans Receivable'!E108 -> #VALUE! | K15: #FN5{;12705;1-30} | L15: #FN5{;12705;31-60} | M15: #FN5{;12705;61-90} | N15: #FN5{;12705;91-180} | O15: #FN5{;12705;181-365} | P15: #FN5{;12705;366-730} | Q15: =G15-P15-O15-N15-M15-L15-K15 -> #VALUE! | S15: =SUM(K15:Q15) -> #VALUE!
A16: 6 | B16: Совместные и иностранные предприятия | C16: ='Loans Receivable'!C109 -> #VALUE! | D16: =C16/C$24 -> #VALUE! | E16: #FNECTC{12909,15305,13309,14305,15619;10;;;E} | F16: =E16/E$24 -> #VALUE! | G16: =I16+J16 -> #VALUE! | H16: =G16/G$24 -> #VALUE! | I16: ='Loans Receivable'!F109 -> #VALUE! | J16: ='Loans Receivable'!E109 -> #VALUE! | K16: #FN5{;12905;1-30} | L16: #FN5{;12905;31-60} | M16: #FN5{;12905;61-90} | N16: #FN5{;12905;91-180} | O16: #FN5{;12905;181-365} | P16: #FN5{;12905;366-730} | Q16: =G16-P16-O16-N16-M16-L16-K16 -> #VALUE! | S16: =SUM(K16:Q16) -> #VALUE!
A17: 7 | B17: Частные товарищества и корпорации | C17: ='Loans Receivable'!C110 -> #VALUE! | D17: =C17/C$24 -> #VALUE! | E17: =E47 -> #VALUE! | F17: =E17/E$24 -> #VALUE! | G17: =I17+J17 -> #VALUE! | H17: =G17/G$24 -> #VALUE! | I17: =I47 -> #VALUE! | J17: =J47 -> #VALUE! | K17: =K47 -> #VALUE! | L17: =L47 -> #VALUE! | M17: =M47 -> #VALUE! | N17: =N47 -> #VALUE! | O17: =O47 -> #VALUE! | P17: =P47 -> #VALUE! | Q17: =G17-P17-O17-N17-M17-L17-K17 -> #VALUE! | S17: =SUM(K17:Q17) -> #VALUE!
A18: 8 | B18: Фермерские хозяйства | C18: ='Loans Receivable'!C111 -> 0 | D18: =C18/C$24 -> #VALUE! | E18: =E46 -> 0 | F18: =E18/E$24 -> #VALUE! | G18: =I18+J18 -> 0 | H18: =G18/G$24 -> #VALUE! | I18: =I46 -> 0 | J18: =J46 -> 0 | K18: =K46 -> 0 | L18: =L46 -> 0 | M18: =M46 -> 0 | N18: =N46 -> 0 | O18: =O46 -> 0 | P18: =P46 -> 0 | Q18: =G18-P18-O18-N18-M18-L18-K18 -> 0 | S18: =SUM(K18:Q18) -> 0
A19: 9 | B19: Небанковские финансовые институты | C19: ='Loans Receivable'!C115 -> #VALUE! | D19: =C19/C$24 -> #VALUE! | E19: #FNECTC{13209,15405,13309,14305,15619;04;;;E} | F19: =E19/E$24 -> #VALUE! | G19: =I19+J19 -> #VALUE! | H19: =G19/G$24 -> #VALUE! | I19: ='Loans Receivable'!F115 -> #VALUE! | J19: ='Loans Receivable'!E115 -> #VALUE! | K19: #FN5{;13205;1-30} | L19: #FN5{;13205;31-60} | M19: #FN5{;13205;61-90} | N19: #FN5{;13205;91-180} | O19: #FN5{;13205;181-365} | P19: #FN5{;13205;366-730} | Q19: =G19-P19-O19-N19-M19-L19-K19 -> #VALUE! | S19: =SUM(K19:Q19) -> #VALUE!
A20: 10 | B20: Негосударственные, некомерческие организации | C20: ='Loans Receivable'!C116 -> #VALUE! | D20: =C20/C$24 -> #VALUE! | E20: #FNECTC{13009,15205,13309,14305,15619;03;;;E} | F20: =E20/E$24 -> #VALUE! | G20: =I20+J20 -> #VALUE! | H20: =G20/G$24 -> #VALUE! | I20: ='Loans Receivable'!F116 -> #FNECTCP{13001,13009,15201,15205,11101,13301,13309,14301,14305,15611;03;;;E} | J20: ='Loans Receivable'!E116 -> #FNECTC{15701,15705;03;;;E} | K20: #FN5{;13005;1-30} | L20: #FN5{;13005;31-60} | M20: #FN5{;13005;61-90} | N20: #FN5{;13005;91-180} | O20: #FN5{;13005;181-365} | P20: #FN5{;13005;366-730} | Q20: =G20-P20-O20-N20-M20-L20-K20 -> #VALUE! | S20: =SUM(K20:Q20) -> #VALUE!
A21: 11 | B21: Бюджетные организации | C21: ='Loans Receivable'!C117 -> #VALUE! | D21: =C21/C$24 -> #VALUE! | E21: #FNECTC{12409,14809,13309,14305,15619;12;;;E} | F21: =E21/E$24 -> #VALUE! | G21: =I21+J21 -> #VALUE! | H21: =G21/G$24 -> #VALUE! | I21: ='Loans Receivable'!F117 -> #VALUE! | J21: ='Loans Receivable'!E117 -> #VALUE! | K21: #FN5{;12405;1-30} | L21: #FN5{;12405;31-60} | M21: #FN5{;12405;61-90} | N21: #FN5{;12405;91-180} | O21: #FN5{;12405;181-365} | P21: #FN5{;12405;366-730} | Q21: =G21-P21-O21-N21-M21-L21-K21 -> #VALUE! | S21: =SUM(K21:Q21) -> #VALUE!
A22: 12 | B22: Прочие | C22: ='Loans Receivable'!C118 -> #VALUE! | D22: =C22/C$24 -> #VALUE! | E22: #FNECTC{12609,15005,13309,14305,15619;11;;;E} | F22: =E22/E$24 -> #VALUE! | G22: =I22+J22 -> #VALUE! | H22: =G22/G$24 -> #VALUE! | I22: ='Loans Receivable'!F118 -> #VALUE! | J22: ='Loans Receivable'!E118 -> #VALUE! | K22: #FN5{;12605;1-30} | L22: #FN5{;12605;31-60} | M22: #FN5{;12605;61-90} | N22: #FN5{;12605;91-180} | O22: #FN5{;12605;181-365} | P22: #FN5{;12605;366-730} | Q22: =G22-P22-O22-N22-M22-L22-K22 -> #VALUE! | S22: =SUM(K22:Q22) -> #VALUE!
G23: =I23+J23 -> 0
A24: 13 | B24: Итого кредита и лизинга | C24: =SUM(C11:C22) -> #VALUE! | D24: =C24/C$24 -> #VALUE! | E24: =SUM(E11:E22) -> #VALUE! | F24: =E24/E$24 -> #VALUE! | G24: =I24+J24 -> #VALUE! | H24: =G24/G$24 -> #VALUE! | I24: =SUM(I11:I22) -> #VALUE! | J24: =SUM(J11:J22) -> #VALUE! | K24: =SUM(K11:K22) -> #VALUE! | L24: =SUM(L11:L22) -> #VALUE! | M24: =SUM(M11:M22) -> #VALUE! | N24: =SUM(N11:N22) -> #VALUE! | O24: =SUM(O11:O22) -> #VALUE! | P24: =SUM(P11:P22) -> #VALUE! | Q24: =SUM(Q11:Q22) -> #VALUE! | S24: =SUM(K24:Q24) -> #VALUE!
B26: По сектору экономики
A27: 14 | B27: Промышленность | C27: ='Loans Receivable'!C19 -> #VALUE! | D27: =C27/C$36 -> #VALUE! | E27: #FNECTC{12109,12309,12409,12509,12609,12709,12909,13009,13109,13209,13309,14305,14505,14705,14809,14905,15005,15105,15205,15305,15405,15505,15619;;1;;E} | F27: =E27/E$36 -> #VALUE! | G27: =I27+J27 -> 0 | H27: =G27/G$36 -> #VALUE! | I27: ='Loans Receivable'!F19 -> 0 | J27: ='Loans Receivable'!E19 -> 0 | K27: #FN5{1;12105,12305,12505,12605,12705,12905,13005,13105,13205,13305,15617,11103;1-30} | L27: #FN5{1;12105,12305,12505,12605,12705,12905,13005,13105,13205,13305,15617,11103;31-60} | M27: #FN5{1;12105,12305,12505,12605,12705,12905,13005,13105,13205,13305,15617,11103;61-90} | N27: #FN5{1;12105,12305,12505,12605,12705,12905,13005,13105,13205,13305,15617,11103;91-180} | O27: #FN5{1;12105,12305,12505,12605,12705,12905,13005,13105,13205,13305,15617,11103;181-365} | P27: #FN5{1;12105,12305,12505,12605,12705,12905,13005,13105,13205,13305,15617,11103;366-730} | Q27: =G27-K27-P27-O27-N27-M27-L27 -> #VALUE! | S27: =SUM(K27:Q27) -> #VALUE!
A28: 15 | B28: Сельское хозяйство | C28: ='Loans Receivable'!C32 -> #VALUE! | D28: =C28/C$36 -> #VALUE! | E28: #FNECTC{12109,12309,12409,12509,12609,12709,12909,13009,13109,13209,13309,14305,14505,14705,14809,14905,15005,15105,15205,15305,15405,15505,15619;;2;;E} | F28: =E28/E$36 -> #VALUE! | G28: =I28+J28 -> #VALUE! | H28: =G28/G$36 -> #VALUE! | I28: ='Loans Receivable'!F32 -> #VALUE! | J28: ='Loans Receivable'!E32 -> #VALUE! | K28: #FN5{2;12105,12305,12505,12605,12705,12905,13005,13105,13205,13305,15617,11103;1-30} | L28: #FN5{2;12105,12305,12505,12605,12705,12905,13005,13105,13205,13305,15617,11103;31-60} | M28: #FN5{2;12105,12305,12505,12605,12705,12905,13005,13105,13205,13305,15617,11103;61-90} | N28: #FN5{2;12105,12305,12505,12605,12705,12905,13005,13105,13205,13305,15617,11103;91-180} | O28: #FN5{2;12105,12305,12505,12605,12705,12905,13005,13105,13205,13305,15617,11103;181-365} | P28: #FN5{2;12105,12305,12505,12605,12705,12905,13005,13105,13205,13305,15617,11103;366-730} | Q28: =G28-K28-P28-O28-N28-M28-L28 -> #VALUE! | S28: =SUM(K28:Q28) -> #VALUE!
A29: 16 | B29: Транспорт и коммуникации | C29: ='Loans Receivable'!C44 -> #VALUE! | D29: =C29/C$36 -> #VALUE! | E29: #FNECTC{12109,12309,12409,12509,12609,12709,12909,13009,13109,13209,13309,14305,14505,14705,14809,14905,15005,15105,15205,15305,15405,15505,15619;;5;;E} | F29: =E29/E$36 -> #VALUE! | G29: =I29+J29 -> 0 | H29: =G29/G$36 -> #VALUE! | I29: ='Loans Receivable'!F44 -> 0 | J29: ='Loans Receivable'!E44 -> 0 | K29: #FN5{5;12105,12305,12505,12605,12705,12905,13005,13105,13205,13305,15617,11103;1-30} | L29: #FN5{5;12105,12305,12505,12605,12705,12905,13005,13105,13205,13305,15617,11103;31-60} | M29: #FN5{5;12105,12305,12505,12605,12705,12905,13005,13105,13205,13305,15617,11103;61-90} | N29: #FN5{5;12105,12305,12505,12605,12705,12905,13005,13105,13205,13305,15617,11103;91-180} | O29: #FN5{5;12105,12305,12505,12605,12705,12905,13005,13105,13205,13305,15617,11103;181-365} | P29: #FN5{5;12105,12305,12505,12605,12705,12905,13005,13105,13205,13305,15617,11103;166-730} | Q29: =G29-K29-P29-O29-N29-M29-L29 -> #VALUE! | S29: =SUM(K29:Q29) -> #VALUE!
A30: 17 | B30: Строительство | C30: ='Loans Receivable'!C56 -> #VALUE! | D30: =C30/C$36 -> #VALUE! | E30: #FNECTC{12109,12309,12409,12509,12609,12709,12909,13009,13109,13209,13309,14305,14505,14705,,14809,14905,15005,15105,15205,15305,15405,15505,15619;;6;;E} | F30: =E30/E$36 -> #VALUE! | G30: =I30+J30 -> 0 | H30: =G30/G$36 -> #VALUE! | I30: ='Loans Receivable'!F56 -> 0 | J30: ='Loans Receivable'!E56 -> 0 | K30: #FN5{6;12105,12305,12505,12605,12705,12905,13005,13105,13205,13305,15617,11103;1-30} | L30: #FN5{6;12105,12305,12505,12605,12705,12905,13005,13105,13205,13305,15617,11103;31-60} | M30: #FN5{6;12105,12305,12505,12605,12705,12905,13005,13105,13205,13305,15617,11103;61-90} | N30: #FN5{6;12105,12305,12505,12605,12705,12905,13005,13105,13205,13305,15617,11103;91-180} | O30: #FN5{6;12105,12305,12505,12605,12705,12905,13005,13105,13205,13305,15617,11103;181-365} | P30: #FN5{6;12105,12305,12505,12605,12705,12905,13005,13105,13205,13305,15617,11103;366-730} | Q30: =G30-K30-P30-O30-N30-M30-L30 -> #VALUE! | S30: =SUM(K30:Q30) -> #VALUE!
A31: 18 | B31: Торговля и общественное питание | C31: ='Loans Receivable'!C68 -> #VALUE! | D31: =C31/C$36 -> #VALUE! | E31: #FNECTC{12109,12309,12409,12509,12609,12709,12909,13009,13109,13209,13309,14305,14505,14705,14809,14905,15005,15105,15205,15305,15405,15505,15619;;7;;E} | F31: =E31/E$36 -> #VALUE! | G31: =I31+J31 -> 0 | H31: =G31/G$36 -> #VALUE! | I31: ='Loans Receivable'!F68 -> 0 | J31: ='Loans Receivable'!E68 -> 0 | K31: #FN5{7;12105,12305,12505,12605,12705,12905,13005,13105,13205,13305,15617,11103;1-30} | L31: #FN5{7;12105,12305,12505,12605,12705,12905,13005,13105,13205,13305,15617,11103;31-60} | M31: #FN5{7;12105,12305,12505,12605,12705,12905,13005,13105,13205,13305,15617,11103;61-90} | N31: #FN5{7;12105,12305,12505,12605,12705,12905,13005,13105,13205,13305,15617,11103;91-180} | O31: #FN5{7;12105,12305,12505,12605,12705,12905,13005,13105,13205,13305,15617,11103;181-365} | P31: #FN5{7;12105,12305,12505,12605,12705,12905,13005,13105,13205,13305,15617,11103;366-730} | Q31: =G31-K31-P31-O31-N31-M31-L31 -> #VALUE! | S31: =SUM(K31:Q31) -> #VALUE!
A32: 19 | B32: Материально-техническое снабжение и сбыт | C32: ='Loans Receivable'!C80 -> #VALUE! | D32: =C32/C$36 -> #VALUE! | E32: #FNECTC{12109,12309,12409,12509,12609,12709,12909,13009,13109,13209,13309,14305,14505,14705,14809,14905,15005,15105,15205,15305,15405,15505,15619;;8;;E} | F32: =E32/E$36 -> #VALUE! | G32: =I32+J32 -> 0 | H32: =G32/G$36 -> #VALUE! | I32: ='Loans Receivable'!F80 -> 0 | J32: ='Loans Receivable'!E80 -> 0 | K32: #FN5{8;12105,12305,12505,12605,12705,12905,13005,13105,13205,13305,15617,11103;1-30} | L32: #FN5{8;12105,12305,12505,12605,12705,12905,13005,13105,13205,13305,15617,11103;31-60} | M32: #FN5{8;12105,12305,12505,12605,12705,12905,13005,13105,13205,13305,15617,11103;61-90} | N32: #FN5{8;12105,12305,12505,12605,12705,12905,13005,13105,13205,13305,15617,11103;91-180} | O32: #FN5{8;12105,12305,12505,12605,12705,12905,13005,13105,13205,13305,15617,11103;181-365} | P32: #FN5{8;12105,12305,12505,12605,12705,12905,13005,13105,13205,13305,15617,11103;366-730} | Q32: =G32-K32-P32-O32-N32-M32-L32 -> #VALUE! | S32: =SUM(K32:Q32) -> #VALUE!
A33: 20 | B33: Жилищно-коммунальные услуги | C33: ='Loans Receivable'!C92 -> #VALUE! | D33: =C33/C$36 -> #VALUE! | E33: #FNECTC{12109,12309,12409,12509,12609,12709,12909,13009,13109,13209,13309,14305,14505,14705,14809,14905,15005,15105,15205,15305,15405,15505,15619;;9;;E} | F33: =E33/E$36 -> #VALUE! | G33: =I33+J33 -> 0 | H33: =G33/G$36 -> #VALUE! | I33: ='Loans Receivable'!F92 -> 0 | J33: ='Loans Receivable'!E92 -> 0 | K33: #FN5{9;12105,12305,12505,12605,12705,12905,13005,13105,13205,13305,15617,11103;1-30} | L33: #FN5{9;12105,12305,12505,12605,12705,12905,13005,13105,13205,13305,15617,11103;31-60} | M33: #FN5{9;12105,12305,12505,12605,12705,12905,13005,13105,13205,13305,15617,11103;61-90} | N33: #FN5{9;12105,12305,12505,12605,12705,12905,13005,13105,13205,13305,15617,11103;91-180} | O33: #FN5{9;12105,12305,12505,12605,12705,12905,13005,13105,13205,15617,11103;181-365} | P33: #FN5{9;12105,12305,12505,12605,12705,12905,13005,13105,13205,13305,15617,11103;366-730} | Q33: =G33-K33-P33-O33-N33-M33-L33 -> #VALUE! | S33: =SUM(K33:Q33) -> #VALUE!
A34: 21 | B34: Другие сектора | C34: ='Loans Receivable'!C105 -> #VALUE! | D34: =C34/C$36 -> #VALUE! | E34: =E24-E27-E28-E29-E30-E31-E32-E33 -> #VALUE! | F34: =E34/E$36 -> #VALUE! | G34: =I34+J34 -> #VALUE! | H34: =G34/G$36 -> #VALUE! | I34: ='Loans Receivable'!F105 -> #VALUE! | J34: ='Loans Receivable'!E105 -> #VALUE! | K34: =K24-K27-K28-K29-K30-K31-K32-K33 -> #VALUE! | L34: =L24-L27-L28-L29-L30-L31-L32-L33 -> #VALUE! | M34: =M24-M27-M28-M29-M30-M31-M32-M33 -> #VALUE! | N34: =N24-N27-N28-N29-N30-N31-N32-N33 -> #VALUE! | O34: =O24-O27-O28-O29-O30-O31-O32-O33 -> #VALUE! | P34: =P24-P27-P28-P29-P30-P31-P32-P33 -> #VALUE! | Q34: =Q24-Q27-Q28-Q29-Q30-Q31-Q32-Q33 -> #VALUE! | S34: =SUM(K34:Q34) -> #VALUE!
F35: =IF(E$24=0,"",E35/E$24) -> #VALUE! | H35: =IF(G$24=0,"",G35/G$24) -> #VALUE!
A36: 22 | B36: Итого кредита и лизинга | C36: =SUM(C27:C34) -> #VALUE! | D36: =C36/C$36 -> #VALUE! | E36: =SUM(E27:E34) -> #VALUE! | F36: =E36/E$36 -> #VALUE! | G36: =SUM(G27:G34) -> #VALUE! | H36: =G36/G$36 -> #VALUE! | I36: =SUM(I27:I35) -> #VALUE! | J36: =SUM(J27:J34) -> #VALUE! | K36: =SUM(K27:K34) -> #VALUE! | L36: =SUM(L27:L34) -> #VALUE! | M36: =SUM(M27:M34) -> #VALUE! | N36: =SUM(N27:N34) -> #VALUE! | O36: =SUM(O27:O34) -> #VALUE! | P36: =SUM(P27:P34) -> #VALUE! | Q36: =SUM(Q27:Q34) -> #VALUE! | S36: =SUM(K36:Q36) -> #VALUE!
B38: Подпись Руководителя:
B40: Подпись Главного Бухгалтера:
B44: Код формы собственности =113 (фермерские хоз-ва)
B45: Частные товарищества и корпорации всего | C45: ='Loans Receivable'!C136 -> #VALUE! | D45: =C45/C$24 -> #VALUE! | E45: #FNECTC{13109,15505,13309,14305,15619;09;;;E} | F45: =E45/E$24 -> #VALUE! | G45: =I45+J45 -> #VALUE! | H45: =G45/G$24 -> #VALUE! | I45: ='Loans Receivable'!F136 -> #FNECTCP{13101,13109,15501,15505,11101,13301,13309,14301,14305,15613;09;;;E} | J45: ='Loans Receivable'!E136 -> #FNECTC{15701,15705;09;;;E} | K45: #FN5{;13105;1-30} | L45: #FN5{;13105;31-60} | M45: #FN5{;13105;61-90} | N45: #FN5{;13105;91-180} | O45: #FN5{;13105;181-365} | P45: #FN5{;13105;366-730} | Q45: =G45-P45-O45-N45-M45-L45-K45 -> #VALUE! | S45: =SUM(K45:Q45) -> #VALUE!
B46: Фермерские хозяйства (ЧТК и КФС=113) | C46: ='Loans Receivable'!C137 -> 0 | D46: =C46/C$24 -> #VALUE! | E46: 0 | F46: =E46/E$24 -> #VALUE! | G46: =I46+J46 -> 0 | H46: =G46/G$24 -> #VALUE! | I46: ='Loans Receivable'!F137 -> 0 | J46: ='Loans Receivable'!E137 -> 0 | K46: 0 | L46: 0 | M46: 0 | N46: 0 | O46: 0 | P46: 0 | Q46: =G46-P46-O46-N46-M46-L46-K46 -> 0 | S46: =SUM(K46:Q46) -> 0
B47: Частные товарищества и корпорации без КФС=113 | C47: ='Loans Receivable'!C138 -> #VALUE! | D47: =C47/C$24 -> #VALUE! | E47: =E45-E46 -> #VALUE! | F47: =E47/E$24 -> #VALUE! | G47: =I47+J47 -> #VALUE! | H47: =G47/G$24 -> #VALUE! | I47: ='Loans Receivable'!F138 -> #VALUE! | J47: ='Loans Receivable'!E138 -> #VALUE! | K47: =K45-K46 -> #VALUE! | L47: =L45-L46 -> #VALUE! | M47: =M45-M46 -> #VALUE! | N47: =N45-N46 -> #VALUE! | O47: =O45-O46 -> #VALUE! | P47: =P45-P46 -> #VALUE! | Q47: =G47-P47-O47-N47-M47-L47-K47 -> #VALUE! | S47: =SUM(K47:Q47) -> #VALUE!
B48: Прочие

Sheet Loan Classification
V1: Приложение №1 к Рекомендациям по заполнению отчетности коммерческих банков по банковскому надзору представляемых Центральному банку Республики Узбекистан
A2: Отчет о классификации активов по классу качества | W2: Таблица-10 (Форма-1596LKA)
B3: #FNP{date_end} | U3: Balance'!B3
A4: № | B4: Статьи баланса | C4: Общая сумма | D4: Стандартные | E4: 1- срочная | F4: 1- просрочка | G4: Общие резервы (1%) | H4: Субстандартные | I4: 2- срочная | J4: 2- просрочка | K4: Специальные резервы (мин 10%) | L4: Неудовлетворительные | M4: 3- срочная | N4: 3- просрочка | O4: Специальные резервы (мин 25%) | P4: Сомнительные | Q4: 4 - срочная | R4: 4- просрочка | S4: Специальные резервы (мин 50%) | T4: Безнадежные | U4: 5 - срочная | V4: 5- просрочка | W4: Специальные резервы (100%) | X4: Совокупная сумма специальных резервов | AB4: хорошие
A5: А | B5: Б | C5: B | D5: Г | G5: Д | H5: Е | K5: Ж | L5: З | O5: И | P5: К | S5: Л | T5: М | W5: Н | X5: О=Ж+И+Л+Н | Z5: всего | AA5: срочные | AB5: просроченные | AD5: контроль
A6: 1 | B6: Промышленность | C6: ='Aging Analysis'!C27 -> #VALUE! | D6: =E6+F6 -> #VALUE! | E6: #FNECTCO{11101,11103,11105,11195,12301,12305,12309,12401,12405,12409,12501,12505,12509,12601,12605,12609,12701,12705,12709,12901,12905,12909,13001,13005,13009,13101,13105,13109,13201,13205,13209,13301,13305,13309,14301,14305,14601,14701,14705,14801,14809,14901,14905,15001,15005,15101,15105,15201,15205,15301,15305,15401,15405,15501,15505,15605,15607,15609,15611,15613,15615,15701,15703,15705;;1;1;;E} | F6: #FNECTCOP{11101,11103,11105,11195,12301,12305,12309,12401,12405,12409,12501,12505,12509,12601,12605,12609,12701,12705,12709,12901,12905,12909,13001,13005,13009,13101,13105,13109,13201,13205,13209,13301,13305,13309,14301,14305,14601,14701,14705,14801,14809,14901,14905,15001,15005,15101,15105,15201,15205,15301,15305,15401,15405,15501,15505,15605,15607,15609,15611,15613,15615,15701,15703,15705;;1;1;;E} | G6: #FNECTCR{11101,11103,11105,11195,12301,12305,12309,12401,12405,12409,12501,12505,12509,12601,12605,12609,12701,12705,12709,12901,12905,12909,13001,13005,13009,13101,13105,13109,13201,13205,13209,13301,13305,13309,14301,14305,14601,14701,14705,14801,14809,14901,14905,15001,15005,15101,15105,15201,15205,15301,15305,15401,15405,15501,15505,15605,15607,15609,15611,15613,15615,15701,15703,15705;;1;1;;E} | H6: =I6+J6 -> #VALUE! | I6: #FNECTCO{11101,11103,11105,11195,12301,12305,12309,12401,12405,12409,12501,12505,12509,12601,12605,12609,12701,12705,12709,12901,12905,12909,13001,13005,13009,13101,13105,13109,13201,13205,13209,13301,13305,13309,14301,14305,14601,14701,14705,14801,14809,14901,14905,15001,15005,15101,15105,15201,15205,15301,15305,15401,15405,15501,15505,15605,15607,15609,15611,15613,15615,15701,15703,15705;;1;2;;E} | J6: #FNECTCOP{11101,11103,11105,11195,12301,12305,12309,12401,12405,12409,12501,12505,12509,12601,12605,12609,12701,12705,12709,12901,12905,12909,13001,13005,13009,13101,13105,13109,13201,13205,13209,13301,13305,13309,14301,14305,14601,14701,14705,14801,14809,14901,14905,15001,15005,15101,15105,15201,15205,15301,15305,15401,15405,15501,15505,15605,15607,15609,15611,15613,15615,15701,15703,15705;;1;2;;E} | K6: #FNECTCR{11101,11103,11105,11195,12301,12305,12309,12401,12405,12409,12501,12505,12509,12601,12605,12609,12701,12705,12709,12901,12905,12909,13001,13005,13009,13101,13105,13109,13201,13205,13209,13301,13305,13309,14301,14305,14601,14701,14705,14801,14809,14901,14905,15001,15005,15101,15105,15201,15205,15301,15305,15401,15405,15501,15505,15605,15607,15609,15611,15613,15615,15701,15703,15705;;1;2;;E} | L6: =M6+N6 -> #VALUE! | M6: #FNECTCO{11101,11103,11105,11195,12301,12305,12309,12401,12405,12409,12501,12505,12509,12601,12605,12609,12701,12705,12709,12901,12905,12909,13001,13005,13009,13101,13105,13109,13201,13205,13209,13301,13305,13309,14301,14305,14601,14701,14705,14801,14809,14901,14905,15001,15005,15101,15105,15201,15205,15301,15305,15401,15405,15501,15505,15605,15607,15609,15611,15613,15615,15701,15703,15705;;1;3;;E} | N6: #FNECTCOP{11101,11103,11105,11195,12301,12305,12309,12401,12405,12409,12501,12505,12509,12601,12605,12609,12701,12705,12709,12901,12905,12909,13001,13005,13009,13101,13105,13109,13201,13205,13209,13301,13305,13309,14301,14305,14601,14701,14705,14801,14809,14901,14905,15001,15005,15101,15105,15201,15205,15301,15305,15401,15405,15501,15505,15605,15607,15609,15611,15613,15615,15701,15703,15705;;1;3;;E} | O6: #FNECTCR{11101,11103,11105,11195,12301,12305,12309,12401,12405,12409,12501,12505,12509,12601,12605,12609,12701,12705,12709,12901,12905,12909,13001,13005,13009,13101,13105,13109,13201,13205,13209,13301,13305,13309,14301,14305,14601,14701,14705,14801,14809,14901,14905,15001,15005,15101,15105,15201,15205,15301,15305,15401,15405,15501,15505,15605,15607,15609,15611,15613,15615,15701,15703,15705;;1;3;;E} | P6: =Q6+R6 -> #VALUE! | Q6: #FNECTCOP{11101,11103,11105,11195,12301,12305,12309,12401,12405,12409,12501,12505,12509,12601,12605,12609,12701,12705,12709,12901,12905,12909,13001,13005,13009,13101,13105,13109,13201,13205,13209,13301,13305,13309,14301,14305,14601,14701,14705,14801,14809,14901,14905,15001,15005,15101,15105,15201,15205,15301,15305,15401,15405,15501,15505,15605,15607,15609,15611,15613,15615,15701,15703,15705;;1;4;;E} | R6: #FNECTCO{11101,11103,11105,11195,12301,12305,12309,12401,12405,12409,12501,12505,12509,12601,12605,12609,12701,12705,12709,12901,12905,12909,13001,13005,13009,13101,13105,13109,13201,13205,13209,13301,13305,13309,14301,14305,14601,14701,14705,14801,14809,14901,14905,15001,15005,15101,15105,15201,15205,15301,15305,15401,15405,15501,15505,15605,15607,15609,15611,15613,15615,15701,15703,15705;;1;4;;E} | S6: #FNECTCR{11101,11103,11105,11195,12301,12305,12309,12401,12405,12409,12501,12505,12509,12601,12605,12609,12701,12705,12709,12901,12905,12909,13001,13005,13009,13101,13105,13109,13201,13205,13209,13301,13305,13309,14301,14305,14601,14701,14705,14801,14809,14901,14905,15001,15005,15101,15105,15201,15205,15301,15305,15401,15405,15501,15505,15605,15607,15609,15611,15613,15615,15701,15703,15705;;1;4;;E} | T6: =U6+V6 -> #VALUE! | U6: #FNECTCO{11101,11103,11105,11195,12301,12305,12309,12401,12405,12409,12501,12505,12509,12601,12605,12609,12701,12705,12709,12901,12905,12909,13001,13005,13009,13101,13105,13109,13201,13205,13209,13301,13305,13309,14301,14305,14601,14701,14705,14801,14809,14901,14905,15001,15005,15101,15105,15201,15205,15301,15305,15401,15405,15501,15505,15605,15607,15609,15611,15613,15615,15701,15703,15705;;1;5;;E} | V6: #FNECTCOP{11101,11103,11105,11195,12301,12305,12309,12401,12405,12409,12501,12505,12509,12601,12605,12609,12701,12705,12709,12901,12905,12909,13001,13005,13009,13101,13105,13109,13201,13205,13209,13301,13305,13309,14301,14305,14601,14701,14705,14801,14809,14901,14905,15001,15005,15101,15105,15201,15205,15301,15305,15401,15405,15501,15505,15605,15607,15609,15611,15613,15615,15701,15703,15705;;1;5;;E} | W6: #FNECTCR{11101,11103,11105,11195,12301,12305,12309,12401,12405,12409,12501,12505,12509,12601,12605,12609,12701,12705,12709,12901,12905,12909,13001,13005,13009,13101,13105,13109,13201,13205,13209,13301,13305,13309,14301,14305,14601,14701,14705,14801,14809,14901,14905,15001,15005,15101,15105,15201,15205,15301,15305,15401,15405,15501,15505,15605,15607,15609,15611,15613,15615,15701,15703,15705;;1;5;;E} | X6: =W6+S6+O6+K6+G6 -> #VALUE! | Z6: =D6+H6+L6+P6+T6 -> #VALUE! | AA6: =E6+I6+M6+Q6+U6 -> #VALUE! | AB6: =F6+J6+N6+R6+V6 -> #VALUE! | AD6: =C6-Z6 -> #VALUE!
A7: 2 | B7: Сельское хозяйство | C7: ='Aging Analysis'!C28 -> #VALUE! | D7: =E7+F7 -> #VALUE! | E7: #FNECTCO{11101,11103,11105,11195,12301,12305,12309,12401,12405,12409,12501,12505,12509,12601,12605,12609,12701,12705,12709,12901,12905,12909,13001,13005,13009,13101,13105,13109,13201,13205,13209,13301,13305,13309,14301,14305,14601,14701,14705,14801,14809,14901,14905,15001,15005,15101,15105,15201,15205,15301,15305,15401,15405,15501,15505,15605,15607,15609,15611,15613,15615,15701,15703,15705;;2;1;;E} | F7: #FNECTCOP{11101,11103,11105,11195,12301,12305,12309,12401,12405,12409,12501,12505,12509,12601,12605,12609,12701,12705,12709,12901,12905,12909,13001,13005,13009,13101,13105,13109,13201,13205,13209,13301,13305,13309,14301,14305,14601,14701,14705,14801,14809,14901,14905,15001,15005,15101,15105,15201,15205,15301,15305,15401,15405,15501,15505,15605,15607,15609,15611,15613,15615,15701,15703,15705;;2;1;;E} | G7: #FNECTCR{11101,11103,11105,11195,12301,12305,12309,12401,12405,12409,12501,12505,12509,12601,12605,12609,12701,12705,12709,12901,12905,12909,13001,13005,13009,13101,13105,13109,13201,13205,13209,13301,13305,13309,14301,14305,14601,14701,14705,14801,14809,14901,14905,15001,15005,15101,15105,15201,15205,15301,15305,15401,15405,15501,15505,15605,15607,15609,15611,15613,15615,15701,15703,15705;;2;1;;E} | H7: =I7+J7 -> #VALUE! | I7: #FNECTCO{11101,11103,11105,11195,12301,12305,12309,12401,12405,12409,12501,12505,12509,12601,12605,12609,12701,12705,12709,12901,12905,12909,13001,13005,13009,13101,13105,13109,13201,13205,13209,13301,13305,13309,14301,14305,14601,14701,14705,14801,14809,14901,14905,15001,15005,15101,15105,15201,15205,15301,15305,15401,15405,15501,15505,15605,15607,15609,15611,15613,15615,15701,15703,15705;;2;2;;E} | J7: #FNECTCOP{11101,11103,11105,11195,12301,12305,12309,12401,12405,12409,12501,12505,12509,12601,12605,12609,12701,12705,12709,12901,12905,12909,13001,13005,13009,13101,13105,13109,13201,13205,13209,13301,13305,13309,14301,14305,14601,14701,14705,14801,14809,14901,14905,15001,15005,15101,15105,15201,15205,15301,15305,15401,15405,15501,15505,15605,15607,15609,15611,15613,15615,15701,15703,15705;;2;2;;E} | K7: #FNECTCR{11101,11103,11105,11195,12301,12305,12309,12401,12405,12409,12501,12505,12509,12601,12605,12609,12701,12705,12709,12901,12905,12909,13001,13005,13009,13101,13105,13109,13201,13205,13209,13301,13305,13309,14301,14305,14601,14701,14705,14801,14809,14901,14905,15001,15005,15101,15105,15201,15205,15301,15305,15401,15405,15501,15505,15605,15607,15609,15611,15613,15615,15701,15703,15705;;2;2;;E} | L7: =M7+N7 -> #VALUE! | M7: #FNECTCO{11101,11103,11105,11195,12301,12305,12309,12401,12405,12409,12501,12505,12509,12601,12605,12609,12701,12705,12709,12901,12905,12909,13001,13005,13009,13101,13105,13109,13201,13205,13209,13301,13305,13309,14301,14305,14601,14701,14705,14801,14809,14901,14905,15001,15005,15101,15105,15201,15205,15301,15305,15401,15405,15501,15505,15605,15607,15609,15611,15613,15615,15701,15703,15705;;2;3;;E} | N7: #FNECTCOP{11101,11103,11105,11195,12301,12305,12309,12401,12405,12409,12501,12505,12509,12601,12605,12609,12701,12705,12709,12901,12905,12909,13001,13005,13009,13101,13105,13109,13201,13205,13209,13301,13305,13309,14301,14305,14601,14701,14705,14801,14809,14901,14905,15001,15005,15101,15105,15201,15205,15301,15305,15401,15405,15501,15505,15605,15607,15609,15611,15613,15615,15701,15703,15705;;2;3;;E} | O7: #FNECTCR{11101,11103,11105,11195,12301,12305,12309,12401,12405,12409,12501,12505,12509,12601,12605,12609,12701,12705,12709,12901,12905,12909,13001,13005,13009,13101,13105,13109,13201,13205,13209,13301,13305,13309,14301,14305,14601,14701,14705,14801,14809,14901,14905,15001,15005,15101,15105,15201,15205,15301,15305,15401,15405,15501,15505,15605,15607,15609,15611,15613,15615,15701,15703,15705;;2;3;;E} | P7: =Q7+R7 -> #VALUE! | Q7: #FNECTCOP{11101,11103,11105,11195,12301,12305,12309,12401,12405,12409,12501,12505,12509,12601,12605,12609,12701,12705,12709,12901,12905,12909,13001,13005,13009,13101,13105,13109,13201,13205,13209,13301,13305,13309,14301,14305,14601,14701,14705,14801,14809,14901,14905,15001,15005,15101,15105,15201,15205,15301,15305,15401,15405,15501,15505,15605,15607,15609,15611,15613,15615,15701,15703,15705;;2;4;;E} | R7: #FNECTCO{11101,11103,11105,11195,12301,12305,12309,12401,12405,12409,12501,12505,12509,12601,12605,12609,12701,12705,12709,12901,12905,12909,13001,13005,13009,13101,13105,13109,13201,13205,13209,13301,13305,13309,14301,14305,14601,14701,14705,14801,14809,14901,14905,15001,15005,15101,15105,15201,15205,15301,15305,15401,15405,15501,15505,15605,15607,15609,15611,15613,15615,15701,15703,15705;;2;4;;E} | S7: #FNECTCR{11101,11103,11105,11195,12301,12305,12309,12401,12405,12409,12501,12505,12509,12601,12605,12609,12701,12705,12709,12901,12905,12909,13001,13005,13009,13101,13105,13109,13201,13205,13209,13301,13305,13309,14301,14305,14601,14701,14705,14801,14809,14901,14905,15001,15005,15101,15105,15201,15205,15301,15305,15401,15405,15501,15505,15605,15607,15609,15611,15613,15615,15701,15703,15705;;2;4;;E} | T7: =U7+V7 -> #VALUE! | U7: #FNECTCO{11101,11103,11105,11195,12301,12305,12309,12401,12405,12409,12501,12505,12509,12601,12605,12609,12701,12705,12709,12901,12905,12909,13001,13005,13009,13101,13105,13109,13201,13205,13209,13301,13305,13309,14301,14305,14601,14701,14705,14801,14809,14901,14905,15001,15005,15101,15105,15201,15205,15301,15305,15401,15405,15501,15505,15605,15607,15609,15611,15613,15615,15701,15703,15705;;2;5;;E} | V7: #FNECTCOP{11101,11103,11105,11195,12301,12305,12309,12401,12405,12409,12501,12505,12509,12601,12605,12609,12701,12705,12709,12901,12905,12909,13001,13005,13009,13101,13105,13109,13201,13205,13209,13301,13305,13309,14301,14305,14601,14701,14705,14801,14809,14901,14905,15001,15005,15101,15105,15201,15205,15301,15305,15401,15405,15501,15505,15605,15607,15609,15611,15613,15615,15701,15703,15705;;2;5;;E} | W7: #FNECTCR{11101,11103,11105,11195,12301,12305,12309,12401,12405,12409,12501,12505,12509,12601,12605,12609,12701,12705,12709,12901,12905,12909,13001,13005,13009,13101,13105,13109,13201,13205,13209,13301,13305,13309,14301,14305,14601,14701,14705,14801,14809,14901,14905,15001,15005,15101,15105,15201,15205,15301,15305,15401,15405,15501,15505,15605,15607,15609,15611,15613,15615,15701,15703,15705;;2;5;;E} | X7: =W7+S7+O7+K7+G7 -> #VALUE! | Z7: =D7+H7+L7+P7+T7 -> #VALUE! | AA7: =E7+I7+M7+Q7+U7 -> #VALUE! | AB7: =F7+J7+N7+R7+V7 -> #VALUE! | AD7: =C7-Z7 -> #VALUE!
A8: 3 | B8: Транспорт и коммуникации | C8: ='Aging Analysis'!C29 -> #VALUE! | D8: =E8+F8 -> #VALUE! | E8: #FNECTCO{11101,11103,11105,11195,12301,12305,12309,12401,12405,12409,12501,12505,12509,12601,12605,12609,12701,12705,12709,12901,12905,12909,13001,13005,13009,13101,13105,13109,13201,13205,13209,13301,13305,13309,14301,14305,14601,14701,14705,14801,14809,14901,14905,15001,15005,15101,15105,15201,15205,15301,15305,15401,15405,15501,15505,15605,15607,15609,15611,15613,15615,15701,15703,15705;;5;1;;E} | F8: #FNECTCOP{11101,11103,11105,11195,12301,12305,12309,12401,12405,12409,12501,12505,12509,12601,12605,12609,12701,12705,12709,12901,12905,12909,13001,13005,13009,13101,13105,13109,13201,13205,13209,13301,13305,13309,14301,14305,14601,14701,14705,14801,14809,14901,14905,15001,15005,15101,15105,15201,15205,15301,15305,15401,15405,15501,15505,15605,15607,15609,15611,15613,15615,15701,15703,15705;;5;1;;E} | G8: #FNECTCR{11101,11103,11105,11195,12301,12305,12309,12401,12405,12409,12501,12505,12509,12601,12605,12609,12701,12705,12709,12901,12905,12909,13001,13005,13009,13101,13105,13109,13201,13205,13209,13301,13305,13309,14301,14305,14601,14701,14705,14801,14809,14901,14905,15001,15005,15101,15105,15201,15205,15301,15305,15401,15405,15501,15505,15605,15607,15609,15611,15613,15615,15701,15703,15705;;5;1;;E} | H8: =I8+J8 -> #VALUE! | I8: #FNECTCO{11101,11103,11105,11195,12301,12305,12309,12401,12405,12409,12501,12505,12509,12601,12605,12609,12701,12705,12709,12901,12905,12909,13001,13005,13009,13101,13105,13109,13201,13205,13209,13301,13305,13309,14301,14305,14601,14701,14705,14801,14809,14901,14905,15001,15005,15101,15105,15201,15205,15301,15305,15401,15405,15501,15505,15605,15607,15609,15611,15613,15615,15701,15703,15705;;5;2;;E} | J8: #FNECTCOP{11101,11103,11105,11195,12301,12305,12309,12401,12405,12409,12501,12505,12509,12601,12605,12609,12701,12705,12709,12901,12905,12909,13001,13005,13009,13101,13105,13109,13201,13205,13209,13301,13305,13309,14301,14305,14601,14701,14705,14801,14809,14901,14905,15001,15005,15101,15105,15201,15205,15301,15305,15401,15405,15501,15505,15605,15607,15609,15611,15613,15615,15701,15703,15705;;5;2;;E} | K8: #FNECTCR{11101,11103,11105,11195,12301,12305,12309,12401,12405,12409,12501,12505,12509,12601,12605,12609,12701,12705,12709,12901,12905,12909,13001,13005,13009,13101,13105,13109,13201,13205,13209,13301,13305,13309,14301,14305,14601,14701,14705,14801,14809,14901,14905,15001,15005,15101,15105,15201,15205,15301,15305,15401,15405,15501,15505,15605,15607,15609,15611,15613,15615,15701,15703,15705;;5;2;;E} | L8: =M8+N8 -> #VALUE! | M8: #FNECTCO{11101,11103,11105,11195,12301,12305,12309,12401,12405,12409,12501,12505,12509,12601,12605,12609,12701,12705,12709,12901,12905,12909,13001,13005,13009,13101,13105,13109,13201,13205,13209,13301,13305,13309,14301,14305,14601,14701,14705,14801,14809,14901,14905,15001,15005,15101,15105,15201,15205,15301,15305,15401,15405,15501,15505,15605,15607,15609,15611,15613,15615,15701,15703,15705;;5;3;;E} | N8: #FNECTCOP{11101,11103,11105,11195,12301,12305,12309,12401,12405,12409,12501,12505,12509,12601,12605,12609,12701,12705,12709,12901,12905,12909,13001,13005,13009,13101,13105,13109,13201,13205,13209,13301,13305,13309,14301,14305,14601,14701,14705,14801,14809,14901,14905,15001,15005,15101,15105,15201,15205,15301,15305,15401,15405,15501,15505,15605,15607,15609,15611,15613,15615,15701,15703,15705;;5;3;;E} | O8: #FNECTCR{11101,11103,11105,11195,12301,12305,12309,12401,12405,12409,12501,12505,12509,12601,12605,12609,12701,12705,12709,12901,12905,12909,13001,13005,13009,13101,13105,13109,13201,13205,13209,13301,13305,13309,14301,14305,14601,14701,14705,14801,14809,14901,14905,15001,15005,15101,15105,15201,15205,15301,15305,15401,15405,15501,15505,15605,15607,15609,15611,15613,15615,15701,15703,15705;;5;3;;E} | P8: =Q8+R8 -> #VALUE! | Q8: #FNECTCOP{11101,11103,11105,11195,12301,12305,12309,12401,12405,12409,12501,12505,12509,12601,12605,12609,12701,12705,12709,12901,12905,12909,13001,13005,13009,13101,13105,13109,13201,13205,13209,13301,13305,13309,14301,14305,14601,14701,14705,14801,14809,14901,14905,15001,15005,15101,15105,15201,15205,15301,15305,15401,15405,15501,15505,15605,15607,15609,15611,15613,15615,15701,15703,15705;;5;4;;E} | R8: #FNECTCO{11101,11103,11105,11195,12301,12305,12309,12401,12405,12409,12501,12505,12509,12601,12605,12609,12701,12705,12709,12901,12905,12909,13001,13005,13009,13101,13105,13109,13201,13205,13209,13301,13305,13309,14301,14305,14601,14701,14705,14801,14809,14901,14905,15001,15005,15101,15105,15201,15205,15301,15305,15401,15405,15501,15505,15605,15607,15609,15611,15613,15615,15701,15703,15705;;5;4;;E} | S8: #FNECTCR{11101,11103,11105,11195,12301,12305,12309,12401,12405,12409,12501,12505,12509,12601,12605,12609,12701,12705,12709,12901,12905,12909,13001,13005,13009,13101,13105,13109,13201,13205,13209,13301,13305,13309,14301,14305,14601,14701,14705,14801,14809,14901,14905,15001,15005,15101,15105,15201,15205,15301,15305,15401,15405,15501,15505,15605,15607,15609,15611,15613,15615,15701,15703,15705;;5;4;;E} | T8: =U8+V8 -> #VALUE! | U8: #FNECTCO{11101,11103,11105,11195,12301,12305,12309,12401,12405,12409,12501,12505,12509,12601,12605,12609,12701,12705,12709,12901,12905,12909,13001,13005,13009,13101,13105,13109,13201,13205,13209,13301,13305,13309,14301,14305,14601,14701,14705,14801,14809,14901,14905,15001,15005,15101,15105,15201,15205,15301,15305,15401,15405,15501,15505,15605,15607,15609,15611,15613,15615,15701,15703,15705;;5;5;;E} | V8: #FNECTCOP{11101,11103,11105,11195,12301,12305,12309,12401,12405,12409,12501,12505,12509,12601,12605,12609,12701,12705,12709,12901,12905,12909,13001,13005,13009,13101,13105,13109,13201,13205,13209,13301,13305,13309,14301,14305,14601,14701,14705,14801,14809,14901,14905,15001,15005,15101,15105,15201,15205,15301,15305,15401,15405,15501,15505,15605,15607,15609,15611,15613,15615,15701,15703,15705;;5;5;;E} | W8: #FNECTCR{11101,11103,11105,11195,12301,12305,12309,12401,12405,12409,12501,12505,12509,12601,12605,12609,12701,12705,12709,12901,12905,12909,13001,13005,13009,13101,13105,13109,13201,13205,13209,13301,13305,13309,14301,14305,14601,14701,14705,14801,14809,14901,14905,15001,15005,15101,15105,15201,15205,15301,15305,15401,15405,15501,15505,15605,15607,15609,15611,15613,15615,15701,15703,15705;;5;5;;E} | X8: =W8+S8+O8+K8+G8 -> #VALUE! | Z8: =D8+H8+L8+P8+T8 -> #VALUE! | AA8: =E8+I8+M8+Q8+U8 -> #VALUE! | AB8: =F8+J8+N8+R8+V8 -> #VALUE! | AD8: =C8-Z8 -> #VALUE!
A9: 4 | B9: Строительство | C9: ='Aging Analysis'!C30 -> #VALUE! | D9: =E9+F9 -> #VALUE! | E9: #FNECTCO{11101,11103,11105,11195,12301,12305,12309,12401,12405,12409,12501,12505,12509,12601,12605,12609,12701,12705,12709,12901,12905,12909,13001,13005,13009,13101,13105,13109,13201,13205,13209,13301,13305,13309,14301,14305,14601,14701,14705,14801,14809,14901,14905,15001,15005,15101,15105,15201,15205,15301,15305,15401,15405,15501,15505,15605,15607,15609,15611,15613,15615,15701,15703,15705;;6;1;;E} | F9: #FNECTCOP{11101,11103,11105,11195,12301,12305,12309,12401,12405,12409,12501,12505,12509,12601,12605,12609,12701,12705,12709,12901,12905,12909,13001,13005,13009,13101,13105,13109,13201,13205,13209,13301,13305,13309,14301,14305,14601,14701,14705,14801,14809,14901,14905,15001,15005,15101,15105,15201,15205,15301,15305,15401,15405,15501,15505,15605,15607,15609,15611,15613,15615,15701,15703,15705;;6;1;;E} | G9: #FNECTCR{11101,11103,11105,11195,12301,12305,12309,12401,12405,12409,12501,12505,12509,12601,12605,12609,12701,12705,12709,12901,12905,12909,13001,13005,13009,13101,13105,13109,13201,13205,13209,13301,13305,13309,14301,14305,14601,14701,14705,14801,14809,14901,14905,15001,15005,15101,15105,15201,15205,15301,15305,15401,15405,15501,15505,15605,15607,15609,15611,15613,15615,15701,15703,15705;;6;1;;E} | H9: =I9+J9 -> #VALUE! | I9: #FNECTCO{11101,11103,11105,11195,12301,12305,12309,12401,12405,12409,12501,12505,12509,12601,12605,12609,12701,12705,12709,12901,12905,12909,13001,13005,13009,13101,13105,13109,13201,13205,13209,13301,13305,13309,14301,14305,14601,14701,14705,14801,14809,14901,14905,15001,15005,15101,15105,15201,15205,15301,15305,15401,15405,15501,15505,15605,15607,15609,15611,15613,15615,15701,15703,15705;;6;2;;E} | J9: #FNECTCOP{11101,11103,11105,11195,12301,12305,12309,12401,12405,12409,12501,12505,12509,12601,12605,12609,12701,12705,12709,12901,12905,12909,13001,13005,13009,13101,13105,13109,13201,13205,13209,13301,13305,13309,14301,14305,14601,14701,14705,14801,14809,14901,14905,15001,15005,15101,15105,15201,15205,15301,15305,15401,15405,15501,15505,15605,15607,15609,15611,15613,15615,15701,15703,15705;;6;2;;E} | K9: #FNECTCR{11101,11103,11105,11195,12301,12305,12309,12401,12405,12409,12501,12505,12509,12601,12605,12609,12701,12705,12709,12901,12905,12909,13001,13005,13009,13101,13105,13109,13201,13205,13209,13301,13305,13309,14301,14305,14601,14701,14705,14801,14809,14901,14905,15001,15005,15101,15105,15201,15205,15301,15305,15401,15405,15501,15505,15605,15607,15609,15611,15613,15615,15701,15703,15705;;6;2;;E} | L9: =M9+N9 -> #VALUE! | M9: #FNECTCO{11101,11103,11105,11195,12301,12305,12309,12401,12405,12409,12501,12505,12509,12601,12605,12609,12701,12705,12709,12901,12905,12909,13001,13005,13009,13101,13105,13109,13201,13205,13209,13301,13305,13309,14301,14305,14601,14701,14705,14801,14809,14901,14905,15001,15005,15101,15105,15201,15205,15301,15305,15401,15405,15501,15505,15605,15607,15609,15611,15613,15615,15701,15703,15705;;6;3;;E} | N9: #FNECTCOP{11101,11103,11105,11195,12301,12305,12309,12401,12405,12409,12501,12505,12509,12601,12605,12609,12701,12705,12709,12901,12905,12909,13001,13005,13009,13101,13105,13109,13201,13205,13209,13301,13305,13309,14301,14305,14601,14701,14705,14801,14809,14901,14905,15001,15005,15101,15105,15201,15205,15301,15305,15401,15405,15501,15505,15605,15607,15609,15611,15613,15615,15701,15703,15705;;6;3;;E} | O9: #FNECTCR{11101,11103,11105,11195,12301,12305,12309,12401,12405,12409,12501,12505,12509,12601,12605,12609,12701,12705,12709,12901,12905,12909,13001,13005,13009,13101,13105,13109,13201,13205,13209,13301,13305,13309,14301,14305,14601,14701,14705,14801,14809,14901,14905,15001,15005,15101,15105,15201,15205,15301,15305,15401,15405,15501,15505,15605,15607,15609,15611,15613,15615,15701,15703,15705;;6;3;;E} | P9: =Q9+R9 -> #VALUE! | Q9: #FNECTCOP{11101,11103,11105,11195,12301,12305,12309,12401,12405,12409,12501,12505,12509,12601,12605,12609,12701,12705,12709,12901,12905,12909,13001,13005,13009,13101,13105,13109,13201,13205,13209,13301,13305,13309,14301,14305,14601,14701,14705,14801,14809,14901,14905,15001,15005,15101,15105,15201,15205,15301,15305,15401,15405,15501,15505,15605,15607,15609,15611,15613,15615,15701,15703,15705;;6;4;;E} | R9: #FNECTCO{11101,11103,11105,11195,12301,12305,12309,12401,12405,12409,12501,12505,12509,12601,12605,12609,12701,12705,12709,12901,12905,12909,13001,13005,13009,13101,13105,13109,13201,13205,13209,13301,13305,13309,14301,14305,14601,14701,14705,14801,14809,14901,14905,15001,15005,15101,15105,15201,15205,15301,15305,15401,15405,15501,15505,15605,15607,15609,15611,15613,15615,15701,15703,15705;;6;4;;E} | S9: #FNECTCR{11101,11103,11105,11195,12301,12305,12309,12401,12405,12409,12501,12505,12509,12601,12605,12609,12701,12705,12709,12901,12905,12909,13001,13005,13009,13101,13105,13109,13201,13205,13209,13301,13305,13309,14301,14305,14601,14701,14705,14801,14809,14901,14905,15001,15005,15101,15105,15201,15205,15301,15305,15401,15405,15501,15505,15605,15607,15609,15611,15613,15615,15701,15703,15705;;6;4;;E} | T9: =U9+V9 -> #VALUE! | U9: #FNECTCO{11101,11103,11105,11195,12301,12305,12309,12401,12405,12409,12501,12505,12509,12601,12605,12609,12701,12705,12709,12901,12905,12909,13001,13005,13009,13101,13105,13109,13201,13205,13209,13301,13305,13309,14301,14305,14601,14701,14705,14801,14809,14901,14905,15001,15005,15101,15105,15201,15205,15301,15305,15401,15405,15501,15505,15605,15607,15609,15611,15613,15615,15701,15703,15705;;6;5;;E} | V9: #FNECTCOP{11101,11103,11105,11195,12301,12305,12309,12401,12405,12409,12501,12505,12509,12601,12605,12609,12701,12705,12709,12901,12905,12909,13001,13005,13009,13101,13105,13109,13201,13205,13209,13301,13305,13309,14301,14305,14601,14701,14705,14801,14809,14901,14905,15001,15005,15101,15105,15201,15205,15301,15305,15401,15405,15501,15505,15605,15607,15609,15611,15613,15615,15701,15703,15705;;6;5;;E} | W9: #FNECTCR{11101,11103,11105,11195,12301,12305,12309,12401,12405,12409,12501,12505,12509,12601,12605,12609,12701,12705,12709,12901,12905,12909,13001,13005,13009,13101,13105,13109,13201,13205,13209,13301,13305,13309,14301,14305,14601,14701,14705,14801,14809,14901,14905,15001,15005,15101,15105,15201,15205,15301,15305,15401,15405,15501,15505,15605,15607,15609,15611,15613,15615,15701,15703,15705;;6;5;;E} | X9: =W9+S9+O9+K9+G9 -> #VALUE! | Z9: =D9+H9+L9+P9+T9 -> #VALUE! | AA9: =E9+I9+M9+Q9+U9 -> #VALUE! | AB9: =F9+J9+N9+R9+V9 -> #VALUE! | AD9: =C9-Z9 -> #VALUE!
A10: 5 | B10: Торговля и сфера общественных услуг | C10: ='Aging Analysis'!C31 -> #VALUE! | D10: =E10+F10 -> #VALUE! | E10: #FNECTCO{11101,11103,11105,11195,12301,12305,12309,12401,12405,12409,12501,12505,12509,12601,12605,12609,12701,12705,12709,12901,12905,12909,13001,13005,13009,13101,13105,13109,13201,13205,13209,13301,13305,13309,14301,14305,14601,14701,14705,14801,14809,14901,14905,15001,15005,15101,15105,15201,15205,15301,15305,15401,15405,15501,15505,15605,15607,15609,15611,15613,15615,15701,15703,15705;;7;1;;E} | F10: #FNECTCOP{11101,11103,11105,11195,12301,12305,12309,12401,12405,12409,12501,12505,12509,12601,12605,12609,12701,12705,12709,12901,12905,12909,13001,13005,13009,13101,13105,13109,13201,13205,13209,13301,13305,13309,14301,14305,14601,14701,14705,14801,14809,14901,14905,15001,15005,15101,15105,15201,15205,15301,15305,15401,15405,15501,15505,15605,15607,15609,15611,15613,15615,15701,15703,15705;;7;1;;E} | G10: #FNECTCR{11101,11103,11105,11195,12301,12305,12309,12401,12405,12409,12501,12505,12509,12601,12605,12609,12701,12705,12709,12901,12905,12909,13001,13005,13009,13101,13105,13109,13201,13205,13209,13301,13305,13309,14301,14305,14601,14701,14705,14801,14809,14901,14905,15001,15005,15101,15105,15201,15205,15301,15305,15401,15405,15501,15505,15605,15607,15609,15611,15613,15615,15701,15703,15705;;7;1;;E} | H10: =I10+J10 -> #VALUE! | I10: #FNECTCO{11101,11103,11105,11195,12301,12305,12309,12401,12405,12409,12501,12505,12509,12601,12605,12609,12701,12705,12709,12901,12905,12909,13001,13005,13009,13101,13105,13109,13201,13205,13209,13301,13305,13309,14301,14305,14601,14701,14705,14801,14809,14901,14905,15001,15005,15101,15105,15201,15205,15301,15305,15401,15405,15501,15505,15605,15607,15609,15611,15613,15615,15701,15703,15705;;7;2;;E} | J10: #FNECTCOP{11101,11103,11105,11195,12301,12305,12309,12401,12405,12409,12501,12505,12509,12601,12605,12609,12701,12705,12709,12901,12905,12909,13001,13005,13009,13101,13105,13109,13201,13205,13209,13301,13305,13309,14301,14305,14601,14701,14705,14801,14809,14901,14905,15001,15005,15101,15105,15201,15205,15301,15305,15401,15405,15501,15505,15605,15607,15609,15611,15613,15615,15701,15703,15705;;7;2;;E} | K10: #FNECTCR{11101,11103,11105,11195,12301,12305,12309,12401,12405,12409,12501,12505,12509,12601,12605,12609,12701,12705,12709,12901,12905,12909,13001,13005,13009,13101,13105,13109,13201,13205,13209,13301,13305,13309,14301,14305,14601,14701,14705,14801,14809,14901,14905,15001,15005,15101,15105,15201,15205,15301,15305,15401,15405,15501,15505,15605,15607,15609,15611,15613,15615,15701,15703,15705;;7;2;;E} | L10: =M10+N10 -> #VALUE! | M10: #FNECTCO{11101,11103,11105,11195,12301,12305,12309,12401,12405,12409,12501,12505,12509,12601,12605,12609,12701,12705,12709,12901,12905,12909,13001,13005,13009,13101,13105,13109,13201,13205,13209,13301,13305,13309,14301,14305,14601,14701,14705,14801,14809,14901,14905,15001,15005,15101,15105,15201,15205,15301,15305,15401,15405,15501,15505,15605,15607,15609,15611,15613,15615,15701,15703,15705;;7;3;;E} | N10: #FNECTCOP{11101,11103,11105,11195,12301,12305,12309,12401,12405,12409,12501,12505,12509,12601,12605,12609,12701,12705,12709,12901,12905,12909,13001,13005,13009,13101,13105,13109,13201,13205,13209,13301,13305,13309,14301,14305,14601,14701,14705,14801,14809,14901,14905,15001,15005,15101,15105,15201,15205,15301,15305,15401,15405,15501,15505,15605,15607,15609,15611,15613,15615,15701,15703,15705;;7;3;;E} | O10: #FNECTCR{11101,11103,11105,11195,12301,12305,12309,12401,12405,12409,12501,12505,12509,12601,12605,12609,12701,12705,12709,12901,12905,12909,13001,13005,13009,13101,13105,13109,13201,13205,13209,13301,13305,13309,14301,14305,14601,14701,14705,14801,14809,14901,14905,15001,15005,15101,15105,15201,15205,15301,15305,15401,15405,15501,15505,15605,15607,15609,15611,15613,15615,15701,15703,15705;;7;3;;E} | P10: =Q10+R10 -> #VALUE! | Q10: #FNECTCOP{11101,11103,11105,11195,12301,12305,12309,12401,12405,12409,12501,12505,12509,12601,12605,12609,12701,12705,12709,12901,12905,12909,13001,13005,13009,13101,13105,13109,13201,13205,13209,13301,13305,13309,14301,14305,14601,14701,14705,14801,14809,14901,14905,15001,15005,15101,15105,15201,15205,15301,15305,15401,15405,15501,15505,15605,15607,15609,15611,15613,15615,15701,15703,15705;;7;4;;E} | R10: #FNECTCO{11101,11103,11105,11195,12301,12305,12309,12401,12405,12409,12501,12505,12509,12601,12605,12609,12701,12705,12709,12901,12905,12909,13001,13005,13009,13101,13105,13109,13201,13205,13209,13301,13305,13309,14301,14305,14601,14701,14705,14801,14809,14901,14905,15001,15005,15101,15105,15201,15205,15301,15305,15401,15405,15501,15505,15605,15607,15609,15611,15613,15615,15701,15703,15705;;7;4;;E} | S10: #FNECTCR{11101,11103,11105,11195,12301,12305,12309,12401,12405,12409,12501,12505,12509,12601,12605,12609,12701,12705,12709,12901,12905,12909,13001,13005,13009,13101,13105,13109,13201,13205,13209,13301,13305,13309,14301,14305,14601,14701,14705,14801,14809,14901,14905,15001,15005,15101,15105,15201,15205,15301,15305,15401,15405,15501,15505,15605,15607,15609,15611,15613,15615,15701,15703,15705;;7;4;;E} | T10: =U10+V10 -> #VALUE! | U10: #FNECTCO{11101,11103,11105,11195,12301,12305,12309,12401,12405,12409,12501,12505,12509,12601,12605,12609,12701,12705,12709,12901,12905,12909,13001,13005,13009,13101,13105,13109,13201,13205,13209,13301,13305,13309,14301,14305,14601,14701,14705,14801,14809,14901,14905,15001,15005,15101,15105,15201,15205,15301,15305,15401,15405,15501,15505,15605,15607,15609,15611,15613,15615,15701,15703,15705;;7;5;;E} | V10: #FNECTCOP{11101,11103,11105,11195,12301,12305,12309,12401,12405,12409,12501,12505,12509,12601,12605,12609,12701,12705,12709,12901,12905,12909,13001,13005,13009,13101,13105,13109,13201,13205,13209,13301,13305,13309,14301,14305,14601,14701,14705,14801,14809,14901,14905,15001,15005,15101,15105,15201,15205,15301,15305,15401,15405,15501,15505,15605,15607,15609,15611,15613,15615,15701,15703,15705;;7;5;;E} | W10: #FNECTCR{11101,11103,11105,11195,12301,12305,12309,12401,12405,12409,12501,12505,12509,12601,12605,12609,12701,12705,12709,12901,12905,12909,13001,13005,13009,13101,13105,13109,13201,13205,13209,13301,13305,13309,14301,14305,14601,14701,14705,14801,14809,14901,14905,15001,15005,15101,15105,15201,15205,15301,15305,15401,15405,15501,15505,15605,15607,15609,15611,15613,15615,15701,15703,15705;;7;5;;E} | X10: =W10+S10+O10+K10+G10 -> #VALUE! | Z10: =D10+H10+L10+P10+T10 -> #VALUE! | AA10: =E10+I10+M10+Q10+U10 -> #VALUE! | AB10: =F10+J10+N10+R10+V10 -> #VALUE! | AD10: =C10-Z10 -> #VALUE!
